Workbook

Sheet Lisez-moi
A1: ARMEMENT01 · Catalogue complet (12 onglets) · contrat v0.3 + jalon ARMEMENT01.2
A2: 82 archétypes · 1640 versions immuables · vrais dés RPG · données historiques conservées
A4: Objet | B4: Ce classeur décrit 82 archétypes d'armes, de focaliseurs et de boucliers; ce ne sont PAS 82 DataAssets UE5 déjà créés.
A5: Onglet Catalogue | B5: Identité par famille : type, dégâts niveau 1, coût PA, portée, poids, attribut, bonus précision et rôle tactique.
A6: Onglet Niveaux 1-20 | B6: 82 archétypes × 20 versions de butin. Jet de dégâts = NdM + K, dés d4/d6/d8/d10/d12/d20; les plages Min/Max sont une conséquence.
A7: Onglet Raretés | B7: Commun gris, Rare vert, Épique bleu, Légendaire violet, Unique doré. Aucun bonus WD de rareté automatique.
A8: Onglet Classes | B8: 6 classes et 18 spécialités canoniques; préférences de gameplay, non restrictions absolues.
A9: Onglet Améliorations | B9: Forge sans gain de niveau, alchimie temporaire, runes permanentes. FOR02/FOR03/FOR07 corrigées selon ARM-001.
A10: Onglet Uniques | B10: Exemples d'objets nommés, avec effet prédéfini et acquisition scénarisée.
A11: Onglet Paramètres | B11: Courbe indicative (k1/k2) pour orienter l'équilibrage; ne régénère pas les dés sans re-authoring explicite.
A12: Onglet Implémentation UE5 | B12: Paramètres de progression à la création de l'objet (niveau fixe), plus paramètres proposés de sous-niveau.
A13: ATTENTION | B13: Valeurs indicatives de game design. À calibrer contre PV/armures monstres, 4 PA/tour, critique, WD et difficulté réelle.
A14: Courbe d'équilibrage | B14: La courbe k1/k2 sert uniquement de cible de comparaison (colonnes Q:R). Les profils de dés M:N:O sont authorés et fixes pour chaque version de butin.
A15: Références | B15: ARMEMENT01_Contrat_Armement_v0_3.md (design) ; ARMEMENT01_2_CONTRAT_TECHNIQUE_MULTIDES.md (contrat technique).
... A26: Contrôles de données | B26: Dans 'Niveaux 1-20', colonnes T:V vérifient faces autorisées, bornes et moyenne de chaque profil sans modifier A:S.

Sheet Catalogue
A1: Catalogue d'armement
A2: Une ligne = un ARCHÉTYPE. E/F sont les CIBLES historiques N1, non les dégâts authorés; la source des dégâts jouables est la table des vrais dés par niveau.
A3: ID | B3: Nom | C3: Famille | D3: Tenue | E3: Min cible N1 | F3: Max cible N1 | G3: Arm phys N1 | H3: Arm mag N1 | I3: PA | J3: Portée cases | K3: Poids kg | L3: Précision | M3: Attribut | N3: Dégâts | O3: Sous-type | P3: Classe principale | Q3: Classes secondaires | R3: Particularité | S3: Tags proposés | T3: Dés N1 réels (voir versions)
A4: ARM001 | B4: Dague | C4: Légères | D4: 1 main | E4: 2 | F4: 4 | G4: 0 | H4: 0 | I4: 2 | J4: 1 | K4: 0.4 | L4: 1 | M4: Dextérité | N4: Physical | O4: Slashing | P4: Voleur | Q4: Rôdeur / Alchimiste | R4: Polyvalente, double arme | S4: Weapon.Light | T4: 1d4
A5: ARM002 | B5: Poignard d'assassin | C5: Légères | D5: 1 main | E5: 2 | F5: 3 | G5: 0 | H5: 0 | I5: 2 | J5: 1 | K5: 0.3 | L5: 2 | M5: Dextérité | N5: Physical | O5: Piercing | P5: Voleur | Q5: Rôdeur / Alchimiste | R5: Critique conditionnel depuis l'ombre | S5: Weapon.Light | T5: 1d4
A6: ARM003 | B6: Stylet | C6: Légères | D6: 1 main | E6: 1 | F6: 4 | G6: 0 | H6: 0 | I6: 2 | J6: 1 | K6: 0.25 | L6: 1 | M6: Dextérité | N6: Physical | O6: Piercing | P6: Voleur | Q6: Rôdeur / Alchimiste | R6: Perforation ciblée | S6: Weapon.Light | T6: 1d4
A7: ARM004 | B7: Kriss | C7: Légères | D7: 1 main | E7: 2 | F7: 4 | G7: 0 | H7: 0 | I7: 2 | J7: 1 | K7: 0.5 | L7: 0 | M7: Dextérité | N7: Physical | O7: Slashing | P7: Voleur | Q7: Rôdeur / Alchimiste | R7: Saigne sur coup critique | S7: Weapon.Light | T7: 1d4
A8: ARM005 | B8: Couteau de chasse | C8: Légères | D8: 1 main | E8: 2 | F8: 4 | G8: 0 | H8: 0 | I8: 2 | J8: 1 | K8: 0.5 | L8: 0 | M8: Dextérité | N8: Physical | O8: Slashing | P8: Voleur | Q8: Rôdeur / Alchimiste | R8: Chasse et utilitaire | S8: Weapon.Light | T8: 1d4
A9: ARM006 | B9: Épée courte | C9: Légères | D9: 1 main | E9: 3 | F9: 5 | G9: 0 | H9: 0 | I9: 2 | J9: 1 | K9: 1 | L9: 0 | M9: Dextérité | N9: Physical | O9: Slashing | P9: Voleur | Q9: Rôdeur / Alchimiste | R9: Bon compromis | S9: Weapon.Light | T9: 1d4 + 1
A10: ARM007 | B10: Rapière | C10: Légères | D10: 1 main | E10: 2 | F10: 5 | G10: 0 | H10: 0 | I10: 2 | J10: 1 | K10: 1 | L10: 1 | M10: Dextérité | N10: Physical | O10: Piercing | P10: Voleur | Q10: Rôdeur / Alchimiste | R10: Parade et précision | S10: Weapon.Light | T10: 1d4 + 1
A11: ARM008 | B11: Sabre léger | C11: Légères | D11: 1 main | E11: 3 | F11: 5 | G11: 0 | H11: 0 | I11: 2 | J11: 1 | K11: 1.1 | L11: 0 | M11: Dextérité | N11: Physical | O11: Slashing | P11: Voleur | Q11: Rôdeur / Alchimiste | R11: Mobilité | S11: Weapon.Light | T11: 1d4 + 1
A12: ARM009 | B12: Cimeterre court | C12: Légères | D12: 1 main | E12: 3 | F12: 5 | G12: 0 | H12: 0 | I12: 2 | J12: 1 | K12: 1.2 | L12: 0 | M12: Dextérité | N12: Physical | O12: Slashing | P12: Voleur | Q12: Rôdeur / Alchimiste | R12: Tranchant | S12: Weapon.Light | T12: 1d4 + 1
A13: ARM010 | B13: Hachette | C13: Légères | D13: 1 main | E13: 3 | F13: 5 | G13: 0 | H13: 0 | I13: 2 | J13: 1 | K13: 1.1 | L13: -1 | M13: Dextérité | N13: Physical | O13: Slashing | P13: Voleur | Q13: Rôdeur / Alchimiste | R13: Peut être lancée selon version | S13: Weapon.Light | T13: 1d4 + 1
A14: ARM011 | B14: Serpe | C14: Légères | D14: 1 main | E14: 2 | F14: 4 | G14: 0 | H14: 0 | I14: 2 | J14: 1 | K14: 0.7 | L14: 0 | M14: Dextérité | N14: Physical | O14: Slashing | P14: Voleur | Q14: Rôdeur / Alchimiste | R14: Affinité poison | S14: Weapon.Light | T14: 1d4
A15: ARM012 | B15: Gourdin léger | C15: Légères | D15: 1 main | E15: 2 | F15: 4 | G15: 0 | H15: 0 | I15: 2 | J15: 1 | K15: 0.8 | L15: 0 | M15: Dextérité | N15: Physical | O15: Bludgeoning | P15: Voleur | Q15: Rôdeur / Alchimiste | R15: Contondant discret | S15: Weapon.Light | T15: 1d4
... A85: ARM082 | B85: Bouclier runique | C85: Boucliers | D85: Secondaire | E85: 0 | F85: 0 | G85: 4 | H85: 4 | I85: 0 | J85: 0 | K85: 3.5 | L85: 0 | M85: Constitution | N85: Physical | O85: Bludgeoning | P85: Guerrier | Q85: Prêtre / Mage | R85: Protection magique | S85: Equipment.Shield | T85: —

Sheet Niveaux 1-20
A1: ARMEMENT01 · Versions fixes niveau 1–20 — DÉS RPG CLASSIQUES
A2: Chaque profil offensif définit ses vrais dés : d4, d6, d8, d10, d12, d20. Plusieurs dés sont additionnés. Les moyennes cibles Q:S servent à l'équilibrage, PAS au tirage.
A3: ID | B3: Arme / bouclier | C3: Niveau OBJET | D3: Famille | E3: Dégâts min | F3: Dégâts max | G3: Arm. physique | H3: Arm. magique | I3: Coût PA | J3: Portée | K3: Poids kg | L3: Dégâts moyens | M3: Nb dés | N3: Faces officielles | O3: Constante | P3: Jet de dégâts (réel) | Q3: Min cible (courbe) | R3: Max cible (courbe) | S3: Écart de moyenne | T3: Profil dés valide | U3: Moyenne dérivée des dés | V3: Moyenne conforme
A4: ARM001 | B4: Dague | C4: 1 | D4: Légères | E4: =IF(M4=0,0,M4+O4) -> 1 | F4: =IF(M4=0,0,M4*N4+O4) -> 4 | G4: =ROUND(Catalogue!G4*SQRT((1+Paramètres!$B$4*(C4-1)+Paramètres!$B$5*(C4-1)^2)),0) -> 0 | H4: =ROUND(Catalogue!H4*SQRT((1+Paramètres!$B$4*(C4-1)+Paramètres!$B$5*(C4-1)^2)),0) -> 0 | I4: 2 | J4: 1 | K4: 0.4 | L4: =IF(M4=0,0,(E4+F4)/2) -> 2.5 | M4: 1 | N4: 4 | O4: 0 | P4: =IF(M4=0,"—",M4&"d"&N4&IF(O4=0,""," + "&O4)) -> 1d4 | Q4: =ROUND(INDEX(Catalogue!E$4:E$85,MATCH(A4,Catalogue!A$4:A$85,0))*(1+Paramètres!$B$4*(C4-1)+Paramètres!$B$5*(C4-1)^2),0) -> 2 | R4: =ROUND(INDEX(Catalogue!F$4:F$85,MATCH(A4,Catalogue!A$4:A$85,0))*(1+Paramètres!$B$4*(C4-1)+Paramètres!$B$5*(C4-1)^2),0) -> 4 | S4: =L4-AVERAGE(Q4:R4) -> -0.5 | T4: =IF(M4=0,IF(AND(N4=0,O4=0,E4=0,F4=0),"OK","ERREUR"),IF(AND(M4>=1,M4<=32,OR(N4=4,N4=6,N4=8,N4=10,N4=12,N4=20),O4>=0,E4=M4+O4,F4=M4*N4+O4),"OK","ERREUR")) -> OK | U4: =IF(M4>0,M4*(N4+1)/2+O4,0) -> 2.5 | V4: =IF(ABS(L4-U4)<0.001,"OK","ERREUR") -> OK
A5: ARM001 | B5: Dague | C5: 2 | D5: Légères | E5: =IF(M5=0,0,M5+O5) -> 2 | F5: =IF(M5=0,0,M5*N5+O5) -> 5 | G5: =ROUND(Catalogue!G4*SQRT((1+Paramètres!$B$4*(C5-1)+Paramètres!$B$5*(C5-1)^2)),0) -> 0 | H5: =ROUND(Catalogue!H4*SQRT((1+Paramètres!$B$4*(C5-1)+Paramètres!$B$5*(C5-1)^2)),0) -> 0 | I5: 2 | J5: 1 | K5: 0.4 | L5: =IF(M5=0,0,(E5+F5)/2) -> 3.5 | M5: 1 | N5: 4 | O5: 1 | P5: =IF(M5=0,"—",M5&"d"&N5&IF(O5=0,""," + "&O5)) -> 1d4 + 1 | Q5: =ROUND(INDEX(Catalogue!E$4:E$85,MATCH(A5,Catalogue!A$4:A$85,0))*(1+Paramètres!$B$4*(C5-1)+Paramètres!$B$5*(C5-1)^2),0) -> 2 | R5: =ROUND(INDEX(Catalogue!F$4:F$85,MATCH(A5,Catalogue!A$4:A$85,0))*(1+Paramètres!$B$4*(C5-1)+Paramètres!$B$5*(C5-1)^2),0) -> 5 | S5: =L5-AVERAGE(Q5:R5) -> 0 | T5: =IF(M5=0,IF(AND(N5=0,O5=0,E5=0,F5=0),"OK","ERREUR"),IF(AND(M5>=1,M5<=32,OR(N5=4,N5=6,N5=8,N5=10,N5=12,N5=20),O5>=0,E5=M5+O5,F5=M5*N5+O5),"OK","ERREUR")) -> OK | U5: =IF(M5>0,M5*(N5+1)/2+O5,0) -> 3.5 | V5: =IF(ABS(L5-U5)<0.001,"OK","ERREUR") -> OK
A6: ARM001 | B6: Dague | C6: 3 | D6: Légères | E6: =IF(M6=0,0,M6+O6) -> 2 | F6: =IF(M6=0,0,M6*N6+O6) -> 5 | G6: =ROUND(Catalogue!G4*SQRT((1+Paramètres!$B$4*(C6-1)+Paramètres!$B$5*(C6-1)^2)),0) -> 0 | H6: =ROUND(Catalogue!H4*SQRT((1+Paramètres!$B$4*(C6-1)+Paramètres!$B$5*(C6-1)^2)),0) -> 0 | I6: 2 | J6: 1 | K6: 0.4 | L6: =IF(M6=0,0,(E6+F6)/2) -> 3.5 | M6: 1 | N6: 4 | O6: 1 | P6: =IF(M6=0,"—",M6&"d"&N6&IF(O6=0,""," + "&O6)) -> 1d4 + 1 | Q6: =ROUND(INDEX(Catalogue!E$4:E$85,MATCH(A6,Catalogue!A$4:A$85,0))*(1+Paramètres!$B$4*(C6-1)+Paramètres!$B$5*(C6-1)^2),0) -> 3 | R6: =ROUND(INDEX(Catalogue!F$4:F$85,MATCH(A6,Catalogue!A$4:A$85,0))*(1+Paramètres!$B$4*(C6-1)+Paramètres!$B$5*(C6-1)^2),0) -> 5 | S6: =L6-AVERAGE(Q6:R6) -> -0.5 | T6: =IF(M6=0,IF(AND(N6=0,O6=0,E6=0,F6=0),"OK","ERREUR"),IF(AND(M6>=1,M6<=32,OR(N6=4,N6=6,N6=8,N6=10,N6=12,N6=20),O6>=0,E6=M6+O6,F6=M6*N6+O6),"OK","ERREUR")) -> OK | U6: =IF(M6>0,M6*(N6+1)/2+O6,0) -> 3.5 | V6: =IF(ABS(L6-U6)<0.001,"OK","ERREUR") -> OK
A7: ARM001 | B7: Dague | C7: 4 | D7: Légères | E7: =IF(M7=0,0,M7+O7) -> 3 | F7: =IF(M7=0,0,M7*N7+O7) -> 6 | G7: =ROUND(Catalogue!G4*SQRT((1+Paramètres!$B$4*(C7-1)+Paramètres!$B$5*(C7-1)^2)),0) -> 0 | H7: =ROUND(Catalogue!H4*SQRT((1+Paramètres!$B$4*(C7-1)+Paramètres!$B$5*(C7-1)^2)),0) -> 0 | I7: 2 | J7: 1 | K7: 0.4 | L7: =IF(M7=0,0,(E7+F7)/2) -> 4.5 | M7: 1 | N7: 4 | O7: 2 | P7: =IF(M7=0,"—",M7&"d"&N7&IF(O7=0,""," + "&O7)) -> 1d4 + 2 | Q7: =ROUND(INDEX(Catalogue!E$4:E$85,MATCH(A7,Catalogue!A$4:A$85,0))*(1+Paramètres!$B$4*(C7-1)+Paramètres!$B$5*(C7-1)^2),0) -> 3 | R7: =ROUND(INDEX(Catalogue!F$4:F$85,MATCH(A7,Catalogue!A$4:A$85,0))*(1+Paramètres!$B$4*(C7-1)+Paramètres!$B$5*(C7-1)^2),0) -> 6 | S7: =L7-AVERAGE(Q7:R7) -> 0 | T7: =IF(M7=0,IF(AND(N7=0,O7=0,E7=0,F7=0),"OK","ERREUR"),IF(AND(M7>=1,M7<=32,OR(N7=4,N7=6,N7=8,N7=10,N7=12,N7=20),O7>=0,E7=M7+O7,F7=M7*N7+O7),"OK","ERREUR")) -> OK | U7: =IF(M7>0,M7*(N7+1)/2+O7,0) -> 4.5 | V7: =IF(ABS(L7-U7)<0.001,"OK","ERREUR") -> OK
A8: ARM001 | B8: Dague | C8: 5 | D8: Légères | E8: =IF(M8=0,0,M8+O8) -> 3 | F8: =IF(M8=0,0,M8*N8+O8) -> 6 | G8: =ROUND(Catalogue!G4*SQRT((1+Paramètres!$B$4*(C8-1)+Paramètres!$B$5*(C8-1)^2)),0) -> 0 | H8: =ROUND(Catalogue!H4*SQRT((1+Paramètres!$B$4*(C8-1)+Paramètres!$B$5*(C8-1)^2)),0) -> 0 | I8: 2 | J8: 1 | K8: 0.4 | L8: =IF(M8=0,0,(E8+F8)/2) -> 4.5 | M8: 1 | N8: 4 | O8: 2 | P8: =IF(M8=0,"—",M8&"d"&N8&IF(O8=0,""," + "&O8)) -> 1d4 + 2 | Q8: =ROUND(INDEX(Catalogue!E$4:E$85,MATCH(A8,Catalogue!A$4:A$85,0))*(1+Paramètres!$B$4*(C8-1)+Paramètres!$B$5*(C8-1)^2),0) -> 3 | R8: =ROUND(INDEX(Catalogue!F$4:F$85,MATCH(A8,Catalogue!A$4:A$85,0))*(1+Paramètres!$B$4*(C8-1)+Paramètres!$B$5*(C8-1)^2),0) -> 7 | S8: =L8-AVERAGE(Q8:R8) -> -0.5 | T8: =IF(M8=0,IF(AND(N8=0,O8=0,E8=0,F8=0),"OK","ERREUR"),IF(AND(M8>=1,M8<=32,OR(N8=4,N8=6,N8=8,N8=10,N8=12,N8=20),O8>=0,E8=M8+O8,F8=M8*N8+O8),"OK","ERREUR")) -> OK | U8: =IF(M8>0,M8*(N8+1)/2+O8,0) -> 4.5 | V8: =IF(ABS(L8-U8)<0.001,"OK","ERREUR") -> OK
A9: ARM001 | B9: Dague | C9: 6 | D9: Légères | E9: =IF(M9=0,0,M9+O9) -> 4 | F9: =IF(M9=0,0,M9*N9+O9) -> 7 | G9: =ROUND(Catalogue!G4*SQRT((1+Paramètres!$B$4*(C9-1)+Paramètres!$B$5*(C9-1)^2)),0) -> 0 | H9: =ROUND(Catalogue!H4*SQRT((1+Paramètres!$B$4*(C9-1)+Paramètres!$B$5*(C9-1)^2)),0) -> 0 | I9: 2 | J9: 1 | K9: 0.4 | L9: =IF(M9=0,0,(E9+F9)/2) -> 5.5 | M9: 1 | N9: 4 | O9: 3 | P9: =IF(M9=0,"—",M9&"d"&N9&IF(O9=0,""," + "&O9)) -> 1d4 + 3 | Q9: =ROUND(INDEX(Catalogue!E$4:E$85,MATCH(A9,Catalogue!A$4:A$85,0))*(1+Paramètres!$B$4*(C9-1)+Paramètres!$B$5*(C9-1)^2),0) -> 4 | R9: =ROUND(INDEX(Catalogue!F$4:F$85,MATCH(A9,Catalogue!A$4:A$85,0))*(1+Paramètres!$B$4*(C9-1)+Paramètres!$B$5*(C9-1)^2),0) -> 8 | S9: =L9-AVERAGE(Q9:R9) -> -0.5 | T9: =IF(M9=0,IF(AND(N9=0,O9=0,E9=0,F9=0),"OK","ERREUR"),IF(AND(M9>=1,M9<=32,OR(N9=4,N9=6,N9=8,N9=10,N9=12,N9=20),O9>=0,E9=M9+O9,F9=M9*N9+O9),"OK","ERREUR")) -> OK | U9: =IF(M9>0,M9*(N9+1)/2+O9,0) -> 5.5 | V9: =IF(ABS(L9-U9)<0.001,"OK","ERREUR") -> OK
A10: ARM001 | B10: Dague | C10: 7 | D10: Légères | E10: =IF(M10=0,0,M10+O10) -> 4 | F10: =IF(M10=0,0,M10*N10+O10) -> 9 | G10: =ROUND(Catalogue!G4*SQRT((1+Paramètres!$B$4*(C10-1)+Paramètres!$B$5*(C10-1)^2)),0) -> 0 | H10: =ROUND(Catalogue!H4*SQRT((1+Paramètres!$B$4*(C10-1)+Paramètres!$B$5*(C10-1)^2)),0) -> 0 | I10: 2 | J10: 1 | K10: 0.4 | L10: =IF(M10=0,0,(E10+F10)/2) -> 6.5 | M10: 1 | N10: 6 | O10: 3 | P10: =IF(M10=0,"—",M10&"d"&N10&IF(O10=0,""," + "&O10)) -> 1d6 + 3 | Q10: =ROUND(INDEX(Catalogue!E$4:E$85,MATCH(A10,Catalogue!A$4:A$85,0))*(1+Paramètres!$B$4*(C10-1)+Paramètres!$B$5*(C10-1)^2),0) -> 4 | R10: =ROUND(INDEX(Catalogue!F$4:F$85,MATCH(A10,Catalogue!A$4:A$85,0))*(1+Paramètres!$B$4*(C10-1)+Paramètres!$B$5*(C10-1)^2),0) -> 9 | S10: =L10-AVERAGE(Q10:R10) -> 0 | T10: =IF(M10=0,IF(AND(N10=0,O10=0,E10=0,F10=0),"OK","ERREUR"),IF(AND(M10>=1,M10<=32,OR(N10=4,N10=6,N10=8,N10=10,N10=12,N10=20),O10>=0,E10=M10+O10,F10=M10*N10+O10),"OK","ERREUR")) -> OK | U10: =IF(M10>0,M10*(N10+1)/2+O10,0) -> 6.5 | V10: =IF(ABS(L10-U10)<0.001,"OK","ERREUR") -> OK
A11: ARM001 | B11: Dague | C11: 8 | D11: Légères | E11: =IF(M11=0,0,M11+O11) -> 5 | F11: =IF(M11=0,0,M11*N11+O11) -> 10 | G11: =ROUND(Catalogue!G4*SQRT((1+Paramètres!$B$4*(C11-1)+Paramètres!$B$5*(C11-1)^2)),0) -> 0 | H11: =ROUND(Catalogue!H4*SQRT((1+Paramètres!$B$4*(C11-1)+Paramètres!$B$5*(C11-1)^2)),0) -> 0 | I11: 2 | J11: 1 | K11: 0.4 | L11: =IF(M11=0,0,(E11+F11)/2) -> 7.5 | M11: 1 | N11: 6 | O11: 4 | P11: =IF(M11=0,"—",M11&"d"&N11&IF(O11=0,""," + "&O11)) -> 1d6 + 4 | Q11: =ROUND(INDEX(Catalogue!E$4:E$85,MATCH(A11,Catalogue!A$4:A$85,0))*(1+Paramètres!$B$4*(C11-1)+Paramètres!$B$5*(C11-1)^2),0) -> 5 | R11: =ROUND(INDEX(Catalogue!F$4:F$85,MATCH(A11,Catalogue!A$4:A$85,0))*(1+Paramètres!$B$4*(C11-1)+Paramètres!$B$5*(C11-1)^2),0) -> 10 | S11: =L11-AVERAGE(Q11:R11) -> 0 | T11: =IF(M11=0,IF(AND(N11=0,O11=0,E11=0,F11=0),"OK","ERREUR"),IF(AND(M11>=1,M11<=32,OR(N11=4,N11=6,N11=8,N11=10,N11=12,N11=20),O11>=0,E11=M11+O11,F11=M11*N11+O11),"OK","ERREUR")) -> OK | U11: =IF(M11>0,M11*(N11+1)/2+O11,0) -> 7.5 | V11: =IF(ABS(L11-U11)<0.001,"OK","ERREUR") -> OK
A12: ARM001 | B12: Dague | C12: 9 | D12: Légères | E12: =IF(M12=0,0,M12+O12) -> 6 | F12: =IF(M12=0,0,M12*N12+O12) -> 12 | G12: =ROUND(Catalogue!G4*SQRT((1+Paramètres!$B$4*(C12-1)+Paramètres!$B$5*(C12-1)^2)),0) -> 0 | H12: =ROUND(Catalogue!H4*SQRT((1+Paramètres!$B$4*(C12-1)+Paramètres!$B$5*(C12-1)^2)),0) -> 0 | I12: 2 | J12: 1 | K12: 0.4 | L12: =IF(M12=0,0,(E12+F12)/2) -> 9 | M12: 2 | N12: 4 | O12: 4 | P12: =IF(M12=0,"—",M12&"d"&N12&IF(O12=0,""," + "&O12)) -> 2d4 + 4 | Q12: =ROUND(INDEX(Catalogue!E$4:E$85,MATCH(A12,Catalogue!A$4:A$85,0))*(1+Paramètres!$B$4*(C12-1)+Paramètres!$B$5*(C12-1)^2),0) -> 6 | R12: =ROUND(INDEX(Catalogue!F$4:F$85,MATCH(A12,Catalogue!A$4:A$85,0))*(1+Paramètres!$B$4*(C12-1)+Paramètres!$B$5*(C12-1)^2),0) -> 12 | S12: =L12-AVERAGE(Q12:R12) -> 0 | T12: =IF(M12=0,IF(AND(N12=0,O12=0,E12=0,F12=0),"OK","ERREUR"),IF(AND(M12>=1,M12<=32,OR(N12=4,N12=6,N12=8,N12=10,N12=12,N12=20),O12>=0,E12=M12+O12,F12=M12*N12+O12),"OK","ERREUR")) -> OK | U12: =IF(M12>0,M12*(N12+1)/2+O12,0) -> 9 | V12: =IF(ABS(L12-U12)<0.001,"OK","ERREUR") -> OK
A13: ARM001 | B13: Dague | C13: 10 | D13: Légères | E13: =IF(M13=0,0,M13+O13) -> 7 | F13: =IF(M13=0,0,M13*N13+O13) -> 13 | G13: =ROUND(Catalogue!G4*SQRT((1+Paramètres!$B$4*(C13-1)+Paramètres!$B$5*(C13-1)^2)),0) -> 0 | H13: =ROUND(Catalogue!H4*SQRT((1+Paramètres!$B$4*(C13-1)+Paramètres!$B$5*(C13-1)^2)),0) -> 0 | I13: 2 | J13: 1 | K13: 0.4 | L13: =IF(M13=0,0,(E13+F13)/2) -> 10 | M13: 2 | N13: 4 | O13: 5 | P13: =IF(M13=0,"—",M13&"d"&N13&IF(O13=0,""," + "&O13)) -> 2d4 + 5 | Q13: =ROUND(INDEX(Catalogue!E$4:E$85,MATCH(A13,Catalogue!A$4:A$85,0))*(1+Paramètres!$B$4*(C13-1)+Paramètres!$B$5*(C13-1)^2),0) -> 7 | R13: =ROUND(INDEX(Catalogue!F$4:F$85,MATCH(A13,Catalogue!A$4:A$85,0))*(1+Paramètres!$B$4*(C13-1)+Paramètres!$B$5*(C13-1)^2),0) -> 13 | S13: =L13-AVERAGE(Q13:R13) -> 0 | T13: =IF(M13=0,IF(AND(N13=0,O13=0,E13=0,F13=0),"OK","ERREUR"),IF(AND(M13>=1,M13<=32,OR(N13=4,N13=6,N13=8,N13=10,N13=12,N13=20),O13>=0,E13=M13+O13,F13=M13*N13+O13),"OK","ERREUR")) -> OK | U13: =IF(M13>0,M13*(N13+1)/2+O13,0) -> 10 | V13: =IF(ABS(L13-U13)<0.001,"OK","ERREUR") -> OK
A14: ARM001 | B14: Dague | C14: 11 | D14: Légères | E14: =IF(M14=0,0,M14+O14) -> 6 | F14: =IF(M14=0,0,M14*N14+O14) -> 15 | G14: =ROUND(Catalogue!G4*SQRT((1+Paramètres!$B$4*(C14-1)+Paramètres!$B$5*(C14-1)^2)),0) -> 0 | H14: =ROUND(Catalogue!H4*SQRT((1+Paramètres!$B$4*(C14-1)+Paramètres!$B$5*(C14-1)^2)),0) -> 0 | I14: 2 | J14: 1 | K14: 0.4 | L14: =IF(M14=0,0,(E14+F14)/2) -> 10.5 | M14: 3 | N14: 4 | O14: 3 | P14: =IF(M14=0,"—",M14&"d"&N14&IF(O14=0,""," + "&O14)) -> 3d4 + 3 | Q14: =ROUND(INDEX(Catalogue!E$4:E$85,MATCH(A14,Catalogue!A$4:A$85,0))*(1+Paramètres!$B$4*(C14-1)+Paramètres!$B$5*(C14-1)^2),0) -> 7 | R14: =ROUND(INDEX(Catalogue!F$4:F$85,MATCH(A14,Catalogue!A$4:A$85,0))*(1+Paramètres!$B$4*(C14-1)+Paramètres!$B$5*(C14-1)^2),0) -> 15 | S14: =L14-AVERAGE(Q14:R14) -> -0.5 | T14: =IF(M14=0,IF(AND(N14=0,O14=0,E14=0,F14=0),"OK","ERREUR"),IF(AND(M14>=1,M14<=32,OR(N14=4,N14=6,N14=8,N14=10,N14=12,N14=20),O14>=0,E14=M14+O14,F14=M14*N14+O14),"OK","ERREUR")) -> OK | U14: =IF(M14>0,M14*(N14+1)/2+O14,0) -> 10.5 | V14: =IF(ABS(L14-U14)<0.001,"OK","ERREUR") -> OK
A15: ARM001 | B15: Dague | C15: 12 | D15: Légères | E15: =IF(M15=0,0,M15+O15) -> 8 | F15: =IF(M15=0,0,M15*N15+O15) -> 17 | G15: =ROUND(Catalogue!G4*SQRT((1+Paramètres!$B$4*(C15-1)+Paramètres!$B$5*(C15-1)^2)),0) -> 0 | H15: =ROUND(Catalogue!H4*SQRT((1+Paramètres!$B$4*(C15-1)+Paramètres!$B$5*(C15-1)^2)),0) -> 0 | I15: 2 | J15: 1 | K15: 0.4 | L15: =IF(M15=0,0,(E15+F15)/2) -> 12.5 | M15: 3 | N15: 4 | O15: 5 | P15: =IF(M15=0,"—",M15&"d"&N15&IF(O15=0,""," + "&O15)) -> 3d4 + 5 | Q15: =ROUND(INDEX(Catalogue!E$4:E$85,MATCH(A15,Catalogue!A$4:A$85,0))*(1+Paramètres!$B$4*(C15-1)+Paramètres!$B$5*(C15-1)^2),0) -> 8 | R15: =ROUND(INDEX(Catalogue!F$4:F$85,MATCH(A15,Catalogue!A$4:A$85,0))*(1+Paramètres!$B$4*(C15-1)+Paramètres!$B$5*(C15-1)^2),0) -> 17 | S15: =L15-AVERAGE(Q15:R15) -> 0 | T15: =IF(M15=0,IF(AND(N15=0,O15=0,E15=0,F15=0),"OK","ERREUR"),IF(AND(M15>=1,M15<=32,OR(N15=4,N15=6,N15=8,N15=10,N15=12,N15=20),O15>=0,E15=M15+O15,F15=M15*N15+O15),"OK","ERREUR")) -> OK | U15: =IF(M15>0,M15*(N15+1)/2+O15,0) -> 12.5 | V15: =IF(ABS(L15-U15)<0.001,"OK","ERREUR") -> OK
A16: ARM001 | B16: Dague | C16: 13 | D16: Légères | E16: =IF(M16=0,0,M16+O16) -> 9 | F16: =IF(M16=0,0,M16*N16+O16) -> 18 | G16: =ROUND(Catalogue!G4*SQRT((1+Paramètres!$B$4*(C16-1)+Paramètres!$B$5*(C16-1)^2)),0) -> 0 | H16: =ROUND(Catalogue!H4*SQRT((1+Paramètres!$B$4*(C16-1)+Paramètres!$B$5*(C16-1)^2)),0) -> 0 | I16: 2 | J16: 1 | K16: 0.4 | L16: =IF(M16=0,0,(E16+F16)/2) -> 13.5 | M16: 3 | N16: 4 | O16: 6 | P16: =IF(M16=0,"—",M16&"d"&N16&IF(O16=0,""," + "&O16)) -> 3d4 + 6 | Q16: =ROUND(INDEX(Catalogue!E$4:E$85,MATCH(A16,Catalogue!A$4:A$85,0))*(1+Paramètres!$B$4*(C16-1)+Paramètres!$B$5*(C16-1)^2),0) -> 9 | R16: =ROUND(INDEX(Catalogue!F$4:F$85,MATCH(A16,Catalogue!A$4:A$85,0))*(1+Paramètres!$B$4*(C16-1)+Paramètres!$B$5*(C16-1)^2),0) -> 18 | S16: =L16-AVERAGE(Q16:R16) -> 0 | T16: =IF(M16=0,IF(AND(N16=0,O16=0,E16=0,F16=0),"OK","ERREUR"),IF(AND(M16>=1,M16<=32,OR(N16=4,N16=6,N16=8,N16=10,N16=12,N16=20),O16>=0,E16=M16+O16,F16=M16*N16+O16),"OK","ERREUR")) -> OK | U16: =IF(M16>0,M16*(N16+1)/2+O16,0) -> 13.5 | V16: =IF(ABS(L16-U16)<0.001,"OK","ERREUR") -> OK
A17: ARM001 | B17: Dague | C17: 14 | D17: Légères | E17: =IF(M17=0,0,M17+O17) -> 10 | F17: =IF(M17=0,0,M17*N17+O17) -> 20 | G17: =ROUND(Catalogue!G4*SQRT((1+Paramètres!$B$4*(C17-1)+Paramètres!$B$5*(C17-1)^2)),0) -> 0 | H17: =ROUND(Catalogue!H4*SQRT((1+Paramètres!$B$4*(C17-1)+Paramètres!$B$5*(C17-1)^2)),0) -> 0 | I17: 2 | J17: 1 | K17: 0.4 | L17: =IF(M17=0,0,(E17+F17)/2) -> 15 | M17: 2 | N17: 6 | O17: 8 | P17: =IF(M17=0,"—",M17&"d"&N17&IF(O17=0,""," + "&O17)) -> 2d6 + 8 | Q17: =ROUND(INDEX(Catalogue!E$4:E$85,MATCH(A17,Catalogue!A$4:A$85,0))*(1+Paramètres!$B$4*(C17-1)+Paramètres!$B$5*(C17-1)^2),0) -> 10 | R17: =ROUND(INDEX(Catalogue!F$4:F$85,MATCH(A17,Catalogue!A$4:A$85,0))*(1+Paramètres!$B$4*(C17-1)+Paramètres!$B$5*(C17-1)^2),0) -> 21 | S17: =L17-AVERAGE(Q17:R17) -> -0.5 | T17: =IF(M17=0,IF(AND(N17=0,O17=0,E17=0,F17=0),"OK","ERREUR"),IF(AND(M17>=1,M17<=32,OR(N17=4,N17=6,N17=8,N17=10,N17=12,N17=20),O17>=0,E17=M17+O17,F17=M17*N17+O17),"OK","ERREUR")) -> OK | U17: =IF(M17>0,M17*(N17+1)/2+O17,0) -> 15 | V17: =IF(ABS(L17-U17)<0.001,"OK","ERREUR") -> OK
A18: ARM001 | B18: Dague | C18: 15 | D18: Légères | E18: =IF(M18=0,0,M18+O18) -> 11 | F18: =IF(M18=0,0,M18*N18+O18) -> 23 | G18: =ROUND(Catalogue!G4*SQRT((1+Paramètres!$B$4*(C18-1)+Paramètres!$B$5*(C18-1)^2)),0) -> 0 | H18: =ROUND(Catalogue!H4*SQRT((1+Paramètres!$B$4*(C18-1)+Paramètres!$B$5*(C18-1)^2)),0) -> 0 | I18: 2 | J18: 1 | K18: 0.4 | L18: =IF(M18=0,0,(E18+F18)/2) -> 17 | M18: 4 | N18: 4 | O18: 7 | P18: =IF(M18=0,"—",M18&"d"&N18&IF(O18=0,""," + "&O18)) -> 4d4 + 7 | Q18: =ROUND(INDEX(Catalogue!E$4:E$85,MATCH(A18,Catalogue!A$4:A$85,0))*(1+Paramètres!$B$4*(C18-1)+Paramètres!$B$5*(C18-1)^2),0) -> 11 | R18: =ROUND(INDEX(Catalogue!F$4:F$85,MATCH(A18,Catalogue!A$4:A$85,0))*(1+Paramètres!$B$4*(C18-1)+Paramètres!$B$5*(C18-1)^2),0) -> 23 | S18: =L18-AVERAGE(Q18:R18) -> 0 | T18: =IF(M18=0,IF(AND(N18=0,O18=0,E18=0,F18=0),"OK","ERREUR"),IF(AND(M18>=1,M18<=32,OR(N18=4,N18=6,N18=8,N18=10,N18=12,N18=20),O18>=0,E18=M18+O18,F18=M18*N18+O18),"OK","ERREUR")) -> OK | U18: =IF(M18>0,M18*(N18+1)/2+O18,0) -> 17 | V18: =IF(ABS(L18-U18)<0.001,"OK","ERREUR") -> OK
A19: ARM001 | B19: Dague | C19: 16 | D19: Légères | E19: =IF(M19=0,0,M19+O19) -> 13 | F19: =IF(M19=0,0,M19*N19+O19) -> 25 | G19: =ROUND(Catalogue!G4*SQRT((1+Paramètres!$B$4*(C19-1)+Paramètres!$B$5*(C19-1)^2)),0) -> 0 | H19: =ROUND(Catalogue!H4*SQRT((1+Paramètres!$B$4*(C19-1)+Paramètres!$B$5*(C19-1)^2)),0) -> 0 | I19: 2 | J19: 1 | K19: 0.4 | L19: =IF(M19=0,0,(E19+F19)/2) -> 19 | M19: 4 | N19: 4 | O19: 9 | P19: =IF(M19=0,"—",M19&"d"&N19&IF(O19=0,""," + "&O19)) -> 4d4 + 9 | Q19: =ROUND(INDEX(Catalogue!E$4:E$85,MATCH(A19,Catalogue!A$4:A$85,0))*(1+Paramètres!$B$4*(C19-1)+Paramètres!$B$5*(C19-1)^2),0) -> 13 | R19: =ROUND(INDEX(Catalogue!F$4:F$85,MATCH(A19,Catalogue!A$4:A$85,0))*(1+Paramètres!$B$4*(C19-1)+Paramètres!$B$5*(C19-1)^2),0) -> 25 | S19: =L19-AVERAGE(Q19:R19) -> 0 | T19: =IF(M19=0,IF(AND(N19=0,O19=0,E19=0,F19=0),"OK","ERREUR"),IF(AND(M19>=1,M19<=32,OR(N19=4,N19=6,N19=8,N19=10,N19=12,N19=20),O19>=0,E19=M19+O19,F19=M19*N19+O19),"OK","ERREUR")) -> OK | U19: =IF(M19>0,M19*(N19+1)/2+O19,0) -> 19 | V19: =IF(ABS(L19-U19)<0.001,"OK","ERREUR") -> OK
A20: ARM001 | B20: Dague | C20: 17 | D20: Légères | E20: =IF(M20=0,0,M20+O20) -> 13 | F20: =IF(M20=0,0,M20*N20+O20) -> 27 | G20: =ROUND(Catalogue!G4*SQRT((1+Paramètres!$B$4*(C20-1)+Paramètres!$B$5*(C20-1)^2)),0) -> 0 | H20: =ROUND(Catalogue!H4*SQRT((1+Paramètres!$B$4*(C20-1)+Paramètres!$B$5*(C20-1)^2)),0) -> 0 | I20: 2 | J20: 1 | K20: 0.4 | L20: =IF(M20=0,0,(E20+F20)/2) -> 20 | M20: 2 | N20: 8 | O20: 11 | P20: =IF(M20=0,"—",M20&"d"&N20&IF(O20=0,""," + "&O20)) -> 2d8 + 11 | Q20: =ROUND(INDEX(Catalogue!E$4:E$85,MATCH(A20,Catalogue!A$4:A$85,0))*(1+Paramètres!$B$4*(C20-1)+Paramètres!$B$5*(C20-1)^2),0) -> 14 | R20: =ROUND(INDEX(Catalogue!F$4:F$85,MATCH(A20,Catalogue!A$4:A$85,0))*(1+Paramètres!$B$4*(C20-1)+Paramètres!$B$5*(C20-1)^2),0) -> 27 | S20: =L20-AVERAGE(Q20:R20) -> -0.5 | T20: =IF(M20=0,IF(AND(N20=0,O20=0,E20=0,F20=0),"OK","ERREUR"),IF(AND(M20>=1,M20<=32,OR(N20=4,N20=6,N20=8,N20=10,N20=12,N20=20),O20>=0,E20=M20+O20,F20=M20*N20+O20),"OK","ERREUR")) -> OK | U20: =IF(M20>0,M20*(N20+1)/2+O20,0) -> 20 | V20: =IF(ABS(L20-U20)<0.001,"OK","ERREUR") -> OK
A21: ARM001 | B21: Dague | C21: 18 | D21: Légères | E21: =IF(M21=0,0,M21+O21) -> 15 | F21: =IF(M21=0,0,M21*N21+O21) -> 30 | G21: =ROUND(Catalogue!G4*SQRT((1+Paramètres!$B$4*(C21-1)+Paramètres!$B$5*(C21-1)^2)),0) -> 0 | H21: =ROUND(Catalogue!H4*SQRT((1+Paramètres!$B$4*(C21-1)+Paramètres!$B$5*(C21-1)^2)),0) -> 0 | I21: 2 | J21: 1 | K21: 0.4 | L21: =IF(M21=0,0,(E21+F21)/2) -> 22.5 | M21: 3 | N21: 6 | O21: 12 | P21: =IF(M21=0,"—",M21&"d"&N21&IF(O21=0,""," + "&O21)) -> 3d6 + 12 | Q21: =ROUND(INDEX(Catalogue!E$4:E$85,MATCH(A21,Catalogue!A$4:A$85,0))*(1+Paramètres!$B$4*(C21-1)+Paramètres!$B$5*(C21-1)^2),0) -> 15 | R21: =ROUND(INDEX(Catalogue!F$4:F$85,MATCH(A21,Catalogue!A$4:A$85,0))*(1+Paramètres!$B$4*(C21-1)+Paramètres!$B$5*(C21-1)^2),0) -> 30 | S21: =L21-AVERAGE(Q21:R21) -> 0 | T21: =IF(M21=0,IF(AND(N21=0,O21=0,E21=0,F21=0),"OK","ERREUR"),IF(AND(M21>=1,M21<=32,OR(N21=4,N21=6,N21=8,N21=10,N21=12,N21=20),O21>=0,E21=M21+O21,F21=M21*N21+O21),"OK","ERREUR")) -> OK | U21: =IF(M21>0,M21*(N21+1)/2+O21,0) -> 22.5 | V21: =IF(ABS(L21-U21)<0.001,"OK","ERREUR") -> OK
A22: ARM001 | B22: Dague | C22: 19 | D22: Légères | E22: =IF(M22=0,0,M22+O22) -> 15 | F22: =IF(M22=0,0,M22*N22+O22) -> 33 | G22: =ROUND(Catalogue!G4*SQRT((1+Paramètres!$B$4*(C22-1)+Paramètres!$B$5*(C22-1)^2)),0) -> 0 | H22: =ROUND(Catalogue!H4*SQRT((1+Paramètres!$B$4*(C22-1)+Paramètres!$B$5*(C22-1)^2)),0) -> 0 | I22: 2 | J22: 1 | K22: 0.4 | L22: =IF(M22=0,0,(E22+F22)/2) -> 24 | M22: 2 | N22: 10 | O22: 13 | P22: =IF(M22=0,"—",M22&"d"&N22&IF(O22=0,""," + "&O22)) -> 2d10 + 13 | Q22: =ROUND(INDEX(Catalogue!E$4:E$85,MATCH(A22,Catalogue!A$4:A$85,0))*(1+Paramètres!$B$4*(C22-1)+Paramètres!$B$5*(C22-1)^2),0) -> 16 | R22: =ROUND(INDEX(Catalogue!F$4:F$85,MATCH(A22,Catalogue!A$4:A$85,0))*(1+Paramètres!$B$4*(C22-1)+Paramètres!$B$5*(C22-1)^2),0) -> 33 | S22: =L22-AVERAGE(Q22:R22) -> -0.5 | T22: =IF(M22=0,IF(AND(N22=0,O22=0,E22=0,F22=0),"OK","ERREUR"),IF(AND(M22>=1,M22<=32,OR(N22=4,N22=6,N22=8,N22=10,N22=12,N22=20),O22>=0,E22=M22+O22,F22=M22*N22+O22),"OK","ERREUR")) -> OK | U22: =IF(M22>0,M22*(N22+1)/2+O22,0) -> 24 | V22: =IF(ABS(L22-U22)<0.001,"OK","ERREUR") -> OK
A23: ARM001 | B23: Dague | C23: 20 | D23: Légères | E23: =IF(M23=0,0,M23+O23) -> 18 | F23: =IF(M23=0,0,M23*N23+O23) -> 36 | G23: =ROUND(Catalogue!G4*SQRT((1+Paramètres!$B$4*(C23-1)+Paramètres!$B$5*(C23-1)^2)),0) -> 0 | H23: =ROUND(Catalogue!H4*SQRT((1+Paramètres!$B$4*(C23-1)+Paramètres!$B$5*(C23-1)^2)),0) -> 0 | I23: 2 | J23: 1 | K23: 0.4 | L23: =IF(M23=0,0,(E23+F23)/2) -> 27 | M23: 2 | N23: 10 | O23: 16 | P23: =IF(M23=0,"—",M23&"d"&N23&IF(O23=0,""," + "&O23)) -> 2d10 + 16 | Q23: =ROUND(INDEX(Catalogue!E$4:E$85,MATCH(A23,Catalogue!A$4:A$85,0))*(1+Paramètres!$B$4*(C23-1)+Paramètres!$B$5*(C23-1)^2),0) -> 18 | R23: =ROUND(INDEX(Catalogue!F$4:F$85,MATCH(A23,Catalogue!A$4:A$85,0))*(1+Paramètres!$B$4*(C23-1)+Paramètres!$B$5*(C23-1)^2),0) -> 35 | S23: =L23-AVERAGE(Q23:R23) -> 0.5 | T23: =IF(M23=0,IF(AND(N23=0,O23=0,E23=0,F23=0),"OK","ERREUR"),IF(AND(M23>=1,M23<=32,OR(N23=4,N23=6,N23=8,N23=10,N23=12,N23=20),O23>=0,E23=M23+O23,F23=M23*N23+O23),"OK","ERREUR")) -> OK | U23: =IF(M23>0,M23*(N23+1)/2+O23,0) -> 27 | V23: =IF(ABS(L23-U23)<0.001,"OK","ERREUR") -> OK
A24: ARM002 | B24: Poignard d'assassin | C24: 1 | D24: Légères | E24: =IF(M24=0,0,M24+O24) -> 1 | F24: =IF(M24=0,0,M24*N24+O24) -> 4 | G24: =ROUND(Catalogue!G5*SQRT((1+Paramètres!$B$4*(C24-1)+Paramètres!$B$5*(C24-1)^2)),0) -> 0 | H24: =ROUND(Catalogue!H5*SQRT((1+Paramètres!$B$4*(C24-1)+Paramètres!$B$5*(C24-1)^2)),0) -> 0 | I24: 2 | J24: 1 | K24: 0.3 | L24: =IF(M24=0,0,(E24+F24)/2) -> 2.5 | M24: 1 | N24: 4 | O24: 0 | P24: =IF(M24=0,"—",M24&"d"&N24&IF(O24=0,""," + "&O24)) -> 1d4 | Q24: =ROUND(INDEX(Catalogue!E$4:E$85,MATCH(A24,Catalogue!A$4:A$85,0))*(1+Paramètres!$B$4*(C24-1)+Paramètres!$B$5*(C24-1)^2),0) -> 2 | R24: =ROUND(INDEX(Catalogue!F$4:F$85,MATCH(A24,Catalogue!A$4:A$85,0))*(1+Paramètres!$B$4*(C24-1)+Paramètres!$B$5*(C24-1)^2),0) -> 3 | S24: =L24-AVERAGE(Q24:R24) -> 0 | T24: =IF(M24=0,IF(AND(N24=0,O24=0,E24=0,F24=0),"OK","ERREUR"),IF(AND(M24>=1,M24<=32,OR(N24=4,N24=6,N24=8,N24=10,N24=12,N24=20),O24>=0,E24=M24+O24,F24=M24*N24+O24),"OK","ERREUR")) -> OK | U24: =IF(M24>0,M24*(N24+1)/2+O24,0) -> 2.5 | V24: =IF(ABS(L24-U24)<0.001,"OK","ERREUR") -> OK
A25: ARM002 | B25: Poignard d'assassin | C25: 2 | D25: Légères | E25: =IF(M25=0,0,M25+O25) -> 1 | F25: =IF(M25=0,0,M25*N25+O25) -> 4 | G25: =ROUND(Catalogue!G5*SQRT((1+Paramètres!$B$4*(C25-1)+Paramètres!$B$5*(C25-1)^2)),0) -> 0 | H25: =ROUND(Catalogue!H5*SQRT((1+Paramètres!$B$4*(C25-1)+Paramètres!$B$5*(C25-1)^2)),0) -> 0 | I25: 2 | J25: 1 | K25: 0.3 | L25: =IF(M25=0,0,(E25+F25)/2) -> 2.5 | M25: 1 | N25: 4 | O25: 0 | P25: =IF(M25=0,"—",M25&"d"&N25&IF(O25=0,""," + "&O25)) -> 1d4 | Q25: =ROUND(INDEX(Catalogue!E$4:E$85,MATCH(A25,Catalogue!A$4:A$85,0))*(1+Paramètres!$B$4*(C25-1)+Paramètres!$B$5*(C25-1)^2),0) -> 2 | R25: =ROUND(INDEX(Catalogue!F$4:F$85,MATCH(A25,Catalogue!A$4:A$85,0))*(1+Paramètres!$B$4*(C25-1)+Paramètres!$B$5*(C25-1)^2),0) -> 3 | S25: =L25-AVERAGE(Q25:R25) -> 0 | T25: =IF(M25=0,IF(AND(N25=0,O25=0,E25=0,F25=0),"OK","ERREUR"),IF(AND(M25>=1,M25<=32,OR(N25=4,N25=6,N25=8,N25=10,N25=12,N25=20),O25>=0,E25=M25+O25,F25=M25*N25+O25),"OK","ERREUR")) -> OK | U25: =IF(M25>0,M25*(N25+1)/2+O25,0) -> 2.5 | V25: =IF(ABS(L25-U25)<0.001,"OK","ERREUR") -> OK
A26: ARM002 | B26: Poignard d'assassin | C26: 3 | D26: Légères | E26: =IF(M26=0,0,M26+O26) -> 2 | F26: =IF(M26=0,0,M26*N26+O26) -> 5 | G26: =ROUND(Catalogue!G5*SQRT((1+Paramètres!$B$4*(C26-1)+Paramètres!$B$5*(C26-1)^2)),0) -> 0 | H26: =ROUND(Catalogue!H5*SQRT((1+Paramètres!$B$4*(C26-1)+Paramètres!$B$5*(C26-1)^2)),0) -> 0 | I26: 2 | J26: 1 | K26: 0.3 | L26: =IF(M26=0,0,(E26+F26)/2) -> 3.5 | M26: 1 | N26: 4 | O26: 1 | P26: =IF(M26=0,"—",M26&"d"&N26&IF(O26=0,""," + "&O26)) -> 1d4 + 1 | Q26: =ROUND(INDEX(Catalogue!E$4:E$85,MATCH(A26,Catalogue!A$4:A$85,0))*(1+Paramètres!$B$4*(C26-1)+Paramètres!$B$5*(C26-1)^2),0) -> 3 | R26: =ROUND(INDEX(Catalogue!F$4:F$85,MATCH(A26,Catalogue!A$4:A$85,0))*(1+Paramètres!$B$4*(C26-1)+Paramètres!$B$5*(C26-1)^2),0) -> 4 | S26: =L26-AVERAGE(Q26:R26) -> 0 | T26: =IF(M26=0,IF(AND(N26=0,O26=0,E26=0,F26=0),"OK","ERREUR"),IF(AND(M26>=1,M26<=32,OR(N26=4,N26=6,N26=8,N26=10,N26=12,N26=20),O26>=0,E26=M26+O26,F26=M26*N26+O26),"OK","ERREUR")) -> OK | U26: =IF(M26>0,M26*(N26+1)/2+O26,0) -> 3.5 | V26: =IF(ABS(L26-U26)<0.001,"OK","ERREUR") -> OK
A27: ARM002 | B27: Poignard d'assassin | C27: 4 | D27: Légères | E27: =IF(M27=0,0,M27+O27) -> 2 | F27: =IF(M27=0,0,M27*N27+O27) -> 5 | G27: =ROUND(Catalogue!G5*SQRT((1+Paramètres!$B$4*(C27-1)+Paramètres!$B$5*(C27-1)^2)),0) -> 0 | H27: =ROUND(Catalogue!H5*SQRT((1+Paramètres!$B$4*(C27-1)+Paramètres!$B$5*(C27-1)^2)),0) -> 0 | I27: 2 | J27: 1 | K27: 0.3 | L27: =IF(M27=0,0,(E27+F27)/2) -> 3.5 | M27: 1 | N27: 4 | O27: 1 | P27: =IF(M27=0,"—",M27&"d"&N27&IF(O27=0,""," + "&O27)) -> 1d4 + 1 | Q27: =ROUND(INDEX(Catalogue!E$4:E$85,MATCH(A27,Catalogue!A$4:A$85,0))*(1+Paramètres!$B$4*(C27-1)+Paramètres!$B$5*(C27-1)^2),0) -> 3 | R27: =ROUND(INDEX(Catalogue!F$4:F$85,MATCH(A27,Catalogue!A$4:A$85,0))*(1+Paramètres!$B$4*(C27-1)+Paramètres!$B$5*(C27-1)^2),0) -> 4 | S27: =L27-AVERAGE(Q27:R27) -> 0 | T27: =IF(M27=0,IF(AND(N27=0,O27=0,E27=0,F27=0),"OK","ERREUR"),IF(AND(M27>=1,M27<=32,OR(N27=4,N27=6,N27=8,N27=10,N27=12,N27=20),O27>=0,E27=M27+O27,F27=M27*N27+O27),"OK","ERREUR")) -> OK | U27: =IF(M27>0,M27*(N27+1)/2+O27,0) -> 3.5 | V27: =IF(ABS(L27-U27)<0.001,"OK","ERREUR") -> OK
A28: ARM002 | B28: Poignard d'assassin | C28: 5 | D28: Légères | E28: =IF(M28=0,0,M28+O28) -> 2 | F28: =IF(M28=0,0,M28*N28+O28) -> 5 | G28: =ROUND(Catalogue!G5*SQRT((1+Paramètres!$B$4*(C28-1)+Paramètres!$B$5*(C28-1)^2)),0) -> 0 | H28: =ROUND(Catalogue!H5*SQRT((1+Paramètres!$B$4*(C28-1)+Paramètres!$B$5*(C28-1)^2)),0) -> 0 | I28: 2 | J28: 1 | K28: 0.3 | L28: =IF(M28=0,0,(E28+F28)/2) -> 3.5 | M28: 1 | N28: 4 | O28: 1 | P28: =IF(M28=0,"—",M28&"d"&N28&IF(O28=0,""," + "&O28)) -> 1d4 + 1 | Q28: =ROUND(INDEX(Catalogue!E$4:E$85,MATCH(A28,Catalogue!A$4:A$85,0))*(1+Paramètres!$B$4*(C28-1)+Paramètres!$B$5*(C28-1)^2),0) -> 3 | R28: =ROUND(INDEX(Catalogue!F$4:F$85,MATCH(A28,Catalogue!A$4:A$85,0))*(1+Paramètres!$B$4*(C28-1)+Paramètres!$B$5*(C28-1)^2),0) -> 5 | S28: =L28-AVERAGE(Q28:R28) -> -0.5 | T28: =IF(M28=0,IF(AND(N28=0,O28=0,E28=0,F28=0),"OK","ERREUR"),IF(AND(M28>=1,M28<=32,OR(N28=4,N28=6,N28=8,N28=10,N28=12,N28=20),O28>=0,E28=M28+O28,F28=M28*N28+O28),"OK","ERREUR")) -> OK | U28: =IF(M28>0,M28*(N28+1)/2+O28,0) -> 3.5 | V28: =IF(ABS(L28-U28)<0.001,"OK","ERREUR") -> OK
A29: ARM002 | B29: Poignard d'assassin | C29: 6 | D29: Légères | E29: =IF(M29=0,0,M29+O29) -> 3 | F29: =IF(M29=0,0,M29*N29+O29) -> 6 | G29: =ROUND(Catalogue!G5*SQRT((1+Paramètres!$B$4*(C29-1)+Paramètres!$B$5*(C29-1)^2)),0) -> 0 | H29: =ROUND(Catalogue!H5*SQRT((1+Paramètres!$B$4*(C29-1)+Paramètres!$B$5*(C29-1)^2)),0) -> 0 | I29: 2 | J29: 1 | K29: 0.3 | L29: =IF(M29=0,0,(E29+F29)/2) -> 4.5 | M29: 1 | N29: 4 | O29: 2 | P29: =IF(M29=0,"—",M29&"d"&N29&IF(O29=0,""," + "&O29)) -> 1d4 + 2 | Q29: =ROUND(INDEX(Catalogue!E$4:E$85,MATCH(A29,Catalogue!A$4:A$85,0))*(1+Paramètres!$B$4*(C29-1)+Paramètres!$B$5*(C29-1)^2),0) -> 4 | R29: =ROUND(INDEX(Catalogue!F$4:F$85,MATCH(A29,Catalogue!A$4:A$85,0))*(1+Paramètres!$B$4*(C29-1)+Paramètres!$B$5*(C29-1)^2),0) -> 6 | S29: =L29-AVERAGE(Q29:R29) -> -0.5 | T29: =IF(M29=0,IF(AND(N29=0,O29=0,E29=0,F29=0),"OK","ERREUR"),IF(AND(M29>=1,M29<=32,OR(N29=4,N29=6,N29=8,N29=10,N29=12,N29=20),O29>=0,E29=M29+O29,F29=M29*N29+O29),"OK","ERREUR")) -> OK | U29: =IF(M29>0,M29*(N29+1)/2+O29,0) -> 4.5 | V29: =IF(ABS(L29-U29)<0.001,"OK","ERREUR") -> OK
A30: ARM002 | B30: Poignard d'assassin | C30: 7 | D30: Légères | E30: =IF(M30=0,0,M30+O30) -> 4 | F30: =IF(M30=0,0,M30*N30+O30) -> 7 | G30: =ROUND(Catalogue!G5*SQRT((1+Paramètres!$B$4*(C30-1)+Paramètres!$B$5*(C30-1)^2)),0) -> 0 | H30: =ROUND(Catalogue!H5*SQRT((1+Paramètres!$B$4*(C30-1)+Paramètres!$B$5*(C30-1)^2)),0) -> 0 | I30: 2 | J30: 1 | K30: 0.3 | L30: =IF(M30=0,0,(E30+F30)/2) -> 5.5 | M30: 1 | N30: 4 | O30: 3 | P30: =IF(M30=0,"—",M30&"d"&N30&IF(O30=0,""," + "&O30)) -> 1d4 + 3 | Q30: =ROUND(INDEX(Catalogue!E$4:E$85,MATCH(A30,Catalogue!A$4:A$85,0))*(1+Paramètres!$B$4*(C30-1)+Paramètres!$B$5*(C30-1)^2),0) -> 4 | R30: =ROUND(INDEX(Catalogue!F$4:F$85,MATCH(A30,Catalogue!A$4:A$85,0))*(1+Paramètres!$B$4*(C30-1)+Paramètres!$B$5*(C30-1)^2),0) -> 7 | S30: =L30-AVERAGE(Q30:R30) -> 0 | T30: =IF(M30=0,IF(AND(N30=0,O30=0,E30=0,F30=0),"OK","ERREUR"),IF(AND(M30>=1,M30<=32,OR(N30=4,N30=6,N30=8,N30=10,N30=12,N30=20),O30>=0,E30=M30+O30,F30=M30*N30+O30),"OK","ERREUR")) -> OK | U30: =IF(M30>0,M30*(N30+1)/2+O30,0) -> 5.5 | V30: =IF(ABS(L30-U30)<0.001,"OK","ERREUR") -> OK
A31: ARM002 | B31: Poignard d'assassin | C31: 8 | D31: Légères | E31: =IF(M31=0,0,M31+O31) -> 5 | F31: =IF(M31=0,0,M31*N31+O31) -> 8 | G31: =ROUND(Catalogue!G5*SQRT((1+Paramètres!$B$4*(C31-1)+Paramètres!$B$5*(C31-1)^2)),0) -> 0 | H31: =ROUND(Catalogue!H5*SQRT((1+Paramètres!$B$4*(C31-1)+Paramètres!$B$5*(C31-1)^2)),0) -> 0 | I31: 2 | J31: 1 | K31: 0.3 | L31: =IF(M31=0,0,(E31+F31)/2) -> 6.5 | M31: 1 | N31: 4 | O31: 4 | P31: =IF(M31=0,"—",M31&"d"&N31&IF(O31=0,""," + "&O31)) -> 1d4 + 4 | Q31: =ROUND(INDEX(Catalogue!E$4:E$85,MATCH(A31,Catalogue!A$4:A$85,0))*(1+Paramètres!$B$4*(C31-1)+Paramètres!$B$5*(C31-1)^2),0) -> 5 | R31: =ROUND(INDEX(Catalogue!F$4:F$85,MATCH(A31,Catalogue!A$4:A$85,0))*(1+Paramètres!$B$4*(C31-1)+Paramètres!$B$5*(C31-1)^2),0) -> 8 | S31: =L31-AVERAGE(Q31:R31) -> 0 | T31: =IF(M31=0,IF(AND(N31=0,O31=0,E31=0,F31=0),"OK","ERREUR"),IF(AND(M31>=1,M31<=32,OR(N31=4,N31=6,N31=8,N31=10,N31=12,N31=20),O31>=0,E31=M31+O31,F31=M31*N31+O31),"OK","ERREUR")) -> OK | U31: =IF(M31>0,M31*(N31+1)/2+O31,0) -> 6.5 | V31: =IF(ABS(L31-U31)<0.001,"OK","ERREUR") -> OK
A32: ARM002 | B32: Poignard d'assassin | C32: 9 | D32: Légères | E32: =IF(M32=0,0,M32+O32) -> 6 | F32: =IF(M32=0,0,M32*N32+O32) -> 9 | G32: =ROUND(Catalogue!G5*SQRT((1+Paramètres!$B$4*(C32-1)+Paramètres!$B$5*(C32-1)^2)),0) -> 0 | H32: =ROUND(Catalogue!H5*SQRT((1+Paramètres!$B$4*(C32-1)+Paramètres!$B$5*(C32-1)^2)),0) -> 0 | I32: 2 | J32: 1 | K32: 0.3 | L32: =IF(M32=0,0,(E32+F32)/2) -> 7.5 | M32: 1 | N32: 4 | O32: 5 | P32: =IF(M32=0,"—",M32&"d"&N32&IF(O32=0,""," + "&O32)) -> 1d4 + 5 | Q32: =ROUND(INDEX(Catalogue!E$4:E$85,MATCH(A32,Catalogue!A$4:A$85,0))*(1+Paramètres!$B$4*(C32-1)+Paramètres!$B$5*(C32-1)^2),0) -> 6 | R32: =ROUND(INDEX(Catalogue!F$4:F$85,MATCH(A32,Catalogue!A$4:A$85,0))*(1+Paramètres!$B$4*(C32-1)+Paramètres!$B$5*(C32-1)^2),0) -> 9 | S32: =L32-AVERAGE(Q32:R32) -> 0 | T32: =IF(M32=0,IF(AND(N32=0,O32=0,E32=0,F32=0),"OK","ERREUR"),IF(AND(M32>=1,M32<=32,OR(N32=4,N32=6,N32=8,N32=10,N32=12,N32=20),O32>=0,E32=M32+O32,F32=M32*N32+O32),"OK","ERREUR")) -> OK | U32: =IF(M32>0,M32*(N32+1)/2+O32,0) -> 7.5 | V32: =IF(ABS(L32-U32)<0.001,"OK","ERREUR") -> OK
A33: ARM002 | B33: Poignard d'assassin | C33: 10 | D33: Légères | E33: =IF(M33=0,0,M33+O33) -> 7 | F33: =IF(M33=0,0,M33*N33+O33) -> 10 | G33: =ROUND(Catalogue!G5*SQRT((1+Paramètres!$B$4*(C33-1)+Paramètres!$B$5*(C33-1)^2)),0) -> 0 | H33: =ROUND(Catalogue!H5*SQRT((1+Paramètres!$B$4*(C33-1)+Paramètres!$B$5*(C33-1)^2)),0) -> 0 | I33: 2 | J33: 1 | K33: 0.3 | L33: =IF(M33=0,0,(E33+F33)/2) -> 8.5 | M33: 1 | N33: 4 | O33: 6 | P33: =IF(M33=0,"—",M33&"d"&N33&IF(O33=0,""," + "&O33)) -> 1d4 + 6 | Q33: =ROUND(INDEX(Catalogue!E$4:E$85,MATCH(A33,Catalogue!A$4:A$85,0))*(1+Paramètres!$B$4*(C33-1)+Paramètres!$B$5*(C33-1)^2),0) -> 7 | R33: =ROUND(INDEX(Catalogue!F$4:F$85,MATCH(A33,Catalogue!A$4:A$85,0))*(1+Paramètres!$B$4*(C33-1)+Paramètres!$B$5*(C33-1)^2),0) -> 10 | S33: =L33-AVERAGE(Q33:R33) -> 0 | T33: =IF(M33=0,IF(AND(N33=0,O33=0,E33=0,F33=0),"OK","ERREUR"),IF(AND(M33>=1,M33<=32,OR(N33=4,N33=6,N33=8,N33=10,N33=12,N33=20),O33>=0,E33=M33+O33,F33=M33*N33+O33),"OK","ERREUR")) -> OK | U33: =IF(M33>0,M33*(N33+1)/2+O33,0) -> 8.5 | V33: =IF(ABS(L33-U33)<0.001,"OK","ERREUR") -> OK
A34: ARM002 | B34: Poignard d'assassin | C34: 11 | D34: Légères | E34: =IF(M34=0,0,M34+O34) -> 7 | F34: =IF(M34=0,0,M34*N34+O34) -> 10 | G34: =ROUND(Catalogue!G5*SQRT((1+Paramètres!$B$4*(C34-1)+Paramètres!$B$5*(C34-1)^2)),0) -> 0 | H34: =ROUND(Catalogue!H5*SQRT((1+Paramètres!$B$4*(C34-1)+Paramètres!$B$5*(C34-1)^2)),0) -> 0 | I34: 2 | J34: 1 | K34: 0.3 | L34: =IF(M34=0,0,(E34+F34)/2) -> 8.5 | M34: 1 | N34: 4 | O34: 6 | P34: =IF(M34=0,"—",M34&"d"&N34&IF(O34=0,""," + "&O34)) -> 1d4 + 6 | Q34: =ROUND(INDEX(Catalogue!E$4:E$85,MATCH(A34,Catalogue!A$4:A$85,0))*(1+Paramètres!$B$4*(C34-1)+Paramètres!$B$5*(C34-1)^2),0) -> 7 | R34: =ROUND(INDEX(Catalogue!F$4:F$85,MATCH(A34,Catalogue!A$4:A$85,0))*(1+Paramètres!$B$4*(C34-1)+Paramètres!$B$5*(C34-1)^2),0) -> 11 | S34: =L34-AVERAGE(Q34:R34) -> -0.5 | T34: =IF(M34=0,IF(AND(N34=0,O34=0,E34=0,F34=0),"OK","ERREUR"),IF(AND(M34>=1,M34<=32,OR(N34=4,N34=6,N34=8,N34=10,N34=12,N34=20),O34>=0,E34=M34+O34,F34=M34*N34+O34),"OK","ERREUR")) -> OK | U34: =IF(M34>0,M34*(N34+1)/2+O34,0) -> 8.5 | V34: =IF(ABS(L34-U34)<0.001,"OK","ERREUR") -> OK
A35: ARM002 | B35: Poignard d'assassin | C35: 12 | D35: Légères | E35: =IF(M35=0,0,M35+O35) -> 9 | F35: =IF(M35=0,0,M35*N35+O35) -> 12 | G35: =ROUND(Catalogue!G5*SQRT((1+Paramètres!$B$4*(C35-1)+Paramètres!$B$5*(C35-1)^2)),0) -> 0 | H35: =ROUND(Catalogue!H5*SQRT((1+Paramètres!$B$4*(C35-1)+Paramètres!$B$5*(C35-1)^2)),0) -> 0 | I35: 2 | J35: 1 | K35: 0.3 | L35: =IF(M35=0,0,(E35+F35)/2) -> 10.5 | M35: 1 | N35: 4 | O35: 8 | P35: =IF(M35=0,"—",M35&"d"&N35&IF(O35=0,""," + "&O35)) -> 1d4 + 8 | Q35: =ROUND(INDEX(Catalogue!E$4:E$85,MATCH(A35,Catalogue!A$4:A$85,0))*(1+Paramètres!$B$4*(C35-1)+Paramètres!$B$5*(C35-1)^2),0) -> 8 | R35: =ROUND(INDEX(Catalogue!F$4:F$85,MATCH(A35,Catalogue!A$4:A$85,0))*(1+Paramètres!$B$4*(C35-1)+Paramètres!$B$5*(C35-1)^2),0) -> 12 | S35: =L35-AVERAGE(Q35:R35) -> 0.5 | T35: =IF(M35=0,IF(AND(N35=0,O35=0,E35=0,F35=0),"OK","ERREUR"),IF(AND(M35>=1,M35<=32,OR(N35=4,N35=6,N35=8,N35=10,N35=12,N35=20),O35>=0,E35=M35+O35,F35=M35*N35+O35),"OK","ERREUR")) -> OK | U35: =IF(M35>0,M35*(N35+1)/2+O35,0) -> 10.5 | V35: =IF(ABS(L35-U35)<0.001,"OK","ERREUR") -> OK
A36: ARM002 | B36: Poignard d'assassin | C36: 13 | D36: Légères | E36: =IF(M36=0,0,M36+O36) -> 9 | F36: =IF(M36=0,0,M36*N36+O36) -> 14 | G36: =ROUND(Catalogue!G5*SQRT((1+Paramètres!$B$4*(C36-1)+Paramètres!$B$5*(C36-1)^2)),0) -> 0 | H36: =ROUND(Catalogue!H5*SQRT((1+Paramètres!$B$4*(C36-1)+Paramètres!$B$5*(C36-1)^2)),0) -> 0 | I36: 2 | J36: 1 | K36: 0.3 | L36: =IF(M36=0,0,(E36+F36)/2) -> 11.5 | M36: 1 | N36: 6 | O36: 8 | P36: =IF(M36=0,"—",M36&"d"&N36&IF(O36=0,""," + "&O36)) -> 1d6 + 8 | Q36: =ROUND(INDEX(Catalogue!E$4:E$85,MATCH(A36,Catalogue!A$4:A$85,0))*(1+Paramètres!$B$4*(C36-1)+Paramètres!$B$5*(C36-1)^2),0) -> 9 | R36: =ROUND(INDEX(Catalogue!F$4:F$85,MATCH(A36,Catalogue!A$4:A$85,0))*(1+Paramètres!$B$4*(C36-1)+Paramètres!$B$5*(C36-1)^2),0) -> 14 | S36: =L36-AVERAGE(Q36:R36) -> 0 | T36: =IF(M36=0,IF(AND(N36=0,O36=0,E36=0,F36=0),"OK","ERREUR"),IF(AND(M36>=1,M36<=32,OR(N36=4,N36=6,N36=8,N36=10,N36=12,N36=20),O36>=0,E36=M36+O36,F36=M36*N36+O36),"OK","ERREUR")) -> OK | U36: =IF(M36>0,M36*(N36+1)/2+O36,0) -> 11.5 | V36: =IF(ABS(L36-U36)<0.001,"OK","ERREUR") -> OK
A37: ARM002 | B37: Poignard d'assassin | C37: 14 | D37: Légères | E37: =IF(M37=0,0,M37+O37) -> 10 | F37: =IF(M37=0,0,M37*N37+O37) -> 15 | G37: =ROUND(Catalogue!G5*SQRT((1+Paramètres!$B$4*(C37-1)+Paramètres!$B$5*(C37-1)^2)),0) -> 0 | H37: =ROUND(Catalogue!H5*SQRT((1+Paramètres!$B$4*(C37-1)+Paramètres!$B$5*(C37-1)^2)),0) -> 0 | I37: 2 | J37: 1 | K37: 0.3 | L37: =IF(M37=0,0,(E37+F37)/2) -> 12.5 | M37: 1 | N37: 6 | O37: 9 | P37: =IF(M37=0,"—",M37&"d"&N37&IF(O37=0,""," + "&O37)) -> 1d6 + 9 | Q37: =ROUND(INDEX(Catalogue!E$4:E$85,MATCH(A37,Catalogue!A$4:A$85,0))*(1+Paramètres!$B$4*(C37-1)+Paramètres!$B$5*(C37-1)^2),0) -> 10 | R37: =ROUND(INDEX(Catalogue!F$4:F$85,MATCH(A37,Catalogue!A$4:A$85,0))*(1+Paramètres!$B$4*(C37-1)+Paramètres!$B$5*(C37-1)^2),0) -> 15 | S37: =L37-AVERAGE(Q37:R37) -> 0 | T37: =IF(M37=0,IF(AND(N37=0,O37=0,E37=0,F37=0),"OK","ERREUR"),IF(AND(M37>=1,M37<=32,OR(N37=4,N37=6,N37=8,N37=10,N37=12,N37=20),O37>=0,E37=M37+O37,F37=M37*N37+O37),"OK","ERREUR")) -> OK | U37: =IF(M37>0,M37*(N37+1)/2+O37,0) -> 12.5 | V37: =IF(ABS(L37-U37)<0.001,"OK","ERREUR") -> OK
A38: ARM002 | B38: Poignard d'assassin | C38: 15 | D38: Légères | E38: =IF(M38=0,0,M38+O38) -> 11 | F38: =IF(M38=0,0,M38*N38+O38) -> 17 | G38: =ROUND(Catalogue!G5*SQRT((1+Paramètres!$B$4*(C38-1)+Paramètres!$B$5*(C38-1)^2)),0) -> 0 | H38: =ROUND(Catalogue!H5*SQRT((1+Paramètres!$B$4*(C38-1)+Paramètres!$B$5*(C38-1)^2)),0) -> 0 | I38: 2 | J38: 1 | K38: 0.3 | L38: =IF(M38=0,0,(E38+F38)/2) -> 14 | M38: 2 | N38: 4 | O38: 9 | P38: =IF(M38=0,"—",M38&"d"&N38&IF(O38=0,""," + "&O38)) -> 2d4 + 9 | Q38: =ROUND(INDEX(Catalogue!E$4:E$85,MATCH(A38,Catalogue!A$4:A$85,0))*(1+Paramètres!$B$4*(C38-1)+Paramètres!$B$5*(C38-1)^2),0) -> 11 | R38: =ROUND(INDEX(Catalogue!F$4:F$85,MATCH(A38,Catalogue!A$4:A$85,0))*(1+Paramètres!$B$4*(C38-1)+Paramètres!$B$5*(C38-1)^2),0) -> 17 | S38: =L38-AVERAGE(Q38:R38) -> 0 | T38: =IF(M38=0,IF(AND(N38=0,O38=0,E38=0,F38=0),"OK","ERREUR"),IF(AND(M38>=1,M38<=32,OR(N38=4,N38=6,N38=8,N38=10,N38=12,N38=20),O38>=0,E38=M38+O38,F38=M38*N38+O38),"OK","ERREUR")) -> OK | U38: =IF(M38>0,M38*(N38+1)/2+O38,0) -> 14 | V38: =IF(ABS(L38-U38)<0.001,"OK","ERREUR") -> OK
A39: ARM002 | B39: Poignard d'assassin | C39: 16 | D39: Légères | E39: =IF(M39=0,0,M39+O39) -> 13 | F39: =IF(M39=0,0,M39*N39+O39) -> 19 | G39: =ROUND(Catalogue!G5*SQRT((1+Paramètres!$B$4*(C39-1)+Paramètres!$B$5*(C39-1)^2)),0) -> 0 | H39: =ROUND(Catalogue!H5*SQRT((1+Paramètres!$B$4*(C39-1)+Paramètres!$B$5*(C39-1)^2)),0) -> 0 | I39: 2 | J39: 1 | K39: 0.3 | L39: =IF(M39=0,0,(E39+F39)/2) -> 16 | M39: 2 | N39: 4 | O39: 11 | P39: =IF(M39=0,"—",M39&"d"&N39&IF(O39=0,""," + "&O39)) -> 2d4 + 11 | Q39: =ROUND(INDEX(Catalogue!E$4:E$85,MATCH(A39,Catalogue!A$4:A$85,0))*(1+Paramètres!$B$4*(C39-1)+Paramètres!$B$5*(C39-1)^2),0) -> 13 | R39: =ROUND(INDEX(Catalogue!F$4:F$85,MATCH(A39,Catalogue!A$4:A$85,0))*(1+Paramètres!$B$4*(C39-1)+Paramètres!$B$5*(C39-1)^2),0) -> 19 | S39: =L39-AVERAGE(Q39:R39) -> 0 | T39: =IF(M39=0,IF(AND(N39=0,O39=0,E39=0,F39=0),"OK","ERREUR"),IF(AND(M39>=1,M39<=32,OR(N39=4,N39=6,N39=8,N39=10,N39=12,N39=20),O39>=0,E39=M39+O39,F39=M39*N39+O39),"OK","ERREUR")) -> OK | U39: =IF(M39>0,M39*(N39+1)/2+O39,0) -> 16 | V39: =IF(ABS(L39-U39)<0.001,"OK","ERREUR") -> OK
A40: ARM002 | B40: Poignard d'assassin | C40: 17 | D40: Légères | E40: =IF(M40=0,0,M40+O40) -> 14 | F40: =IF(M40=0,0,M40*N40+O40) -> 21 | G40: =ROUND(Catalogue!G5*SQRT((1+Paramètres!$B$4*(C40-1)+Paramètres!$B$5*(C40-1)^2)),0) -> 0 | H40: =ROUND(Catalogue!H5*SQRT((1+Paramètres!$B$4*(C40-1)+Paramètres!$B$5*(C40-1)^2)),0) -> 0 | I40: 2 | J40: 1 | K40: 0.3 | L40: =IF(M40=0,0,(E40+F40)/2) -> 17.5 | M40: 1 | N40: 8 | O40: 13 | P40: =IF(M40=0,"—",M40&"d"&N40&IF(O40=0,""," + "&O40)) -> 1d8 + 13 | Q40: =ROUND(INDEX(Catalogue!E$4:E$85,MATCH(A40,Catalogue!A$4:A$85,0))*(1+Paramètres!$B$4*(C40-1)+Paramètres!$B$5*(C40-1)^2),0) -> 14 | R40: =ROUND(INDEX(Catalogue!F$4:F$85,MATCH(A40,Catalogue!A$4:A$85,0))*(1+Paramètres!$B$4*(C40-1)+Paramètres!$B$5*(C40-1)^2),0) -> 21 | S40: =L40-AVERAGE(Q40:R40) -> 0 | T40: =IF(M40=0,IF(AND(N40=0,O40=0,E40=0,F40=0),"OK","ERREUR"),IF(AND(M40>=1,M40<=32,OR(N40=4,N40=6,N40=8,N40=10,N40=12,N40=20),O40>=0,E40=M40+O40,F40=M40*N40+O40),"OK","ERREUR")) -> OK | U40: =IF(M40>0,M40*(N40+1)/2+O40,0) -> 17.5 | V40: =IF(ABS(L40-U40)<0.001,"OK","ERREUR") -> OK
A41: ARM002 | B41: Poignard d'assassin | C41: 18 | D41: Légères | E41: =IF(M41=0,0,M41+O41) -> 15 | F41: =IF(M41=0,0,M41*N41+O41) -> 22 | G41: =ROUND(Catalogue!G5*SQRT((1+Paramètres!$B$4*(C41-1)+Paramètres!$B$5*(C41-1)^2)),0) -> 0 | H41: =ROUND(Catalogue!H5*SQRT((1+Paramètres!$B$4*(C41-1)+Paramètres!$B$5*(C41-1)^2)),0) -> 0 | I41: 2 | J41: 1 | K41: 0.3 | L41: =IF(M41=0,0,(E41+F41)/2) -> 18.5 | M41: 1 | N41: 8 | O41: 14 | P41: =IF(M41=0,"—",M41&"d"&N41&IF(O41=0,""," + "&O41)) -> 1d8 + 14 | Q41: =ROUND(INDEX(Catalogue!E$4:E$85,MATCH(A41,Catalogue!A$4:A$85,0))*(1+Paramètres!$B$4*(C41-1)+Paramètres!$B$5*(C41-1)^2),0) -> 15 | R41: =ROUND(INDEX(Catalogue!F$4:F$85,MATCH(A41,Catalogue!A$4:A$85,0))*(1+Paramètres!$B$4*(C41-1)+Paramètres!$B$5*(C41-1)^2),0) -> 22 | S41: =L41-AVERAGE(Q41:R41) -> 0 | T41: =IF(M41=0,IF(AND(N41=0,O41=0,E41=0,F41=0),"OK","ERREUR"),IF(AND(M41>=1,M41<=32,OR(N41=4,N41=6,N41=8,N41=10,N41=12,N41=20),O41>=0,E41=M41+O41,F41=M41*N41+O41),"OK","ERREUR")) -> OK | U41: =IF(M41>0,M41*(N41+1)/2+O41,0) -> 18.5 | V41: =IF(ABS(L41-U41)<0.001,"OK","ERREUR") -> OK
A42: ARM002 | B42: Poignard d'assassin | C42: 19 | D42: Légères | E42: =IF(M42=0,0,M42+O42) -> 15 | F42: =IF(M42=0,0,M42*N42+O42) -> 24 | G42: =ROUND(Catalogue!G5*SQRT((1+Paramètres!$B$4*(C42-1)+Paramètres!$B$5*(C42-1)^2)),0) -> 0 | H42: =ROUND(Catalogue!H5*SQRT((1+Paramètres!$B$4*(C42-1)+Paramètres!$B$5*(C42-1)^2)),0) -> 0 | I42: 2 | J42: 1 | K42: 0.3 | L42: =IF(M42=0,0,(E42+F42)/2) -> 19.5 | M42: 3 | N42: 4 | O42: 12 | P42: =IF(M42=0,"—",M42&"d"&N42&IF(O42=0,""," + "&O42)) -> 3d4 + 12 | Q42: =ROUND(INDEX(Catalogue!E$4:E$85,MATCH(A42,Catalogue!A$4:A$85,0))*(1+Paramètres!$B$4*(C42-1)+Paramètres!$B$5*(C42-1)^2),0) -> 16 | R42: =ROUND(INDEX(Catalogue!F$4:F$85,MATCH(A42,Catalogue!A$4:A$85,0))*(1+Paramètres!$B$4*(C42-1)+Paramètres!$B$5*(C42-1)^2),0) -> 24 | S42: =L42-AVERAGE(Q42:R42) -> -0.5 | T42: =IF(M42=0,IF(AND(N42=0,O42=0,E42=0,F42=0),"OK","ERREUR"),IF(AND(M42>=1,M42<=32,OR(N42=4,N42=6,N42=8,N42=10,N42=12,N42=20),O42>=0,E42=M42+O42,F42=M42*N42+O42),"OK","ERREUR")) -> OK | U42: =IF(M42>0,M42*(N42+1)/2+O42,0) -> 19.5 | V42: =IF(ABS(L42-U42)<0.001,"OK","ERREUR") -> OK
A43: ARM002 | B43: Poignard d'assassin | C43: 20 | D43: Légères | E43: =IF(M43=0,0,M43+O43) -> 18 | F43: =IF(M43=0,0,M43*N43+O43) -> 27 | G43: =ROUND(Catalogue!G5*SQRT((1+Paramètres!$B$4*(C43-1)+Paramètres!$B$5*(C43-1)^2)),0) -> 0 | H43: =ROUND(Catalogue!H5*SQRT((1+Paramètres!$B$4*(C43-1)+Paramètres!$B$5*(C43-1)^2)),0) -> 0 | I43: 2 | J43: 1 | K43: 0.3 | L43: =IF(M43=0,0,(E43+F43)/2) -> 22.5 | M43: 3 | N43: 4 | O43: 15 | P43: =IF(M43=0,"—",M43&"d"&N43&IF(O43=0,""," + "&O43)) -> 3d4 + 15 | Q43: =ROUND(INDEX(Catalogue!E$4:E$85,MATCH(A43,Catalogue!A$4:A$85,0))*(1+Paramètres!$B$4*(C43-1)+Paramètres!$B$5*(C43-1)^2),0) -> 18 | R43: =ROUND(INDEX(Catalogue!F$4:F$85,MATCH(A43,Catalogue!A$4:A$85,0))*(1+Paramètres!$B$4*(C43-1)+Paramètres!$B$5*(C43-1)^2),0) -> 27 | S43: =L43-AVERAGE(Q43:R43) -> 0 | T43: =IF(M43=0,IF(AND(N43=0,O43=0,E43=0,F43=0),"OK","ERREUR"),IF(AND(M43>=1,M43<=32,OR(N43=4,N43=6,N43=8,N43=10,N43=12,N43=20),O43>=0,E43=M43+O43,F43=M43*N43+O43),"OK","ERREUR")) -> OK | U43: =IF(M43>0,M43*(N43+1)/2+O43,0) -> 22.5 | V43: =IF(ABS(L43-U43)<0.001,"OK","ERREUR") -> OK
A44: ARM003 | B44: Stylet | C44: 1 | D44: Légères | E44: =IF(M44=0,0,M44+O44) -> 1 | F44: =IF(M44=0,0,M44*N44+O44) -> 4 | G44: =ROUND(Catalogue!G6*SQRT((1+Paramètres!$B$4*(C44-1)+Paramètres!$B$5*(C44-1)^2)),0) -> 0 | H44: =ROUND(Catalogue!H6*SQRT((1+Paramètres!$B$4*(C44-1)+Paramètres!$B$5*(C44-1)^2)),0) -> 0 | I44: 2 | J44: 1 | K44: 0.25 | L44: =IF(M44=0,0,(E44+F44)/2) -> 2.5 | M44: 1 | N44: 4 | O44: 0 | P44: =IF(M44=0,"—",M44&"d"&N44&IF(O44=0,""," + "&O44)) -> 1d4 | Q44: =ROUND(INDEX(Catalogue!E$4:E$85,MATCH(A44,Catalogue!A$4:A$85,0))*(1+Paramètres!$B$4*(C44-1)+Paramètres!$B$5*(C44-1)^2),0) -> 1 | R44: =ROUND(INDEX(Catalogue!F$4:F$85,MATCH(A44,Catalogue!A$4:A$85,0))*(1+Paramètres!$B$4*(C44-1)+Paramètres!$B$5*(C44-1)^2),0) -> 4 | S44: =L44-AVERAGE(Q44:R44) -> 0 | T44: =IF(M44=0,IF(AND(N44=0,O44=0,E44=0,F44=0),"OK","ERREUR"),IF(AND(M44>=1,M44<=32,OR(N44=4,N44=6,N44=8,N44=10,N44=12,N44=20),O44>=0,E44=M44+O44,F44=M44*N44+O44),"OK","ERREUR")) -> OK | U44: =IF(M44>0,M44*(N44+1)/2+O44,0) -> 2.5 | V44: =IF(ABS(L44-U44)<0.001,"OK","ERREUR") -> OK
A45: ARM003 | B45: Stylet | C45: 2 | D45: Légères | E45: =IF(M45=0,0,M45+O45) -> 1 | F45: =IF(M45=0,0,M45*N45+O45) -> 4 | G45: =ROUND(Catalogue!G6*SQRT((1+Paramètres!$B$4*(C45-1)+Paramètres!$B$5*(C45-1)^2)),0) -> 0 | H45: =ROUND(Catalogue!H6*SQRT((1+Paramètres!$B$4*(C45-1)+Paramètres!$B$5*(C45-1)^2)),0) -> 0 | I45: 2 | J45: 1 | K45: 0.25 | L45: =IF(M45=0,0,(E45+F45)/2) -> 2.5 | M45: 1 | N45: 4 | O45: 0 | P45: =IF(M45=0,"—",M45&"d"&N45&IF(O45=0,""," + "&O45)) -> 1d4 | Q45: =ROUND(INDEX(Catalogue!E$4:E$85,MATCH(A45,Catalogue!A$4:A$85,0))*(1+Paramètres!$B$4*(C45-1)+Paramètres!$B$5*(C45-1)^2),0) -> 1 | R45: =ROUND(INDEX(Catalogue!F$4:F$85,MATCH(A45,Catalogue!A$4:A$85,0))*(1+Paramètres!$B$4*(C45-1)+Paramètres!$B$5*(C45-1)^2),0) -> 5 | S45: =L45-AVERAGE(Q45:R45) -> -0.5 | T45: =IF(M45=0,IF(AND(N45=0,O45=0,E45=0,F45=0),"OK","ERREUR"),IF(AND(M45>=1,M45<=32,OR(N45=4,N45=6,N45=8,N45=10,N45=12,N45=20),O45>=0,E45=M45+O45,F45=M45*N45+O45),"OK","ERREUR")) -> OK | U45: =IF(M45>0,M45*(N45+1)/2+O45,0) -> 2.5 | V45: =IF(ABS(L45-U45)<0.001,"OK","ERREUR") -> OK
A46: ARM003 | B46: Stylet | C46: 3 | D46: Légères | E46: =IF(M46=0,0,M46+O46) -> 1 | F46: =IF(M46=0,0,M46*N46+O46) -> 4 | G46: =ROUND(Catalogue!G6*SQRT((1+Paramètres!$B$4*(C46-1)+Paramètres!$B$5*(C46-1)^2)),0) -> 0 | H46: =ROUND(Catalogue!H6*SQRT((1+Paramètres!$B$4*(C46-1)+Paramètres!$B$5*(C46-1)^2)),0) -> 0 | I46: 2 | J46: 1 | K46: 0.25 | L46: =IF(M46=0,0,(E46+F46)/2) -> 2.5 | M46: 1 | N46: 4 | O46: 0 | P46: =IF(M46=0,"—",M46&"d"&N46&IF(O46=0,""," + "&O46)) -> 1d4 | Q46: =ROUND(INDEX(Catalogue!E$4:E$85,MATCH(A46,Catalogue!A$4:A$85,0))*(1+Paramètres!$B$4*(C46-1)+Paramètres!$B$5*(C46-1)^2),0) -> 1 | R46: =ROUND(INDEX(Catalogue!F$4:F$85,MATCH(A46,Catalogue!A$4:A$85,0))*(1+Paramètres!$B$4*(C46-1)+Paramètres!$B$5*(C46-1)^2),0) -> 5 | S46: =L46-AVERAGE(Q46:R46) -> -0.5 | T46: =IF(M46=0,IF(AND(N46=0,O46=0,E46=0,F46=0),"OK","ERREUR"),IF(AND(M46>=1,M46<=32,OR(N46=4,N46=6,N46=8,N46=10,N46=12,N46=20),O46>=0,E46=M46+O46,F46=M46*N46+O46),"OK","ERREUR")) -> OK | U46: =IF(M46>0,M46*(N46+1)/2+O46,0) -> 2.5 | V46: =IF(ABS(L46-U46)<0.001,"OK","ERREUR") -> OK
A47: ARM003 | B47: Stylet | C47: 4 | D47: Légères | E47: =IF(M47=0,0,M47+O47) -> 1 | F47: =IF(M47=0,0,M47*N47+O47) -> 6 | G47: =ROUND(Catalogue!G6*SQRT((1+Paramètres!$B$4*(C47-1)+Paramètres!$B$5*(C47-1)^2)),0) -> 0 | H47: =ROUND(Catalogue!H6*SQRT((1+Paramètres!$B$4*(C47-1)+Paramètres!$B$5*(C47-1)^2)),0) -> 0 | I47: 2 | J47: 1 | K47: 0.25 | L47: =IF(M47=0,0,(E47+F47)/2) -> 3.5 | M47: 1 | N47: 6 | O47: 0 | P47: =IF(M47=0,"—",M47&"d"&N47&IF(O47=0,""," + "&O47)) -> 1d6 | Q47: =ROUND(INDEX(Catalogue!E$4:E$85,MATCH(A47,Catalogue!A$4:A$85,0))*(1+Paramètres!$B$4*(C47-1)+Paramètres!$B$5*(C47-1)^2),0) -> 1 | R47: =ROUND(INDEX(Catalogue!F$4:F$85,MATCH(A47,Catalogue!A$4:A$85,0))*(1+Paramètres!$B$4*(C47-1)+Paramètres!$B$5*(C47-1)^2),0) -> 6 | S47: =L47-AVERAGE(Q47:R47) -> 0 | T47: =IF(M47=0,IF(AND(N47=0,O47=0,E47=0,F47=0),"OK","ERREUR"),IF(AND(M47>=1,M47<=32,OR(N47=4,N47=6,N47=8,N47=10,N47=12,N47=20),O47>=0,E47=M47+O47,F47=M47*N47+O47),"OK","ERREUR")) -> OK | U47: =IF(M47>0,M47*(N47+1)/2+O47,0) -> 3.5 | V47: =IF(ABS(L47-U47)<0.001,"OK","ERREUR") -> OK
A48: ARM003 | B48: Stylet | C48: 5 | D48: Légères | E48: =IF(M48=0,0,M48+O48) -> 2 | F48: =IF(M48=0,0,M48*N48+O48) -> 7 | G48: =ROUND(Catalogue!G6*SQRT((1+Paramètres!$B$4*(C48-1)+Paramètres!$B$5*(C48-1)^2)),0) -> 0 | H48: =ROUND(Catalogue!H6*SQRT((1+Paramètres!$B$4*(C48-1)+Paramètres!$B$5*(C48-1)^2)),0) -> 0 | I48: 2 | J48: 1 | K48: 0.25 | L48: =IF(M48=0,0,(E48+F48)/2) -> 4.5 | M48: 1 | N48: 6 | O48: 1 | P48: =IF(M48=0,"—",M48&"d"&N48&IF(O48=0,""," + "&O48)) -> 1d6 + 1 | Q48: =ROUND(INDEX(Catalogue!E$4:E$85,MATCH(A48,Catalogue!A$4:A$85,0))*(1+Paramètres!$B$4*(C48-1)+Paramètres!$B$5*(C48-1)^2),0) -> 2 | R48: =ROUND(INDEX(Catalogue!F$4:F$85,MATCH(A48,Catalogue!A$4:A$85,0))*(1+Paramètres!$B$4*(C48-1)+Paramètres!$B$5*(C48-1)^2),0) -> 7 | S48: =L48-AVERAGE(Q48:R48) -> 0 | T48: =IF(M48=0,IF(AND(N48=0,O48=0,E48=0,F48=0),"OK","ERREUR"),IF(AND(M48>=1,M48<=32,OR(N48=4,N48=6,N48=8,N48=10,N48=12,N48=20),O48>=0,E48=M48+O48,F48=M48*N48+O48),"OK","ERREUR")) -> OK | U48: =IF(M48>0,M48*(N48+1)/2+O48,0) -> 4.5 | V48: =IF(ABS(L48-U48)<0.001,"OK","ERREUR") -> OK
A49: ARM003 | B49: Stylet | C49: 6 | D49: Légères | E49: =IF(M49=0,0,M49+O49) -> 2 | F49: =IF(M49=0,0,M49*N49+O49) -> 8 | G49: =ROUND(Catalogue!G6*SQRT((1+Paramètres!$B$4*(C49-1)+Paramètres!$B$5*(C49-1)^2)),0) -> 0 | H49: =ROUND(Catalogue!H6*SQRT((1+Paramètres!$B$4*(C49-1)+Paramètres!$B$5*(C49-1)^2)),0) -> 0 | I49: 2 | J49: 1 | K49: 0.25 | L49: =IF(M49=0,0,(E49+F49)/2) -> 5 | M49: 2 | N49: 4 | O49: 0 | P49: =IF(M49=0,"—",M49&"d"&N49&IF(O49=0,""," + "&O49)) -> 2d4 | Q49: =ROUND(INDEX(Catalogue!E$4:E$85,MATCH(A49,Catalogue!A$4:A$85,0))*(1+Paramètres!$B$4*(C49-1)+Paramètres!$B$5*(C49-1)^2),0) -> 2 | R49: =ROUND(INDEX(Catalogue!F$4:F$85,MATCH(A49,Catalogue!A$4:A$85,0))*(1+Paramètres!$B$4*(C49-1)+Paramètres!$B$5*(C49-1)^2),0) -> 8 | S49: =L49-AVERAGE(Q49:R49) -> 0 | T49: =IF(M49=0,IF(AND(N49=0,O49=0,E49=0,F49=0),"OK","ERREUR"),IF(AND(M49>=1,M49<=32,OR(N49=4,N49=6,N49=8,N49=10,N49=12,N49=20),O49>=0,E49=M49+O49,F49=M49*N49+O49),"OK","ERREUR")) -> OK | U49: =IF(M49>0,M49*(N49+1)/2+O49,0) -> 5 | V49: =IF(ABS(L49-U49)<0.001,"OK","ERREUR") -> OK
A50: ARM003 | B50: Stylet | C50: 7 | D50: Légères | E50: =IF(M50=0,0,M50+O50) -> 2 | F50: =IF(M50=0,0,M50*N50+O50) -> 9 | G50: =ROUND(Catalogue!G6*SQRT((1+Paramètres!$B$4*(C50-1)+Paramètres!$B$5*(C50-1)^2)),0) -> 0 | H50: =ROUND(Catalogue!H6*SQRT((1+Paramètres!$B$4*(C50-1)+Paramètres!$B$5*(C50-1)^2)),0) -> 0 | I50: 2 | J50: 1 | K50: 0.25 | L50: =IF(M50=0,0,(E50+F50)/2) -> 5.5 | M50: 1 | N50: 8 | O50: 1 | P50: =IF(M50=0,"—",M50&"d"&N50&IF(O50=0,""," + "&O50)) -> 1d8 + 1 | Q50: =ROUND(INDEX(Catalogue!E$4:E$85,MATCH(A50,Catalogue!A$4:A$85,0))*(1+Paramètres!$B$4*(C50-1)+Paramètres!$B$5*(C50-1)^2),0) -> 2 | R50: =ROUND(INDEX(Catalogue!F$4:F$85,MATCH(A50,Catalogue!A$4:A$85,0))*(1+Paramètres!$B$4*(C50-1)+Paramètres!$B$5*(C50-1)^2),0) -> 9 | S50: =L50-AVERAGE(Q50:R50) -> 0 | T50: =IF(M50=0,IF(AND(N50=0,O50=0,E50=0,F50=0),"OK","ERREUR"),IF(AND(M50>=1,M50<=32,OR(N50=4,N50=6,N50=8,N50=10,N50=12,N50=20),O50>=0,E50=M50+O50,F50=M50*N50+O50),"OK","ERREUR")) -> OK | U50: =IF(M50>0,M50*(N50+1)/2+O50,0) -> 5.5 | V50: =IF(ABS(L50-U50)<0.001,"OK","ERREUR") -> OK
A51: ARM003 | B51: Stylet | C51: 8 | D51: Légères | E51: =IF(M51=0,0,M51+O51) -> 3 | F51: =IF(M51=0,0,M51*N51+O51) -> 10 | G51: =ROUND(Catalogue!G6*SQRT((1+Paramètres!$B$4*(C51-1)+Paramètres!$B$5*(C51-1)^2)),0) -> 0 | H51: =ROUND(Catalogue!H6*SQRT((1+Paramètres!$B$4*(C51-1)+Paramètres!$B$5*(C51-1)^2)),0) -> 0 | I51: 2 | J51: 1 | K51: 0.25 | L51: =IF(M51=0,0,(E51+F51)/2) -> 6.5 | M51: 1 | N51: 8 | O51: 2 | P51: =IF(M51=0,"—",M51&"d"&N51&IF(O51=0,""," + "&O51)) -> 1d8 + 2 | Q51: =ROUND(INDEX(Catalogue!E$4:E$85,MATCH(A51,Catalogue!A$4:A$85,0))*(1+Paramètres!$B$4*(C51-1)+Paramètres!$B$5*(C51-1)^2),0) -> 3 | R51: =ROUND(INDEX(Catalogue!F$4:F$85,MATCH(A51,Catalogue!A$4:A$85,0))*(1+Paramètres!$B$4*(C51-1)+Paramètres!$B$5*(C51-1)^2),0) -> 10 | S51: =L51-AVERAGE(Q51:R51) -> 0 | T51: =IF(M51=0,IF(AND(N51=0,O51=0,E51=0,F51=0),"OK","ERREUR"),IF(AND(M51>=1,M51<=32,OR(N51=4,N51=6,N51=8,N51=10,N51=12,N51=20),O51>=0,E51=M51+O51,F51=M51*N51+O51),"OK","ERREUR")) -> OK | U51: =IF(M51>0,M51*(N51+1)/2+O51,0) -> 6.5 | V51: =IF(ABS(L51-U51)<0.001,"OK","ERREUR") -> OK
A52: ARM003 | B52: Stylet | C52: 9 | D52: Légères | E52: =IF(M52=0,0,M52+O52) -> 3 | F52: =IF(M52=0,0,M52*N52+O52) -> 12 | G52: =ROUND(Catalogue!G6*SQRT((1+Paramètres!$B$4*(C52-1)+Paramètres!$B$5*(C52-1)^2)),0) -> 0 | H52: =ROUND(Catalogue!H6*SQRT((1+Paramètres!$B$4*(C52-1)+Paramètres!$B$5*(C52-1)^2)),0) -> 0 | I52: 2 | J52: 1 | K52: 0.25 | L52: =IF(M52=0,0,(E52+F52)/2) -> 7.5 | M52: 3 | N52: 4 | O52: 0 | P52: =IF(M52=0,"—",M52&"d"&N52&IF(O52=0,""," + "&O52)) -> 3d4 | Q52: =ROUND(INDEX(Catalogue!E$4:E$85,MATCH(A52,Catalogue!A$4:A$85,0))*(1+Paramètres!$B$4*(C52-1)+Paramètres!$B$5*(C52-1)^2),0) -> 3 | R52: =ROUND(INDEX(Catalogue!F$4:F$85,MATCH(A52,Catalogue!A$4:A$85,0))*(1+Paramètres!$B$4*(C52-1)+Paramètres!$B$5*(C52-1)^2),0) -> 12 | S52: =L52-AVERAGE(Q52:R52) -> 0 | T52: =IF(M52=0,IF(AND(N52=0,O52=0,E52=0,F52=0),"OK","ERREUR"),IF(AND(M52>=1,M52<=32,OR(N52=4,N52=6,N52=8,N52=10,N52=12,N52=20),O52>=0,E52=M52+O52,F52=M52*N52+O52),"OK","ERREUR")) -> OK | U52: =IF(M52>0,M52*(N52+1)/2+O52,0) -> 7.5 | V52: =IF(ABS(L52-U52)<0.001,"OK","ERREUR") -> OK
A53: ARM003 | B53: Stylet | C53: 10 | D53: Légères | E53: =IF(M53=0,0,M53+O53) -> 3 | F53: =IF(M53=0,0,M53*N53+O53) -> 13 | G53: =ROUND(Catalogue!G6*SQRT((1+Paramètres!$B$4*(C53-1)+Paramètres!$B$5*(C53-1)^2)),0) -> 0 | H53: =ROUND(Catalogue!H6*SQRT((1+Paramètres!$B$4*(C53-1)+Paramètres!$B$5*(C53-1)^2)),0) -> 0 | I53: 2 | J53: 1 | K53: 0.25 | L53: =IF(M53=0,0,(E53+F53)/2) -> 8 | M53: 2 | N53: 6 | O53: 1 | P53: =IF(M53=0,"—",M53&"d"&N53&IF(O53=0,""," + "&O53)) -> 2d6 + 1 | Q53: =ROUND(INDEX(Catalogue!E$4:E$85,MATCH(A53,Catalogue!A$4:A$85,0))*(1+Paramètres!$B$4*(C53-1)+Paramètres!$B$5*(C53-1)^2),0) -> 3 | R53: =ROUND(INDEX(Catalogue!F$4:F$85,MATCH(A53,Catalogue!A$4:A$85,0))*(1+Paramètres!$B$4*(C53-1)+Paramètres!$B$5*(C53-1)^2),0) -> 13 | S53: =L53-AVERAGE(Q53:R53) -> 0 | T53: =IF(M53=0,IF(AND(N53=0,O53=0,E53=0,F53=0),"OK","ERREUR"),IF(AND(M53>=1,M53<=32,OR(N53=4,N53=6,N53=8,N53=10,N53=12,N53=20),O53>=0,E53=M53+O53,F53=M53*N53+O53),"OK","ERREUR")) -> OK | U53: =IF(M53>0,M53*(N53+1)/2+O53,0) -> 8 | V53: =IF(ABS(L53-U53)<0.001,"OK","ERREUR") -> OK
A54: ARM003 | B54: Stylet | C54: 11 | D54: Légères | E54: =IF(M54=0,0,M54+O54) -> 4 | F54: =IF(M54=0,0,M54*N54+O54) -> 14 | G54: =ROUND(Catalogue!G6*SQRT((1+Paramètres!$B$4*(C54-1)+Paramètres!$B$5*(C54-1)^2)),0) -> 0 | H54: =ROUND(Catalogue!H6*SQRT((1+Paramètres!$B$4*(C54-1)+Paramètres!$B$5*(C54-1)^2)),0) -> 0 | I54: 2 | J54: 1 | K54: 0.25 | L54: =IF(M54=0,0,(E54+F54)/2) -> 9 | M54: 2 | N54: 6 | O54: 2 | P54: =IF(M54=0,"—",M54&"d"&N54&IF(O54=0,""," + "&O54)) -> 2d6 + 2 | Q54: =ROUND(INDEX(Catalogue!E$4:E$85,MATCH(A54,Catalogue!A$4:A$85,0))*(1+Paramètres!$B$4*(C54-1)+Paramètres!$B$5*(C54-1)^2),0) -> 4 | R54: =ROUND(INDEX(Catalogue!F$4:F$85,MATCH(A54,Catalogue!A$4:A$85,0))*(1+Paramètres!$B$4*(C54-1)+Paramètres!$B$5*(C54-1)^2),0) -> 15 | S54: =L54-AVERAGE(Q54:R54) -> -0.5 | T54: =IF(M54=0,IF(AND(N54=0,O54=0,E54=0,F54=0),"OK","ERREUR"),IF(AND(M54>=1,M54<=32,OR(N54=4,N54=6,N54=8,N54=10,N54=12,N54=20),O54>=0,E54=M54+O54,F54=M54*N54+O54),"OK","ERREUR")) -> OK | U54: =IF(M54>0,M54*(N54+1)/2+O54,0) -> 9 | V54: =IF(ABS(L54-U54)<0.001,"OK","ERREUR") -> OK
A55: ARM003 | B55: Stylet | C55: 12 | D55: Légères | E55: =IF(M55=0,0,M55+O55) -> 3 | F55: =IF(M55=0,0,M55*N55+O55) -> 17 | G55: =ROUND(Catalogue!G6*SQRT((1+Paramètres!$B$4*(C55-1)+Paramètres!$B$5*(C55-1)^2)),0) -> 0 | H55: =ROUND(Catalogue!H6*SQRT((1+Paramètres!$B$4*(C55-1)+Paramètres!$B$5*(C55-1)^2)),0) -> 0 | I55: 2 | J55: 1 | K55: 0.25 | L55: =IF(M55=0,0,(E55+F55)/2) -> 10 | M55: 2 | N55: 8 | O55: 1 | P55: =IF(M55=0,"—",M55&"d"&N55&IF(O55=0,""," + "&O55)) -> 2d8 + 1 | Q55: =ROUND(INDEX(Catalogue!E$4:E$85,MATCH(A55,Catalogue!A$4:A$85,0))*(1+Paramètres!$B$4*(C55-1)+Paramètres!$B$5*(C55-1)^2),0) -> 4 | R55: =ROUND(INDEX(Catalogue!F$4:F$85,MATCH(A55,Catalogue!A$4:A$85,0))*(1+Paramètres!$B$4*(C55-1)+Paramètres!$B$5*(C55-1)^2),0) -> 17 | S55: =L55-AVERAGE(Q55:R55) -> -0.5 | T55: =IF(M55=0,IF(AND(N55=0,O55=0,E55=0,F55=0),"OK","ERREUR"),IF(AND(M55>=1,M55<=32,OR(N55=4,N55=6,N55=8,N55=10,N55=12,N55=20),O55>=0,E55=M55+O55,F55=M55*N55+O55),"OK","ERREUR")) -> OK | U55: =IF(M55>0,M55*(N55+1)/2+O55,0) -> 10 | V55: =IF(ABS(L55-U55)<0.001,"OK","ERREUR") -> OK
A56: ARM003 | B56: Stylet | C56: 13 | D56: Légères | E56: =IF(M56=0,0,M56+O56) -> 4 | F56: =IF(M56=0,0,M56*N56+O56) -> 18 | G56: =ROUND(Catalogue!G6*SQRT((1+Paramètres!$B$4*(C56-1)+Paramètres!$B$5*(C56-1)^2)),0) -> 0 | H56: =ROUND(Catalogue!H6*SQRT((1+Paramètres!$B$4*(C56-1)+Paramètres!$B$5*(C56-1)^2)),0) -> 0 | I56: 2 | J56: 1 | K56: 0.25 | L56: =IF(M56=0,0,(E56+F56)/2) -> 11 | M56: 2 | N56: 8 | O56: 2 | P56: =IF(M56=0,"—",M56&"d"&N56&IF(O56=0,""," + "&O56)) -> 2d8 + 2 | Q56: =ROUND(INDEX(Catalogue!E$4:E$85,MATCH(A56,Catalogue!A$4:A$85,0))*(1+Paramètres!$B$4*(C56-1)+Paramètres!$B$5*(C56-1)^2),0) -> 5 | R56: =ROUND(INDEX(Catalogue!F$4:F$85,MATCH(A56,Catalogue!A$4:A$85,0))*(1+Paramètres!$B$4*(C56-1)+Paramètres!$B$5*(C56-1)^2),0) -> 18 | S56: =L56-AVERAGE(Q56:R56) -> -0.5 | T56: =IF(M56=0,IF(AND(N56=0,O56=0,E56=0,F56=0),"OK","ERREUR"),IF(AND(M56>=1,M56<=32,OR(N56=4,N56=6,N56=8,N56=10,N56=12,N56=20),O56>=0,E56=M56+O56,F56=M56*N56+O56),"OK","ERREUR")) -> OK | U56: =IF(M56>0,M56*(N56+1)/2+O56,0) -> 11 | V56: =IF(ABS(L56-U56)<0.001,"OK","ERREUR") -> OK
A57: ARM003 | B57: Stylet | C57: 14 | D57: Légères | E57: =IF(M57=0,0,M57+O57) -> 5 | F57: =IF(M57=0,0,M57*N57+O57) -> 20 | G57: =ROUND(Catalogue!G6*SQRT((1+Paramètres!$B$4*(C57-1)+Paramètres!$B$5*(C57-1)^2)),0) -> 0 | H57: =ROUND(Catalogue!H6*SQRT((1+Paramètres!$B$4*(C57-1)+Paramètres!$B$5*(C57-1)^2)),0) -> 0 | I57: 2 | J57: 1 | K57: 0.25 | L57: =IF(M57=0,0,(E57+F57)/2) -> 12.5 | M57: 3 | N57: 6 | O57: 2 | P57: =IF(M57=0,"—",M57&"d"&N57&IF(O57=0,""," + "&O57)) -> 3d6 + 2 | Q57: =ROUND(INDEX(Catalogue!E$4:E$85,MATCH(A57,Catalogue!A$4:A$85,0))*(1+Paramètres!$B$4*(C57-1)+Paramètres!$B$5*(C57-1)^2),0) -> 5 | R57: =ROUND(INDEX(Catalogue!F$4:F$85,MATCH(A57,Catalogue!A$4:A$85,0))*(1+Paramètres!$B$4*(C57-1)+Paramètres!$B$5*(C57-1)^2),0) -> 21 | S57: =L57-AVERAGE(Q57:R57) -> -0.5 | T57: =IF(M57=0,IF(AND(N57=0,O57=0,E57=0,F57=0),"OK","ERREUR"),IF(AND(M57>=1,M57<=32,OR(N57=4,N57=6,N57=8,N57=10,N57=12,N57=20),O57>=0,E57=M57+O57,F57=M57*N57+O57),"OK","ERREUR")) -> OK | U57: =IF(M57>0,M57*(N57+1)/2+O57,0) -> 12.5 | V57: =IF(ABS(L57-U57)<0.001,"OK","ERREUR") -> OK
A58: ARM003 | B58: Stylet | C58: 15 | D58: Légères | E58: =IF(M58=0,0,M58+O58) -> 5 | F58: =IF(M58=0,0,M58*N58+O58) -> 23 | G58: =ROUND(Catalogue!G6*SQRT((1+Paramètres!$B$4*(C58-1)+Paramètres!$B$5*(C58-1)^2)),0) -> 0 | H58: =ROUND(Catalogue!H6*SQRT((1+Paramètres!$B$4*(C58-1)+Paramètres!$B$5*(C58-1)^2)),0) -> 0 | I58: 2 | J58: 1 | K58: 0.25 | L58: =IF(M58=0,0,(E58+F58)/2) -> 14 | M58: 2 | N58: 10 | O58: 3 | P58: =IF(M58=0,"—",M58&"d"&N58&IF(O58=0,""," + "&O58)) -> 2d10 + 3 | Q58: =ROUND(INDEX(Catalogue!E$4:E$85,MATCH(A58,Catalogue!A$4:A$85,0))*(1+Paramètres!$B$4*(C58-1)+Paramètres!$B$5*(C58-1)^2),0) -> 6 | R58: =ROUND(INDEX(Catalogue!F$4:F$85,MATCH(A58,Catalogue!A$4:A$85,0))*(1+Paramètres!$B$4*(C58-1)+Paramètres!$B$5*(C58-1)^2),0) -> 23 | S58: =L58-AVERAGE(Q58:R58) -> -0.5 | T58: =IF(M58=0,IF(AND(N58=0,O58=0,E58=0,F58=0),"OK","ERREUR"),IF(AND(M58>=1,M58<=32,OR(N58=4,N58=6,N58=8,N58=10,N58=12,N58=20),O58>=0,E58=M58+O58,F58=M58*N58+O58),"OK","ERREUR")) -> OK | U58: =IF(M58>0,M58*(N58+1)/2+O58,0) -> 14 | V58: =IF(ABS(L58-U58)<0.001,"OK","ERREUR") -> OK
A59: ARM003 | B59: Stylet | C59: 16 | D59: Légères | E59: =IF(M59=0,0,M59+O59) -> 6 | F59: =IF(M59=0,0,M59*N59+O59) -> 24 | G59: =ROUND(Catalogue!G6*SQRT((1+Paramètres!$B$4*(C59-1)+Paramètres!$B$5*(C59-1)^2)),0) -> 0 | H59: =ROUND(Catalogue!H6*SQRT((1+Paramètres!$B$4*(C59-1)+Paramètres!$B$5*(C59-1)^2)),0) -> 0 | I59: 2 | J59: 1 | K59: 0.25 | L59: =IF(M59=0,0,(E59+F59)/2) -> 15 | M59: 2 | N59: 10 | O59: 4 | P59: =IF(M59=0,"—",M59&"d"&N59&IF(O59=0,""," + "&O59)) -> 2d10 + 4 | Q59: =ROUND(INDEX(Catalogue!E$4:E$85,MATCH(A59,Catalogue!A$4:A$85,0))*(1+Paramètres!$B$4*(C59-1)+Paramètres!$B$5*(C59-1)^2),0) -> 6 | R59: =ROUND(INDEX(Catalogue!F$4:F$85,MATCH(A59,Catalogue!A$4:A$85,0))*(1+Paramètres!$B$4*(C59-1)+Paramètres!$B$5*(C59-1)^2),0) -> 25 | S59: =L59-AVERAGE(Q59:R59) -> -0.5 | T59: =IF(M59=0,IF(AND(N59=0,O59=0,E59=0,F59=0),"OK","ERREUR"),IF(AND(M59>=1,M59<=32,OR(N59=4,N59=6,N59=8,N59=10,N59=12,N59=20),O59>=0,E59=M59+O59,F59=M59*N59+O59),"OK","ERREUR")) -> OK | U59: =IF(M59>0,M59*(N59+1)/2+O59,0) -> 15 | V59: =IF(ABS(L59-U59)<0.001,"OK","ERREUR") -> OK
A60: ARM003 | B60: Stylet | C60: 17 | D60: Légères | E60: =IF(M60=0,0,M60+O60) -> 7 | F60: =IF(M60=0,0,M60*N60+O60) -> 27 | G60: =ROUND(Catalogue!G6*SQRT((1+Paramètres!$B$4*(C60-1)+Paramètres!$B$5*(C60-1)^2)),0) -> 0 | H60: =ROUND(Catalogue!H6*SQRT((1+Paramètres!$B$4*(C60-1)+Paramètres!$B$5*(C60-1)^2)),0) -> 0 | I60: 2 | J60: 1 | K60: 0.25 | L60: =IF(M60=0,0,(E60+F60)/2) -> 17 | M60: 4 | N60: 6 | O60: 3 | P60: =IF(M60=0,"—",M60&"d"&N60&IF(O60=0,""," + "&O60)) -> 4d6 + 3 | Q60: =ROUND(INDEX(Catalogue!E$4:E$85,MATCH(A60,Catalogue!A$4:A$85,0))*(1+Paramètres!$B$4*(C60-1)+Paramètres!$B$5*(C60-1)^2),0) -> 7 | R60: =ROUND(INDEX(Catalogue!F$4:F$85,MATCH(A60,Catalogue!A$4:A$85,0))*(1+Paramètres!$B$4*(C60-1)+Paramètres!$B$5*(C60-1)^2),0) -> 27 | S60: =L60-AVERAGE(Q60:R60) -> 0 | T60: =IF(M60=0,IF(AND(N60=0,O60=0,E60=0,F60=0),"OK","ERREUR"),IF(AND(M60>=1,M60<=32,OR(N60=4,N60=6,N60=8,N60=10,N60=12,N60=20),O60>=0,E60=M60+O60,F60=M60*N60+O60),"OK","ERREUR")) -> OK | U60: =IF(M60>0,M60*(N60+1)/2+O60,0) -> 17 | V60: =IF(ABS(L60-U60)<0.001,"OK","ERREUR") -> OK
A61: ARM003 | B61: Stylet | C61: 18 | D61: Légères | E61: =IF(M61=0,0,M61+O61) -> 8 | F61: =IF(M61=0,0,M61*N61+O61) -> 29 | G61: =ROUND(Catalogue!G6*SQRT((1+Paramètres!$B$4*(C61-1)+Paramètres!$B$5*(C61-1)^2)),0) -> 0 | H61: =ROUND(Catalogue!H6*SQRT((1+Paramètres!$B$4*(C61-1)+Paramètres!$B$5*(C61-1)^2)),0) -> 0 | I61: 2 | J61: 1 | K61: 0.25 | L61: =IF(M61=0,0,(E61+F61)/2) -> 18.5 | M61: 3 | N61: 8 | O61: 5 | P61: =IF(M61=0,"—",M61&"d"&N61&IF(O61=0,""," + "&O61)) -> 3d8 + 5 | Q61: =ROUND(INDEX(Catalogue!E$4:E$85,MATCH(A61,Catalogue!A$4:A$85,0))*(1+Paramètres!$B$4*(C61-1)+Paramètres!$B$5*(C61-1)^2),0) -> 7 | R61: =ROUND(INDEX(Catalogue!F$4:F$85,MATCH(A61,Catalogue!A$4:A$85,0))*(1+Paramètres!$B$4*(C61-1)+Paramètres!$B$5*(C61-1)^2),0) -> 30 | S61: =L61-AVERAGE(Q61:R61) -> 0 | T61: =IF(M61=0,IF(AND(N61=0,O61=0,E61=0,F61=0),"OK","ERREUR"),IF(AND(M61>=1,M61<=32,OR(N61=4,N61=6,N61=8,N61=10,N61=12,N61=20),O61>=0,E61=M61+O61,F61=M61*N61+O61),"OK","ERREUR")) -> OK | U61: =IF(M61>0,M61*(N61+1)/2+O61,0) -> 18.5 | V61: =IF(ABS(L61-U61)<0.001,"OK","ERREUR") -> OK
A62: ARM003 | B62: Stylet | C62: 19 | D62: Légères | E62: =IF(M62=0,0,M62+O62) -> 8 | F62: =IF(M62=0,0,M62*N62+O62) -> 33 | G62: =ROUND(Catalogue!G6*SQRT((1+Paramètres!$B$4*(C62-1)+Paramètres!$B$5*(C62-1)^2)),0) -> 0 | H62: =ROUND(Catalogue!H6*SQRT((1+Paramètres!$B$4*(C62-1)+Paramètres!$B$5*(C62-1)^2)),0) -> 0 | I62: 2 | J62: 1 | K62: 0.25 | L62: =IF(M62=0,0,(E62+F62)/2) -> 20.5 | M62: 5 | N62: 6 | O62: 3 | P62: =IF(M62=0,"—",M62&"d"&N62&IF(O62=0,""," + "&O62)) -> 5d6 + 3 | Q62: =ROUND(INDEX(Catalogue!E$4:E$85,MATCH(A62,Catalogue!A$4:A$85,0))*(1+Paramètres!$B$4*(C62-1)+Paramètres!$B$5*(C62-1)^2),0) -> 8 | R62: =ROUND(INDEX(Catalogue!F$4:F$85,MATCH(A62,Catalogue!A$4:A$85,0))*(1+Paramètres!$B$4*(C62-1)+Paramètres!$B$5*(C62-1)^2),0) -> 33 | S62: =L62-AVERAGE(Q62:R62) -> 0 | T62: =IF(M62=0,IF(AND(N62=0,O62=0,E62=0,F62=0),"OK","ERREUR"),IF(AND(M62>=1,M62<=32,OR(N62=4,N62=6,N62=8,N62=10,N62=12,N62=20),O62>=0,E62=M62+O62,F62=M62*N62+O62),"OK","ERREUR")) -> OK | U62: =IF(M62>0,M62*(N62+1)/2+O62,0) -> 20.5 | V62: =IF(ABS(L62-U62)<0.001,"OK","ERREUR") -> OK
A63: ARM003 | B63: Stylet | C63: 20 | D63: Légères | E63: =IF(M63=0,0,M63+O63) -> 8 | F63: =IF(M63=0,0,M63*N63+O63) -> 35 | G63: =ROUND(Catalogue!G6*SQRT((1+Paramètres!$B$4*(C63-1)+Paramètres!$B$5*(C63-1)^2)),0) -> 0 | H63: =ROUND(Catalogue!H6*SQRT((1+Paramètres!$B$4*(C63-1)+Paramètres!$B$5*(C63-1)^2)),0) -> 0 | I63: 2 | J63: 1 | K63: 0.25 | L63: =IF(M63=0,0,(E63+F63)/2) -> 21.5 | M63: 3 | N63: 10 | O63: 5 | P63: =IF(M63=0,"—",M63&"d"&N63&IF(O63=0,""," + "&O63)) -> 3d10 + 5 | Q63: =ROUND(INDEX(Catalogue!E$4:E$85,MATCH(A63,Catalogue!A$4:A$85,0))*(1+Paramètres!$B$4*(C63-1)+Paramètres!$B$5*(C63-1)^2),0) -> 9 | R63: =ROUND(INDEX(Catalogue!F$4:F$85,MATCH(A63,Catalogue!A$4:A$85,0))*(1+Paramètres!$B$4*(C63-1)+Paramètres!$B$5*(C63-1)^2),0) -> 35 | S63: =L63-AVERAGE(Q63:R63) -> -0.5 | T63: =IF(M63=0,IF(AND(N63=0,O63=0,E63=0,F63=0),"OK","ERREUR"),IF(AND(M63>=1,M63<=32,OR(N63=4,N63=6,N63=8,N63=10,N63=12,N63=20),O63>=0,E63=M63+O63,F63=M63*N63+O63),"OK","ERREUR")) -> OK | U63: =IF(M63>0,M63*(N63+1)/2+O63,0) -> 21.5 | V63: =IF(ABS(L63-U63)<0.001,"OK","ERREUR") -> OK
A64: ARM004 | B64: Kriss | C64: 1 | D64: Légères | E64: =IF(M64=0,0,M64+O64) -> 1 | F64: =IF(M64=0,0,M64*N64+O64) -> 4 | G64: =ROUND(Catalogue!G7*SQRT((1+Paramètres!$B$4*(C64-1)+Paramètres!$B$5*(C64-1)^2)),0) -> 0 | H64: =ROUND(Catalogue!H7*SQRT((1+Paramètres!$B$4*(C64-1)+Paramètres!$B$5*(C64-1)^2)),0) -> 0 | I64: 2 | J64: 1 | K64: 0.5 | L64: =IF(M64=0,0,(E64+F64)/2) -> 2.5 | M64: 1 | N64: 4 | O64: 0 | P64: =IF(M64=0,"—",M64&"d"&N64&IF(O64=0,""," + "&O64)) -> 1d4 | Q64: =ROUND(INDEX(Catalogue!E$4:E$85,MATCH(A64,Catalogue!A$4:A$85,0))*(1+Paramètres!$B$4*(C64-1)+Paramètres!$B$5*(C64-1)^2),0) -> 2 | R64: =ROUND(INDEX(Catalogue!F$4:F$85,MATCH(A64,Catalogue!A$4:A$85,0))*(1+Paramètres!$B$4*(C64-1)+Paramètres!$B$5*(C64-1)^2),0) -> 4 | S64: =L64-AVERAGE(Q64:R64) -> -0.5 | T64: =IF(M64=0,IF(AND(N64=0,O64=0,E64=0,F64=0),"OK","ERREUR"),IF(AND(M64>=1,M64<=32,OR(N64=4,N64=6,N64=8,N64=10,N64=12,N64=20),O64>=0,E64=M64+O64,F64=M64*N64+O64),"OK","ERREUR")) -> OK | U64: =IF(M64>0,M64*(N64+1)/2+O64,0) -> 2.5 | V64: =IF(ABS(L64-U64)<0.001,"OK","ERREUR") -> OK
A65: ARM004 | B65: Kriss | C65: 2 | D65: Légères | E65: =IF(M65=0,0,M65+O65) -> 2 | F65: =IF(M65=0,0,M65*N65+O65) -> 5 | G65: =ROUND(Catalogue!G7*SQRT((1+Paramètres!$B$4*(C65-1)+Paramètres!$B$5*(C65-1)^2)),0) -> 0 | H65: =ROUND(Catalogue!H7*SQRT((1+Paramètres!$B$4*(C65-1)+Paramètres!$B$5*(C65-1)^2)),0) -> 0 | I65: 2 | J65: 1 | K65: 0.5 | L65: =IF(M65=0,0,(E65+F65)/2) -> 3.5 | M65: 1 | N65: 4 | O65: 1 | P65: =IF(M65=0,"—",M65&"d"&N65&IF(O65=0,""," + "&O65)) -> 1d4 + 1 | Q65: =ROUND(INDEX(Catalogue!E$4:E$85,MATCH(A65,Catalogue!A$4:A$85,0))*(1+Paramètres!$B$4*(C65-1)+Paramètres!$B$5*(C65-1)^2),0) -> 2 | R65: =ROUND(INDEX(Catalogue!F$4:F$85,MATCH(A65,Catalogue!A$4:A$85,0))*(1+Paramètres!$B$4*(C65-1)+Paramètres!$B$5*(C65-1)^2),0) -> 5 | S65: =L65-AVERAGE(Q65:R65) -> 0 | T65: =IF(M65=0,IF(AND(N65=0,O65=0,E65=0,F65=0),"OK","ERREUR"),IF(AND(M65>=1,M65<=32,OR(N65=4,N65=6,N65=8,N65=10,N65=12,N65=20),O65>=0,E65=M65+O65,F65=M65*N65+O65),"OK","ERREUR")) -> OK | U65: =IF(M65>0,M65*(N65+1)/2+O65,0) -> 3.5 | V65: =IF(ABS(L65-U65)<0.001,"OK","ERREUR") -> OK
A66: ARM004 | B66: Kriss | C66: 3 | D66: Légères | E66: =IF(M66=0,0,M66+O66) -> 2 | F66: =IF(M66=0,0,M66*N66+O66) -> 5 | G66: =ROUND(Catalogue!G7*SQRT((1+Paramètres!$B$4*(C66-1)+Paramètres!$B$5*(C66-1)^2)),0) -> 0 | H66: =ROUND(Catalogue!H7*SQRT((1+Paramètres!$B$4*(C66-1)+Paramètres!$B$5*(C66-1)^2)),0) -> 0 | I66: 2 | J66: 1 | K66: 0.5 | L66: =IF(M66=0,0,(E66+F66)/2) -> 3.5 | M66: 1 | N66: 4 | O66: 1 | P66: =IF(M66=0,"—",M66&"d"&N66&IF(O66=0,""," + "&O66)) -> 1d4 + 1 | Q66: =ROUND(INDEX(Catalogue!E$4:E$85,MATCH(A66,Catalogue!A$4:A$85,0))*(1+Paramètres!$B$4*(C66-1)+Paramètres!$B$5*(C66-1)^2),0) -> 3 | R66: =ROUND(INDEX(Catalogue!F$4:F$85,MATCH(A66,Catalogue!A$4:A$85,0))*(1+Paramètres!$B$4*(C66-1)+Paramètres!$B$5*(C66-1)^2),0) -> 5 | S66: =L66-AVERAGE(Q66:R66) -> -0.5 | T66: =IF(M66=0,IF(AND(N66=0,O66=0,E66=0,F66=0),"OK","ERREUR"),IF(AND(M66>=1,M66<=32,OR(N66=4,N66=6,N66=8,N66=10,N66=12,N66=20),O66>=0,E66=M66+O66,F66=M66*N66+O66),"OK","ERREUR")) -> OK | U66: =IF(M66>0,M66*(N66+1)/2+O66,0) -> 3.5 | V66: =IF(ABS(L66-U66)<0.001,"OK","ERREUR") -> OK
A67: ARM004 | B67: Kriss | C67: 4 | D67: Légères | E67: =IF(M67=0,0,M67+O67) -> 3 | F67: =IF(M67=0,0,M67*N67+O67) -> 6 | G67: =ROUND(Catalogue!G7*SQRT((1+Paramètres!$B$4*(C67-1)+Paramètres!$B$5*(C67-1)^2)),0) -> 0 | H67: =ROUND(Catalogue!H7*SQRT((1+Paramètres!$B$4*(C67-1)+Paramètres!$B$5*(C67-1)^2)),0) -> 0 | I67: 2 | J67: 1 | K67: 0.5 | L67: =IF(M67=0,0,(E67+F67)/2) -> 4.5 | M67: 1 | N67: 4 | O67: 2 | P67: =IF(M67=0,"—",M67&"d"&N67&IF(O67=0,""," + "&O67)) -> 1d4 + 2 | Q67: =ROUND(INDEX(Catalogue!E$4:E$85,MATCH(A67,Catalogue!A$4:A$85,0))*(1+Paramètres!$B$4*(C67-1)+Paramètres!$B$5*(C67-1)^2),0) -> 3 | R67: =ROUND(INDEX(Catalogue!F$4:F$85,MATCH(A67,Catalogue!A$4:A$85,0))*(1+Paramètres!$B$4*(C67-1)+Paramètres!$B$5*(C67-1)^2),0) -> 6 | S67: =L67-AVERAGE(Q67:R67) -> 0 | T67: =IF(M67=0,IF(AND(N67=0,O67=0,E67=0,F67=0),"OK","ERREUR"),IF(AND(M67>=1,M67<=32,OR(N67=4,N67=6,N67=8,N67=10,N67=12,N67=20),O67>=0,E67=M67+O67,F67=M67*N67+O67),"OK","ERREUR")) -> OK | U67: =IF(M67>0,M67*(N67+1)/2+O67,0) -> 4.5 | V67: =IF(ABS(L67-U67)<0.001,"OK","ERREUR") -> OK
A68: ARM004 | B68: Kriss | C68: 5 | D68: Légères | E68: =IF(M68=0,0,M68+O68) -> 3 | F68: =IF(M68=0,0,M68*N68+O68) -> 6 | G68: =ROUND(Catalogue!G7*SQRT((1+Paramètres!$B$4*(C68-1)+Paramètres!$B$5*(C68-1)^2)),0) -> 0 | H68: =ROUND(Catalogue!H7*SQRT((1+Paramètres!$B$4*(C68-1)+Paramètres!$B$5*(C68-1)^2)),0) -> 0 | I68: 2 | J68: 1 | K68: 0.5 | L68: =IF(M68=0,0,(E68+F68)/2) -> 4.5 | M68: 1 | N68: 4 | O68: 2 | P68: =IF(M68=0,"—",M68&"d"&N68&IF(O68=0,""," + "&O68)) -> 1d4 + 2 | Q68: =ROUND(INDEX(Catalogue!E$4:E$85,MATCH(A68,Catalogue!A$4:A$85,0))*(1+Paramètres!$B$4*(C68-1)+Paramètres!$B$5*(C68-1)^2),0) -> 3 | R68: =ROUND(INDEX(Catalogue!F$4:F$85,MATCH(A68,Catalogue!A$4:A$85,0))*(1+Paramètres!$B$4*(C68-1)+Paramètres!$B$5*(C68-1)^2),0) -> 7 | S68: =L68-AVERAGE(Q68:R68) -> -0.5 | T68: =IF(M68=0,IF(AND(N68=0,O68=0,E68=0,F68=0),"OK","ERREUR"),IF(AND(M68>=1,M68<=32,OR(N68=4,N68=6,N68=8,N68=10,N68=12,N68=20),O68>=0,E68=M68+O68,F68=M68*N68+O68),"OK","ERREUR")) -> OK | U68: =IF(M68>0,M68*(N68+1)/2+O68,0) -> 4.5 | V68: =IF(ABS(L68-U68)<0.001,"OK","ERREUR") -> OK
A69: ARM004 | B69: Kriss | C69: 6 | D69: Légères | E69: =IF(M69=0,0,M69+O69) -> 4 | F69: =IF(M69=0,0,M69*N69+O69) -> 7 | G69: =ROUND(Catalogue!G7*SQRT((1+Paramètres!$B$4*(C69-1)+Paramètres!$B$5*(C69-1)^2)),0) -> 0 | H69: =ROUND(Catalogue!H7*SQRT((1+Paramètres!$B$4*(C69-1)+Paramètres!$B$5*(C69-1)^2)),0) -> 0 | I69: 2 | J69: 1 | K69: 0.5 | L69: =IF(M69=0,0,(E69+F69)/2) -> 5.5 | M69: 1 | N69: 4 | O69: 3 | P69: =IF(M69=0,"—",M69&"d"&N69&IF(O69=0,""," + "&O69)) -> 1d4 + 3 | Q69: =ROUND(INDEX(Catalogue!E$4:E$85,MATCH(A69,Catalogue!A$4:A$85,0))*(1+Paramètres!$B$4*(C69-1)+Paramètres!$B$5*(C69-1)^2),0) -> 4 | R69: =ROUND(INDEX(Catalogue!F$4:F$85,MATCH(A69,Catalogue!A$4:A$85,0))*(1+Paramètres!$B$4*(C69-1)+Paramètres!$B$5*(C69-1)^2),0) -> 8 | S69: =L69-AVERAGE(Q69:R69) -> -0.5 | T69: =IF(M69=0,IF(AND(N69=0,O69=0,E69=0,F69=0),"OK","ERREUR"),IF(AND(M69>=1,M69<=32,OR(N69=4,N69=6,N69=8,N69=10,N69=12,N69=20),O69>=0,E69=M69+O69,F69=M69*N69+O69),"OK","ERREUR")) -> OK | U69: =IF(M69>0,M69*(N69+1)/2+O69,0) -> 5.5 | V69: =IF(ABS(L69-U69)<0.001,"OK","ERREUR") -> OK
A70: ARM004 | B70: Kriss | C70: 7 | D70: Légères | E70: =IF(M70=0,0,M70+O70) -> 4 | F70: =IF(M70=0,0,M70*N70+O70) -> 9 | G70: =ROUND(Catalogue!G7*SQRT((1+Paramètres!$B$4*(C70-1)+Paramètres!$B$5*(C70-1)^2)),0) -> 0 | H70: =ROUND(Catalogue!H7*SQRT((1+Paramètres!$B$4*(C70-1)+Paramètres!$B$5*(C70-1)^2)),0) -> 0 | I70: 2 | J70: 1 | K70: 0.5 | L70: =IF(M70=0,0,(E70+F70)/2) -> 6.5 | M70: 1 | N70: 6 | O70: 3 | P70: =IF(M70=0,"—",M70&"d"&N70&IF(O70=0,""," + "&O70)) -> 1d6 + 3 | Q70: =ROUND(INDEX(Catalogue!E$4:E$85,MATCH(A70,Catalogue!A$4:A$85,0))*(1+Paramètres!$B$4*(C70-1)+Paramètres!$B$5*(C70-1)^2),0) -> 4 | R70: =ROUND(INDEX(Catalogue!F$4:F$85,MATCH(A70,Catalogue!A$4:A$85,0))*(1+Paramètres!$B$4*(C70-1)+Paramètres!$B$5*(C70-1)^2),0) -> 9 | S70: =L70-AVERAGE(Q70:R70) -> 0 | T70: =IF(M70=0,IF(AND(N70=0,O70=0,E70=0,F70=0),"OK","ERREUR"),IF(AND(M70>=1,M70<=32,OR(N70=4,N70=6,N70=8,N70=10,N70=12,N70=20),O70>=0,E70=M70+O70,F70=M70*N70+O70),"OK","ERREUR")) -> OK | U70: =IF(M70>0,M70*(N70+1)/2+O70,0) -> 6.5 | V70: =IF(ABS(L70-U70)<0.001,"OK","ERREUR") -> OK
A71: ARM004 | B71: Kriss | C71: 8 | D71: Légères | E71: =IF(M71=0,0,M71+O71) -> 5 | F71: =IF(M71=0,0,M71*N71+O71) -> 10 | G71: =ROUND(Catalogue!G7*SQRT((1+Paramètres!$B$4*(C71-1)+Paramètres!$B$5*(C71-1)^2)),0) -> 0 | H71: =ROUND(Catalogue!H7*SQRT((1+Paramètres!$B$4*(C71-1)+Paramètres!$B$5*(C71-1)^2)),0) -> 0 | I71: 2 | J71: 1 | K71: 0.5 | L71: =IF(M71=0,0,(E71+F71)/2) -> 7.5 | M71: 1 | N71: 6 | O71: 4 | P71: =IF(M71=0,"—",M71&"d"&N71&IF(O71=0,""," + "&O71)) -> 1d6 + 4 | Q71: =ROUND(INDEX(Catalogue!E$4:E$85,MATCH(A71,Catalogue!A$4:A$85,0))*(1+Paramètres!$B$4*(C71-1)+Paramètres!$B$5*(C71-1)^2),0) -> 5 | R71: =ROUND(INDEX(Catalogue!F$4:F$85,MATCH(A71,Catalogue!A$4:A$85,0))*(1+Paramètres!$B$4*(C71-1)+Paramètres!$B$5*(C71-1)^2),0) -> 10 | S71: =L71-AVERAGE(Q71:R71) -> 0 | T71: =IF(M71=0,IF(AND(N71=0,O71=0,E71=0,F71=0),"OK","ERREUR"),IF(AND(M71>=1,M71<=32,OR(N71=4,N71=6,N71=8,N71=10,N71=12,N71=20),O71>=0,E71=M71+O71,F71=M71*N71+O71),"OK","ERREUR")) -> OK | U71: =IF(M71>0,M71*(N71+1)/2+O71,0) -> 7.5 | V71: =IF(ABS(L71-U71)<0.001,"OK","ERREUR") -> OK
A72: ARM004 | B72: Kriss | C72: 9 | D72: Légères | E72: =IF(M72=0,0,M72+O72) -> 6 | F72: =IF(M72=0,0,M72*N72+O72) -> 12 | G72: =ROUND(Catalogue!G7*SQRT((1+Paramètres!$B$4*(C72-1)+Paramètres!$B$5*(C72-1)^2)),0) -> 0 | H72: =ROUND(Catalogue!H7*SQRT((1+Paramètres!$B$4*(C72-1)+Paramètres!$B$5*(C72-1)^2)),0) -> 0 | I72: 2 | J72: 1 | K72: 0.5 | L72: =IF(M72=0,0,(E72+F72)/2) -> 9 | M72: 2 | N72: 4 | O72: 4 | P72: =IF(M72=0,"—",M72&"d"&N72&IF(O72=0,""," + "&O72)) -> 2d4 + 4 | Q72: =ROUND(INDEX(Catalogue!E$4:E$85,MATCH(A72,Catalogue!A$4:A$85,0))*(1+Paramètres!$B$4*(C72-1)+Paramètres!$B$5*(C72-1)^2),0) -> 6 | R72: =ROUND(INDEX(Catalogue!F$4:F$85,MATCH(A72,Catalogue!A$4:A$85,0))*(1+Paramètres!$B$4*(C72-1)+Paramètres!$B$5*(C72-1)^2),0) -> 12 | S72: =L72-AVERAGE(Q72:R72) -> 0 | T72: =IF(M72=0,IF(AND(N72=0,O72=0,E72=0,F72=0),"OK","ERREUR"),IF(AND(M72>=1,M72<=32,OR(N72=4,N72=6,N72=8,N72=10,N72=12,N72=20),O72>=0,E72=M72+O72,F72=M72*N72+O72),"OK","ERREUR")) -> OK | U72: =IF(M72>0,M72*(N72+1)/2+O72,0) -> 9 | V72: =IF(ABS(L72-U72)<0.001,"OK","ERREUR") -> OK
A73: ARM004 | B73: Kriss | C73: 10 | D73: Légères | E73: =IF(M73=0,0,M73+O73) -> 7 | F73: =IF(M73=0,0,M73*N73+O73) -> 13 | G73: =ROUND(Catalogue!G7*SQRT((1+Paramètres!$B$4*(C73-1)+Paramètres!$B$5*(C73-1)^2)),0) -> 0 | H73: =ROUND(Catalogue!H7*SQRT((1+Paramètres!$B$4*(C73-1)+Paramètres!$B$5*(C73-1)^2)),0) -> 0 | I73: 2 | J73: 1 | K73: 0.5 | L73: =IF(M73=0,0,(E73+F73)/2) -> 10 | M73: 2 | N73: 4 | O73: 5 | P73: =IF(M73=0,"—",M73&"d"&N73&IF(O73=0,""," + "&O73)) -> 2d4 + 5 | Q73: =ROUND(INDEX(Catalogue!E$4:E$85,MATCH(A73,Catalogue!A$4:A$85,0))*(1+Paramètres!$B$4*(C73-1)+Paramètres!$B$5*(C73-1)^2),0) -> 7 | R73: =ROUND(INDEX(Catalogue!F$4:F$85,MATCH(A73,Catalogue!A$4:A$85,0))*(1+Paramètres!$B$4*(C73-1)+Paramètres!$B$5*(C73-1)^2),0) -> 13 | S73: =L73-AVERAGE(Q73:R73) -> 0 | T73: =IF(M73=0,IF(AND(N73=0,O73=0,E73=0,F73=0),"OK","ERREUR"),IF(AND(M73>=1,M73<=32,OR(N73=4,N73=6,N73=8,N73=10,N73=12,N73=20),O73>=0,E73=M73+O73,F73=M73*N73+O73),"OK","ERREUR")) -> OK | U73: =IF(M73>0,M73*(N73+1)/2+O73,0) -> 10 | V73: =IF(ABS(L73-U73)<0.001,"OK","ERREUR") -> OK
A74: ARM004 | B74: Kriss | C74: 11 | D74: Légères | E74: =IF(M74=0,0,M74+O74) -> 6 | F74: =IF(M74=0,0,M74*N74+O74) -> 15 | G74: =ROUND(Catalogue!G7*SQRT((1+Paramètres!$B$4*(C74-1)+Paramètres!$B$5*(C74-1)^2)),0) -> 0 | H74: =ROUND(Catalogue!H7*SQRT((1+Paramètres!$B$4*(C74-1)+Paramètres!$B$5*(C74-1)^2)),0) -> 0 | I74: 2 | J74: 1 | K74: 0.5 | L74: =IF(M74=0,0,(E74+F74)/2) -> 10.5 | M74: 3 | N74: 4 | O74: 3 | P74: =IF(M74=0,"—",M74&"d"&N74&IF(O74=0,""," + "&O74)) -> 3d4 + 3 | Q74: =ROUND(INDEX(Catalogue!E$4:E$85,MATCH(A74,Catalogue!A$4:A$85,0))*(1+Paramètres!$B$4*(C74-1)+Paramètres!$B$5*(C74-1)^2),0) -> 7 | R74: =ROUND(INDEX(Catalogue!F$4:F$85,MATCH(A74,Catalogue!A$4:A$85,0))*(1+Paramètres!$B$4*(C74-1)+Paramètres!$B$5*(C74-1)^2),0) -> 15 | S74: =L74-AVERAGE(Q74:R74) -> -0.5 | T74: =IF(M74=0,IF(AND(N74=0,O74=0,E74=0,F74=0),"OK","ERREUR"),IF(AND(M74>=1,M74<=32,OR(N74=4,N74=6,N74=8,N74=10,N74=12,N74=20),O74>=0,E74=M74+O74,F74=M74*N74+O74),"OK","ERREUR")) -> OK | U74: =IF(M74>0,M74*(N74+1)/2+O74,0) -> 10.5 | V74: =IF(ABS(L74-U74)<0.001,"OK","ERREUR") -> OK
A75: ARM004 | B75: Kriss | C75: 12 | D75: Légères | E75: =IF(M75=0,0,M75+O75) -> 8 | F75: =IF(M75=0,0,M75*N75+O75) -> 17 | G75: =ROUND(Catalogue!G7*SQRT((1+Paramètres!$B$4*(C75-1)+Paramètres!$B$5*(C75-1)^2)),0) -> 0 | H75: =ROUND(Catalogue!H7*SQRT((1+Paramètres!$B$4*(C75-1)+Paramètres!$B$5*(C75-1)^2)),0) -> 0 | I75: 2 | J75: 1 | K75: 0.5 | L75: =IF(M75=0,0,(E75+F75)/2) -> 12.5 | M75: 3 | N75: 4 | O75: 5 | P75: =IF(M75=0,"—",M75&"d"&N75&IF(O75=0,""," + "&O75)) -> 3d4 + 5 | Q75: =ROUND(INDEX(Catalogue!E$4:E$85,MATCH(A75,Catalogue!A$4:A$85,0))*(1+Paramètres!$B$4*(C75-1)+Paramètres!$B$5*(C75-1)^2),0) -> 8 | R75: =ROUND(INDEX(Catalogue!F$4:F$85,MATCH(A75,Catalogue!A$4:A$85,0))*(1+Paramètres!$B$4*(C75-1)+Paramètres!$B$5*(C75-1)^2),0) -> 17 | S75: =L75-AVERAGE(Q75:R75) -> 0 | T75: =IF(M75=0,IF(AND(N75=0,O75=0,E75=0,F75=0),"OK","ERREUR"),IF(AND(M75>=1,M75<=32,OR(N75=4,N75=6,N75=8,N75=10,N75=12,N75=20),O75>=0,E75=M75+O75,F75=M75*N75+O75),"OK","ERREUR")) -> OK | U75: =IF(M75>0,M75*(N75+1)/2+O75,0) -> 12.5 | V75: =IF(ABS(L75-U75)<0.001,"OK","ERREUR") -> OK
A76: ARM004 | B76: Kriss | C76: 13 | D76: Légères | E76: =IF(M76=0,0,M76+O76) -> 9 | F76: =IF(M76=0,0,M76*N76+O76) -> 18 | G76: =ROUND(Catalogue!G7*SQRT((1+Paramètres!$B$4*(C76-1)+Paramètres!$B$5*(C76-1)^2)),0) -> 0 | H76: =ROUND(Catalogue!H7*SQRT((1+Paramètres!$B$4*(C76-1)+Paramètres!$B$5*(C76-1)^2)),0) -> 0 | I76: 2 | J76: 1 | K76: 0.5 | L76: =IF(M76=0,0,(E76+F76)/2) -> 13.5 | M76: 3 | N76: 4 | O76: 6 | P76: =IF(M76=0,"—",M76&"d"&N76&IF(O76=0,""," + "&O76)) -> 3d4 + 6 | Q76: =ROUND(INDEX(Catalogue!E$4:E$85,MATCH(A76,Catalogue!A$4:A$85,0))*(1+Paramètres!$B$4*(C76-1)+Paramètres!$B$5*(C76-1)^2),0) -> 9 | R76: =ROUND(INDEX(Catalogue!F$4:F$85,MATCH(A76,Catalogue!A$4:A$85,0))*(1+Paramètres!$B$4*(C76-1)+Paramètres!$B$5*(C76-1)^2),0) -> 18 | S76: =L76-AVERAGE(Q76:R76) -> 0 | T76: =IF(M76=0,IF(AND(N76=0,O76=0,E76=0,F76=0),"OK","ERREUR"),IF(AND(M76>=1,M76<=32,OR(N76=4,N76=6,N76=8,N76=10,N76=12,N76=20),O76>=0,E76=M76+O76,F76=M76*N76+O76),"OK","ERREUR")) -> OK | U76: =IF(M76>0,M76*(N76+1)/2+O76,0) -> 13.5 | V76: =IF(ABS(L76-U76)<0.001,"OK","ERREUR") -> OK
A77: ARM004 | B77: Kriss | C77: 14 | D77: Légères | E77: =IF(M77=0,0,M77+O77) -> 10 | F77: =IF(M77=0,0,M77*N77+O77) -> 20 | G77: =ROUND(Catalogue!G7*SQRT((1+Paramètres!$B$4*(C77-1)+Paramètres!$B$5*(C77-1)^2)),0) -> 0 | H77: =ROUND(Catalogue!H7*SQRT((1+Paramètres!$B$4*(C77-1)+Paramètres!$B$5*(C77-1)^2)),0) -> 0 | I77: 2 | J77: 1 | K77: 0.5 | L77: =IF(M77=0,0,(E77+F77)/2) -> 15 | M77: 2 | N77: 6 | O77: 8 | P77: =IF(M77=0,"—",M77&"d"&N77&IF(O77=0,""," + "&O77)) -> 2d6 + 8 | Q77: =ROUND(INDEX(Catalogue!E$4:E$85,MATCH(A77,Catalogue!A$4:A$85,0))*(1+Paramètres!$B$4*(C77-1)+Paramètres!$B$5*(C77-1)^2),0) -> 10 | R77: =ROUND(INDEX(Catalogue!F$4:F$85,MATCH(A77,Catalogue!A$4:A$85,0))*(1+Paramètres!$B$4*(C77-1)+Paramètres!$B$5*(C77-1)^2),0) -> 21 | S77: =L77-AVERAGE(Q77:R77) -> -0.5 | T77: =IF(M77=0,IF(AND(N77=0,O77=0,E77=0,F77=0),"OK","ERREUR"),IF(AND(M77>=1,M77<=32,OR(N77=4,N77=6,N77=8,N77=10,N77=12,N77=20),O77>=0,E77=M77+O77,F77=M77*N77+O77),"OK","ERREUR")) -> OK | U77: =IF(M77>0,M77*(N77+1)/2+O77,0) -> 15 | V77: =IF(ABS(L77-U77)<0.001,"OK","ERREUR") -> OK
A78: ARM004 | B78: Kriss | C78: 15 | D78: Légères | E78: =IF(M78=0,0,M78+O78) -> 11 | F78: =IF(M78=0,0,M78*N78+O78) -> 23 | G78: =ROUND(Catalogue!G7*SQRT((1+Paramètres!$B$4*(C78-1)+Paramètres!$B$5*(C78-1)^2)),0) -> 0 | H78: =ROUND(Catalogue!H7*SQRT((1+Paramètres!$B$4*(C78-1)+Paramètres!$B$5*(C78-1)^2)),0) -> 0 | I78: 2 | J78: 1 | K78: 0.5 | L78: =IF(M78=0,0,(E78+F78)/2) -> 17 | M78: 4 | N78: 4 | O78: 7 | P78: =IF(M78=0,"—",M78&"d"&N78&IF(O78=0,""," + "&O78)) -> 4d4 + 7 | Q78: =ROUND(INDEX(Catalogue!E$4:E$85,MATCH(A78,Catalogue!A$4:A$85,0))*(1+Paramètres!$B$4*(C78-1)+Paramètres!$B$5*(C78-1)^2),0) -> 11 | R78: =ROUND(INDEX(Catalogue!F$4:F$85,MATCH(A78,Catalogue!A$4:A$85,0))*(1+Paramètres!$B$4*(C78-1)+Paramètres!$B$5*(C78-1)^2),0) -> 23 | S78: =L78-AVERAGE(Q78:R78) -> 0 | T78: =IF(M78=0,IF(AND(N78=0,O78=0,E78=0,F78=0),"OK","ERREUR"),IF(AND(M78>=1,M78<=32,OR(N78=4,N78=6,N78=8,N78=10,N78=12,N78=20),O78>=0,E78=M78+O78,F78=M78*N78+O78),"OK","ERREUR")) -> OK | U78: =IF(M78>0,M78*(N78+1)/2+O78,0) -> 17 | V78: =IF(ABS(L78-U78)<0.001,"OK","ERREUR") -> OK
A79: ARM004 | B79: Kriss | C79: 16 | D79: Légères | E79: =IF(M79=0,0,M79+O79) -> 13 | F79: =IF(M79=0,0,M79*N79+O79) -> 25 | G79: =ROUND(Catalogue!G7*SQRT((1+Paramètres!$B$4*(C79-1)+Paramètres!$B$5*(C79-1)^2)),0) -> 0 | H79: =ROUND(Catalogue!H7*SQRT((1+Paramètres!$B$4*(C79-1)+Paramètres!$B$5*(C79-1)^2)),0) -> 0 | I79: 2 | J79: 1 | K79: 0.5 | L79: =IF(M79=0,0,(E79+F79)/2) -> 19 | M79: 4 | N79: 4 | O79: 9 | P79: =IF(M79=0,"—",M79&"d"&N79&IF(O79=0,""," + "&O79)) -> 4d4 + 9 | Q79: =ROUND(INDEX(Catalogue!E$4:E$85,MATCH(A79,Catalogue!A$4:A$85,0))*(1+Paramètres!$B$4*(C79-1)+Paramètres!$B$5*(C79-1)^2),0) -> 13 | R79: =ROUND(INDEX(Catalogue!F$4:F$85,MATCH(A79,Catalogue!A$4:A$85,0))*(1+Paramètres!$B$4*(C79-1)+Paramètres!$B$5*(C79-1)^2),0) -> 25 | S79: =L79-AVERAGE(Q79:R79) -> 0 | T79: =IF(M79=0,IF(AND(N79=0,O79=0,E79=0,F79=0),"OK","ERREUR"),IF(AND(M79>=1,M79<=32,OR(N79=4,N79=6,N79=8,N79=10,N79=12,N79=20),O79>=0,E79=M79+O79,F79=M79*N79+O79),"OK","ERREUR")) -> OK | U79: =IF(M79>0,M79*(N79+1)/2+O79,0) -> 19 | V79: =IF(ABS(L79-U79)<0.001,"OK","ERREUR") -> OK
A80: ARM004 | B80: Kriss | C80: 17 | D80: Légères | E80: =IF(M80=0,0,M80+O80) -> 13 | F80: =IF(M80=0,0,M80*N80+O80) -> 27 | G80: =ROUND(Catalogue!G7*SQRT((1+Paramètres!$B$4*(C80-1)+Paramètres!$B$5*(C80-1)^2)),0) -> 0 | H80: =ROUND(Catalogue!H7*SQRT((1+Paramètres!$B$4*(C80-1)+Paramètres!$B$5*(C80-1)^2)),0) -> 0 | I80: 2 | J80: 1 | K80: 0.5 | L80: =IF(M80=0,0,(E80+F80)/2) -> 20 | M80: 2 | N80: 8 | O80: 11 | P80: =IF(M80=0,"—",M80&"d"&N80&IF(O80=0,""," + "&O80)) -> 2d8 + 11 | Q80: =ROUND(INDEX(Catalogue!E$4:E$85,MATCH(A80,Catalogue!A$4:A$85,0))*(1+Paramètres!$B$4*(C80-1)+Paramètres!$B$5*(C80-1)^2),0) -> 14 | R80: =ROUND(INDEX(Catalogue!F$4:F$85,MATCH(A80,Catalogue!A$4:A$85,0))*(1+Paramètres!$B$4*(C80-1)+Paramètres!$B$5*(C80-1)^2),0) -> 27 | S80: =L80-AVERAGE(Q80:R80) -> -0.5 | T80: =IF(M80=0,IF(AND(N80=0,O80=0,E80=0,F80=0),"OK","ERREUR"),IF(AND(M80>=1,M80<=32,OR(N80=4,N80=6,N80=8,N80=10,N80=12,N80=20),O80>=0,E80=M80+O80,F80=M80*N80+O80),"OK","ERREUR")) -> OK | U80: =IF(M80>0,M80*(N80+1)/2+O80,0) -> 20 | V80: =IF(ABS(L80-U80)<0.001,"OK","ERREUR") -> OK
A81: ARM004 | B81: Kriss | C81: 18 | D81: Légères | E81: =IF(M81=0,0,M81+O81) -> 15 | F81: =IF(M81=0,0,M81*N81+O81) -> 30 | G81: =ROUND(Catalogue!G7*SQRT((1+Paramètres!$B$4*(C81-1)+Paramètres!$B$5*(C81-1)^2)),0) -> 0 | H81: =ROUND(Catalogue!H7*SQRT((1+Paramètres!$B$4*(C81-1)+Paramètres!$B$5*(C81-1)^2)),0) -> 0 | I81: 2 | J81: 1 | K81: 0.5 | L81: =IF(M81=0,0,(E81+F81)/2) -> 22.5 | M81: 3 | N81: 6 | O81: 12 | P81: =IF(M81=0,"—",M81&"d"&N81&IF(O81=0,""," + "&O81)) -> 3d6 + 12 | Q81: =ROUND(INDEX(Catalogue!E$4:E$85,MATCH(A81,Catalogue!A$4:A$85,0))*(1+Paramètres!$B$4*(C81-1)+Paramètres!$B$5*(C81-1)^2),0) -> 15 | R81: =ROUND(INDEX(Catalogue!F$4:F$85,MATCH(A81,Catalogue!A$4:A$85,0))*(1+Paramètres!$B$4*(C81-1)+Paramètres!$B$5*(C81-1)^2),0) -> 30 | S81: =L81-AVERAGE(Q81:R81) -> 0 | T81: =IF(M81=0,IF(AND(N81=0,O81=0,E81=0,F81=0),"OK","ERREUR"),IF(AND(M81>=1,M81<=32,OR(N81=4,N81=6,N81=8,N81=10,N81=12,N81=20),O81>=0,E81=M81+O81,F81=M81*N81+O81),"OK","ERREUR")) -> OK | U81: =IF(M81>0,M81*(N81+1)/2+O81,0) -> 22.5 | V81: =IF(ABS(L81-U81)<0.001,"OK","ERREUR") -> OK
A82: ARM004 | B82: Kriss | C82: 19 | D82: Légères | E82: =IF(M82=0,0,M82+O82) -> 15 | F82: =IF(M82=0,0,M82*N82+O82) -> 33 | G82: =ROUND(Catalogue!G7*SQRT((1+Paramètres!$B$4*(C82-1)+Paramètres!$B$5*(C82-1)^2)),0) -> 0 | H82: =ROUND(Catalogue!H7*SQRT((1+Paramètres!$B$4*(C82-1)+Paramètres!$B$5*(C82-1)^2)),0) -> 0 | I82: 2 | J82: 1 | K82: 0.5 | L82: =IF(M82=0,0,(E82+F82)/2) -> 24 | M82: 2 | N82: 10 | O82: 13 | P82: =IF(M82=0,"—",M82&"d"&N82&IF(O82=0,""," + "&O82)) -> 2d10 + 13 | Q82: =ROUND(INDEX(Catalogue!E$4:E$85,MATCH(A82,Catalogue!A$4:A$85,0))*(1+Paramètres!$B$4*(C82-1)+Paramètres!$B$5*(C82-1)^2),0) -> 16 | R82: =ROUND(INDEX(Catalogue!F$4:F$85,MATCH(A82,Catalogue!A$4:A$85,0))*(1+Paramètres!$B$4*(C82-1)+Paramètres!$B$5*(C82-1)^2),0) -> 33 | S82: =L82-AVERAGE(Q82:R82) -> -0.5 | T82: =IF(M82=0,IF(AND(N82=0,O82=0,E82=0,F82=0),"OK","ERREUR"),IF(AND(M82>=1,M82<=32,OR(N82=4,N82=6,N82=8,N82=10,N82=12,N82=20),O82>=0,E82=M82+O82,F82=M82*N82+O82),"OK","ERREUR")) -> OK | U82: =IF(M82>0,M82*(N82+1)/2+O82,0) -> 24 | V82: =IF(ABS(L82-U82)<0.001,"OK","ERREUR") -> OK
A83: ARM004 | B83: Kriss | C83: 20 | D83: Légères | E83: =IF(M83=0,0,M83+O83) -> 18 | F83: =IF(M83=0,0,M83*N83+O83) -> 36 | G83: =ROUND(Catalogue!G7*SQRT((1+Paramètres!$B$4*(C83-1)+Paramètres!$B$5*(C83-1)^2)),0) -> 0 | H83: =ROUND(Catalogue!H7*SQRT((1+Paramètres!$B$4*(C83-1)+Paramètres!$B$5*(C83-1)^2)),0) -> 0 | I83: 2 | J83: 1 | K83: 0.5 | L83: =IF(M83=0,0,(E83+F83)/2) -> 27 | M83: 2 | N83: 10 | O83: 16 | P83: =IF(M83=0,"—",M83&"d"&N83&IF(O83=0,""," + "&O83)) -> 2d10 + 16 | Q83: =ROUND(INDEX(Catalogue!E$4:E$85,MATCH(A83,Catalogue!A$4:A$85,0))*(1+Paramètres!$B$4*(C83-1)+Paramètres!$B$5*(C83-1)^2),0) -> 18 | R83: =ROUND(INDEX(Catalogue!F$4:F$85,MATCH(A83,Catalogue!A$4:A$85,0))*(1+Paramètres!$B$4*(C83-1)+Paramètres!$B$5*(C83-1)^2),0) -> 35 | S83: =L83-AVERAGE(Q83:R83) -> 0.5 | T83: =IF(M83=0,IF(AND(N83=0,O83=0,E83=0,F83=0),"OK","ERREUR"),IF(AND(M83>=1,M83<=32,OR(N83=4,N83=6,N83=8,N83=10,N83=12,N83=20),O83>=0,E83=M83+O83,F83=M83*N83+O83),"OK","ERREUR")) -> OK | U83: =IF(M83>0,M83*(N83+1)/2+O83,0) -> 27 | V83: =IF(ABS(L83-U83)<0.001,"OK","ERREUR") -> OK
A84: ARM005 | B84: Couteau de chasse | C84: 1 | D84: Légères | E84: =IF(M84=0,0,M84+O84) -> 1 | F84: =IF(M84=0,0,M84*N84+O84) -> 4 | G84: =ROUND(Catalogue!G8*SQRT((1+Paramètres!$B$4*(C84-1)+Paramètres!$B$5*(C84-1)^2)),0) -> 0 | H84: =ROUND(Catalogue!H8*SQRT((1+Paramètres!$B$4*(C84-1)+Paramètres!$B$5*(C84-1)^2)),0) -> 0 | I84: 2 | J84: 1 | K84: 0.5 | L84: =IF(M84=0,0,(E84+F84)/2) -> 2.5 | M84: 1 | N84: 4 | O84: 0 | P84: =IF(M84=0,"—",M84&"d"&N84&IF(O84=0,""," + "&O84)) -> 1d4 | Q84: =ROUND(INDEX(Catalogue!E$4:E$85,MATCH(A84,Catalogue!A$4:A$85,0))*(1+Paramètres!$B$4*(C84-1)+Paramètres!$B$5*(C84-1)^2),0) -> 2 | R84: =ROUND(INDEX(Catalogue!F$4:F$85,MATCH(A84,Catalogue!A$4:A$85,0))*(1+Paramètres!$B$4*(C84-1)+Paramètres!$B$5*(C84-1)^2),0) -> 4 | S84: =L84-AVERAGE(Q84:R84) -> -0.5 | T84: =IF(M84=0,IF(AND(N84=0,O84=0,E84=0,F84=0),"OK","ERREUR"),IF(AND(M84>=1,M84<=32,OR(N84=4,N84=6,N84=8,N84=10,N84=12,N84=20),O84>=0,E84=M84+O84,F84=M84*N84+O84),"OK","ERREUR")) -> OK | U84: =IF(M84>0,M84*(N84+1)/2+O84,0) -> 2.5 | V84: =IF(ABS(L84-U84)<0.001,"OK","ERREUR") -> OK
A85: ARM005 | B85: Couteau de chasse | C85: 2 | D85: Légères | E85: =IF(M85=0,0,M85+O85) -> 2 | F85: =IF(M85=0,0,M85*N85+O85) -> 5 | G85: =ROUND(Catalogue!G8*SQRT((1+Paramètres!$B$4*(C85-1)+Paramètres!$B$5*(C85-1)^2)),0) -> 0 | H85: =ROUND(Catalogue!H8*SQRT((1+Paramètres!$B$4*(C85-1)+Paramètres!$B$5*(C85-1)^2)),0) -> 0 | I85: 2 | J85: 1 | K85: 0.5 | L85: =IF(M85=0,0,(E85+F85)/2) -> 3.5 | M85: 1 | N85: 4 | O85: 1 | P85: =IF(M85=0,"—",M85&"d"&N85&IF(O85=0,""," + "&O85)) -> 1d4 + 1 | Q85: =ROUND(INDEX(Catalogue!E$4:E$85,MATCH(A85,Catalogue!A$4:A$85,0))*(1+Paramètres!$B$4*(C85-1)+Paramètres!$B$5*(C85-1)^2),0) -> 2 | R85: =ROUND(INDEX(Catalogue!F$4:F$85,MATCH(A85,Catalogue!A$4:A$85,0))*(1+Paramètres!$B$4*(C85-1)+Paramètres!$B$5*(C85-1)^2),0) -> 5 | S85: =L85-AVERAGE(Q85:R85) -> 0 | T85: =IF(M85=0,IF(AND(N85=0,O85=0,E85=0,F85=0),"OK","ERREUR"),IF(AND(M85>=1,M85<=32,OR(N85=4,N85=6,N85=8,N85=10,N85=12,N85=20),O85>=0,E85=M85+O85,F85=M85*N85+O85),"OK","ERREUR")) -> OK | U85: =IF(M85>0,M85*(N85+1)/2+O85,0) -> 3.5 | V85: =IF(ABS(L85-U85)<0.001,"OK","ERREUR") -> OK
A86: ARM005 | B86: Couteau de chasse | C86: 3 | D86: Légères | E86: =IF(M86=0,0,M86+O86) -> 2 | F86: =IF(M86=0,0,M86*N86+O86) -> 5 | G86: =ROUND(Catalogue!G8*SQRT((1+Paramètres!$B$4*(C86-1)+Paramètres!$B$5*(C86-1)^2)),0) -> 0 | H86: =ROUND(Catalogue!H8*SQRT((1+Paramètres!$B$4*(C86-1)+Paramètres!$B$5*(C86-1)^2)),0) -> 0 | I86: 2 | J86: 1 | K86: 0.5 | L86: =IF(M86=0,0,(E86+F86)/2) -> 3.5 | M86: 1 | N86: 4 | O86: 1 | P86: =IF(M86=0,"—",M86&"d"&N86&IF(O86=0,""," + "&O86)) -> 1d4 + 1 | Q86: =ROUND(INDEX(Catalogue!E$4:E$85,MATCH(A86,Catalogue!A$4:A$85,0))*(1+Paramètres!$B$4*(C86-1)+Paramètres!$B$5*(C86-1)^2),0) -> 3 | R86: =ROUND(INDEX(Catalogue!F$4:F$85,MATCH(A86,Catalogue!A$4:A$85,0))*(1+Paramètres!$B$4*(C86-1)+Paramètres!$B$5*(C86-1)^2),0) -> 5 | S86: =L86-AVERAGE(Q86:R86) -> -0.5 | T86: =IF(M86=0,IF(AND(N86=0,O86=0,E86=0,F86=0),"OK","ERREUR"),IF(AND(M86>=1,M86<=32,OR(N86=4,N86=6,N86=8,N86=10,N86=12,N86=20),O86>=0,E86=M86+O86,F86=M86*N86+O86),"OK","ERREUR")) -> OK | U86: =IF(M86>0,M86*(N86+1)/2+O86,0) -> 3.5 | V86: =IF(ABS(L86-U86)<0.001,"OK","ERREUR") -> OK
A87: ARM005 | B87: Couteau de chasse | C87: 4 | D87: Légères | E87: =IF(M87=0,0,M87+O87) -> 3 | F87: =IF(M87=0,0,M87*N87+O87) -> 6 | G87: =ROUND(Catalogue!G8*SQRT((1+Paramètres!$B$4*(C87-1)+Paramètres!$B$5*(C87-1)^2)),0) -> 0 | H87: =ROUND(Catalogue!H8*SQRT((1+Paramètres!$B$4*(C87-1)+Paramètres!$B$5*(C87-1)^2)),0) -> 0 | I87: 2 | J87: 1 | K87: 0.5 | L87: =IF(M87=0,0,(E87+F87)/2) -> 4.5 | M87: 1 | N87: 4 | O87: 2 | P87: =IF(M87=0,"—",M87&"d"&N87&IF(O87=0,""," + "&O87)) -> 1d4 + 2 | Q87: =ROUND(INDEX(Catalogue!E$4:E$85,MATCH(A87,Catalogue!A$4:A$85,0))*(1+Paramètres!$B$4*(C87-1)+Paramètres!$B$5*(C87-1)^2),0) -> 3 | R87: =ROUND(INDEX(Catalogue!F$4:F$85,MATCH(A87,Catalogue!A$4:A$85,0))*(1+Paramètres!$B$4*(C87-1)+Paramètres!$B$5*(C87-1)^2),0) -> 6 | S87: =L87-AVERAGE(Q87:R87) -> 0 | T87: =IF(M87=0,IF(AND(N87=0,O87=0,E87=0,F87=0),"OK","ERREUR"),IF(AND(M87>=1,M87<=32,OR(N87=4,N87=6,N87=8,N87=10,N87=12,N87=20),O87>=0,E87=M87+O87,F87=M87*N87+O87),"OK","ERREUR")) -> OK | U87: =IF(M87>0,M87*(N87+1)/2+O87,0) -> 4.5 | V87: =IF(ABS(L87-U87)<0.001,"OK","ERREUR") -> OK
A88: ARM005 | B88: Couteau de chasse | C88: 5 | D88: Légères | E88: =IF(M88=0,0,M88+O88) -> 3 | F88: =IF(M88=0,0,M88*N88+O88) -> 6 | G88: =ROUND(Catalogue!G8*SQRT((1+Paramètres!$B$4*(C88-1)+Paramètres!$B$5*(C88-1)^2)),0) -> 0 | H88: =ROUND(Catalogue!H8*SQRT((1+Paramètres!$B$4*(C88-1)+Paramètres!$B$5*(C88-1)^2)),0) -> 0 | I88: 2 | J88: 1 | K88: 0.5 | L88: =IF(M88=0,0,(E88+F88)/2) -> 4.5 | M88: 1 | N88: 4 | O88: 2 | P88: =IF(M88=0,"—",M88&"d"&N88&IF(O88=0,""," + "&O88)) -> 1d4 + 2 | Q88: =ROUND(INDEX(Catalogue!E$4:E$85,MATCH(A88,Catalogue!A$4:A$85,0))*(1+Paramètres!$B$4*(C88-1)+Paramètres!$B$5*(C88-1)^2),0) -> 3 | R88: =ROUND(INDEX(Catalogue!F$4:F$85,MATCH(A88,Catalogue!A$4:A$85,0))*(1+Paramètres!$B$4*(C88-1)+Paramètres!$B$5*(C88-1)^2),0) -> 7 | S88: =L88-AVERAGE(Q88:R88) -> -0.5 | T88: =IF(M88=0,IF(AND(N88=0,O88=0,E88=0,F88=0),"OK","ERREUR"),IF(AND(M88>=1,M88<=32,OR(N88=4,N88=6,N88=8,N88=10,N88=12,N88=20),O88>=0,E88=M88+O88,F88=M88*N88+O88),"OK","ERREUR")) -> OK | U88: =IF(M88>0,M88*(N88+1)/2+O88,0) -> 4.5 | V88: =IF(ABS(L88-U88)<0.001,"OK","ERREUR") -> OK
A89: ARM005 | B89: Couteau de chasse | C89: 6 | D89: Légères | E89: =IF(M89=0,0,M89+O89) -> 4 | F89: =IF(M89=0,0,M89*N89+O89) -> 7 | G89: =ROUND(Catalogue!G8*SQRT((1+Paramètres!$B$4*(C89-1)+Paramètres!$B$5*(C89-1)^2)),0) -> 0 | H89: =ROUND(Catalogue!H8*SQRT((1+Paramètres!$B$4*(C89-1)+Paramètres!$B$5*(C89-1)^2)),0) -> 0 | I89: 2 | J89: 1 | K89: 0.5 | L89: =IF(M89=0,0,(E89+F89)/2) -> 5.5 | M89: 1 | N89: 4 | O89: 3 | P89: =IF(M89=0,"—",M89&"d"&N89&IF(O89=0,""," + "&O89)) -> 1d4 + 3 | Q89: =ROUND(INDEX(Catalogue!E$4:E$85,MATCH(A89,Catalogue!A$4:A$85,0))*(1+Paramètres!$B$4*(C89-1)+Paramètres!$B$5*(C89-1)^2),0) -> 4 | R89: =ROUND(INDEX(Catalogue!F$4:F$85,MATCH(A89,Catalogue!A$4:A$85,0))*(1+Paramètres!$B$4*(C89-1)+Paramètres!$B$5*(C89-1)^2),0) -> 8 | S89: =L89-AVERAGE(Q89:R89) -> -0.5 | T89: =IF(M89=0,IF(AND(N89=0,O89=0,E89=0,F89=0),"OK","ERREUR"),IF(AND(M89>=1,M89<=32,OR(N89=4,N89=6,N89=8,N89=10,N89=12,N89=20),O89>=0,E89=M89+O89,F89=M89*N89+O89),"OK","ERREUR")) -> OK | U89: =IF(M89>0,M89*(N89+1)/2+O89,0) -> 5.5 | V89: =IF(ABS(L89-U89)<0.001,"OK","ERREUR") -> OK
A90: ARM005 | B90: Couteau de chasse | C90: 7 | D90: Légères | E90: =IF(M90=0,0,M90+O90) -> 4 | F90: =IF(M90=0,0,M90*N90+O90) -> 9 | G90: =ROUND(Catalogue!G8*SQRT((1+Paramètres!$B$4*(C90-1)+Paramètres!$B$5*(C90-1)^2)),0) -> 0 | H90: =ROUND(Catalogue!H8*SQRT((1+Paramètres!$B$4*(C90-1)+Paramètres!$B$5*(C90-1)^2)),0) -> 0 | I90: 2 | J90: 1 | K90: 0.5 | L90: =IF(M90=0,0,(E90+F90)/2) -> 6.5 | M90: 1 | N90: 6 | O90: 3 | P90: =IF(M90=0,"—",M90&"d"&N90&IF(O90=0,""," + "&O90)) -> 1d6 + 3 | Q90: =ROUND(INDEX(Catalogue!E$4:E$85,MATCH(A90,Catalogue!A$4:A$85,0))*(1+Paramètres!$B$4*(C90-1)+Paramètres!$B$5*(C90-1)^2),0) -> 4 | R90: =ROUND(INDEX(Catalogue!F$4:F$85,MATCH(A90,Catalogue!A$4:A$85,0))*(1+Paramètres!$B$4*(C90-1)+Paramètres!$B$5*(C90-1)^2),0) -> 9 | S90: =L90-AVERAGE(Q90:R90) -> 0 | T90: =IF(M90=0,IF(AND(N90=0,O90=0,E90=0,F90=0),"OK","ERREUR"),IF(AND(M90>=1,M90<=32,OR(N90=4,N90=6,N90=8,N90=10,N90=12,N90=20),O90>=0,E90=M90+O90,F90=M90*N90+O90),"OK","ERREUR")) -> OK | U90: =IF(M90>0,M90*(N90+1)/2+O90,0) -> 6.5 | V90: =IF(ABS(L90-U90)<0.001,"OK","ERREUR") -> OK
A91: ARM005 | B91: Couteau de chasse | C91: 8 | D91: Légères | E91: =IF(M91=0,0,M91+O91) -> 5 | F91: =IF(M91=0,0,M91*N91+O91) -> 10 | G91: =ROUND(Catalogue!G8*SQRT((1+Paramètres!$B$4*(C91-1)+Paramètres!$B$5*(C91-1)^2)),0) -> 0 | H91: =ROUND(Catalogue!H8*SQRT((1+Paramètres!$B$4*(C91-1)+Paramètres!$B$5*(C91-1)^2)),0) -> 0 | I91: 2 | J91: 1 | K91: 0.5 | L91: =IF(M91=0,0,(E91+F91)/2) -> 7.5 | M91: 1 | N91: 6 | O91: 4 | P91: =IF(M91=0,"—",M91&"d"&N91&IF(O91=0,""," + "&O91)) -> 1d6 + 4 | Q91: =ROUND(INDEX(Catalogue!E$4:E$85,MATCH(A91,Catalogue!A$4:A$85,0))*(1+Paramètres!$B$4*(C91-1)+Paramètres!$B$5*(C91-1)^2),0) -> 5 | R91: =ROUND(INDEX(Catalogue!F$4:F$85,MATCH(A91,Catalogue!A$4:A$85,0))*(1+Paramètres!$B$4*(C91-1)+Paramètres!$B$5*(C91-1)^2),0) -> 10 | S91: =L91-AVERAGE(Q91:R91) -> 0 | T91: =IF(M91=0,IF(AND(N91=0,O91=0,E91=0,F91=0),"OK","ERREUR"),IF(AND(M91>=1,M91<=32,OR(N91=4,N91=6,N91=8,N91=10,N91=12,N91=20),O91>=0,E91=M91+O91,F91=M91*N91+O91),"OK","ERREUR")) -> OK | U91: =IF(M91>0,M91*(N91+1)/2+O91,0) -> 7.5 | V91: =IF(ABS(L91-U91)<0.001,"OK","ERREUR") -> OK
A92: ARM005 | B92: Couteau de chasse | C92: 9 | D92: Légères | E92: =IF(M92=0,0,M92+O92) -> 6 | F92: =IF(M92=0,0,M92*N92+O92) -> 12 | G92: =ROUND(Catalogue!G8*SQRT((1+Paramètres!$B$4*(C92-1)+Paramètres!$B$5*(C92-1)^2)),0) -> 0 | H92: =ROUND(Catalogue!H8*SQRT((1+Paramètres!$B$4*(C92-1)+Paramètres!$B$5*(C92-1)^2)),0) -> 0 | I92: 2 | J92: 1 | K92: 0.5 | L92: =IF(M92=0,0,(E92+F92)/2) -> 9 | M92: 2 | N92: 4 | O92: 4 | P92: =IF(M92=0,"—",M92&"d"&N92&IF(O92=0,""," + "&O92)) -> 2d4 + 4 | Q92: =ROUND(INDEX(Catalogue!E$4:E$85,MATCH(A92,Catalogue!A$4:A$85,0))*(1+Paramètres!$B$4*(C92-1)+Paramètres!$B$5*(C92-1)^2),0) -> 6 | R92: =ROUND(INDEX(Catalogue!F$4:F$85,MATCH(A92,Catalogue!A$4:A$85,0))*(1+Paramètres!$B$4*(C92-1)+Paramètres!$B$5*(C92-1)^2),0) -> 12 | S92: =L92-AVERAGE(Q92:R92) -> 0 | T92: =IF(M92=0,IF(AND(N92=0,O92=0,E92=0,F92=0),"OK","ERREUR"),IF(AND(M92>=1,M92<=32,OR(N92=4,N92=6,N92=8,N92=10,N92=12,N92=20),O92>=0,E92=M92+O92,F92=M92*N92+O92),"OK","ERREUR")) -> OK | U92: =IF(M92>0,M92*(N92+1)/2+O92,0) -> 9 | V92: =IF(ABS(L92-U92)<0.001,"OK","ERREUR") -> OK
A93: ARM005 | B93: Couteau de chasse | C93: 10 | D93: Légères | E93: =IF(M93=0,0,M93+O93) -> 7 | F93: =IF(M93=0,0,M93*N93+O93) -> 13 | G93: =ROUND(Catalogue!G8*SQRT((1+Paramètres!$B$4*(C93-1)+Paramètres!$B$5*(C93-1)^2)),0) -> 0 | H93: =ROUND(Catalogue!H8*SQRT((1+Paramètres!$B$4*(C93-1)+Paramètres!$B$5*(C93-1)^2)),0) -> 0 | I93: 2 | J93: 1 | K93: 0.5 | L93: =IF(M93=0,0,(E93+F93)/2) -> 10 | M93: 2 | N93: 4 | O93: 5 | P93: =IF(M93=0,"—",M93&"d"&N93&IF(O93=0,""," + "&O93)) -> 2d4 + 5 | Q93: =ROUND(INDEX(Catalogue!E$4:E$85,MATCH(A93,Catalogue!A$4:A$85,0))*(1+Paramètres!$B$4*(C93-1)+Paramètres!$B$5*(C93-1)^2),0) -> 7 | R93: =ROUND(INDEX(Catalogue!F$4:F$85,MATCH(A93,Catalogue!A$4:A$85,0))*(1+Paramètres!$B$4*(C93-1)+Paramètres!$B$5*(C93-1)^2),0) -> 13 | S93: =L93-AVERAGE(Q93:R93) -> 0 | T93: =IF(M93=0,IF(AND(N93=0,O93=0,E93=0,F93=0),"OK","ERREUR"),IF(AND(M93>=1,M93<=32,OR(N93=4,N93=6,N93=8,N93=10,N93=12,N93=20),O93>=0,E93=M93+O93,F93=M93*N93+O93),"OK","ERREUR")) -> OK | U93: =IF(M93>0,M93*(N93+1)/2+O93,0) -> 10 | V93: =IF(ABS(L93-U93)<0.001,"OK","ERREUR") -> OK
A94: ARM005 | B94: Couteau de chasse | C94: 11 | D94: Légères | E94: =IF(M94=0,0,M94+O94) -> 6 | F94: =IF(M94=0,0,M94*N94+O94) -> 15 | G94: =ROUND(Catalogue!G8*SQRT((1+Paramètres!$B$4*(C94-1)+Paramètres!$B$5*(C94-1)^2)),0) -> 0 | H94: =ROUND(Catalogue!H8*SQRT((1+Paramètres!$B$4*(C94-1)+Paramètres!$B$5*(C94-1)^2)),0) -> 0 | I94: 2 | J94: 1 | K94: 0.5 | L94: =IF(M94=0,0,(E94+F94)/2) -> 10.5 | M94: 3 | N94: 4 | O94: 3 | P94: =IF(M94=0,"—",M94&"d"&N94&IF(O94=0,""," + "&O94)) -> 3d4 + 3 | Q94: =ROUND(INDEX(Catalogue!E$4:E$85,MATCH(A94,Catalogue!A$4:A$85,0))*(1+Paramètres!$B$4*(C94-1)+Paramètres!$B$5*(C94-1)^2),0) -> 7 | R94: =ROUND(INDEX(Catalogue!F$4:F$85,MATCH(A94,Catalogue!A$4:A$85,0))*(1+Paramètres!$B$4*(C94-1)+Paramètres!$B$5*(C94-1)^2),0) -> 15 | S94: =L94-AVERAGE(Q94:R94) -> -0.5 | T94: =IF(M94=0,IF(AND(N94=0,O94=0,E94=0,F94=0),"OK","ERREUR"),IF(AND(M94>=1,M94<=32,OR(N94=4,N94=6,N94=8,N94=10,N94=12,N94=20),O94>=0,E94=M94+O94,F94=M94*N94+O94),"OK","ERREUR")) -> OK | U94: =IF(M94>0,M94*(N94+1)/2+O94,0) -> 10.5 | V94: =IF(ABS(L94-U94)<0.001,"OK","ERREUR") -> OK
A95: ARM005 | B95: Couteau de chasse | C95: 12 | D95: Légères | E95: =IF(M95=0,0,M95+O95) -> 8 | F95: =IF(M95=0,0,M95*N95+O95) -> 17 | G95: =ROUND(Catalogue!G8*SQRT((1+Paramètres!$B$4*(C95-1)+Paramètres!$B$5*(C95-1)^2)),0) -> 0 | H95: =ROUND(Catalogue!H8*SQRT((1+Paramètres!$B$4*(C95-1)+Paramètres!$B$5*(C95-1)^2)),0) -> 0 | I95: 2 | J95: 1 | K95: 0.5 | L95: =IF(M95=0,0,(E95+F95)/2) -> 12.5 | M95: 3 | N95: 4 | O95: 5 | P95: =IF(M95=0,"—",M95&"d"&N95&IF(O95=0,""," + "&O95)) -> 3d4 + 5 | Q95: =ROUND(INDEX(Catalogue!E$4:E$85,MATCH(A95,Catalogue!A$4:A$85,0))*(1+Paramètres!$B$4*(C95-1)+Paramètres!$B$5*(C95-1)^2),0) -> 8 | R95: =ROUND(INDEX(Catalogue!F$4:F$85,MATCH(A95,Catalogue!A$4:A$85,0))*(1+Paramètres!$B$4*(C95-1)+Paramètres!$B$5*(C95-1)^2),0) -> 17 | S95: =L95-AVERAGE(Q95:R95) -> 0 | T95: =IF(M95=0,IF(AND(N95=0,O95=0,E95=0,F95=0),"OK","ERREUR"),IF(AND(M95>=1,M95<=32,OR(N95=4,N95=6,N95=8,N95=10,N95=12,N95=20),O95>=0,E95=M95+O95,F95=M95*N95+O95),"OK","ERREUR")) -> OK | U95: =IF(M95>0,M95*(N95+1)/2+O95,0) -> 12.5 | V95: =IF(ABS(L95-U95)<0.001,"OK","ERREUR") -> OK
A96: ARM005 | B96: Couteau de chasse | C96: 13 | D96: Légères | E96: =IF(M96=0,0,M96+O96) -> 9 | F96: =IF(M96=0,0,M96*N96+O96) -> 18 | G96: =ROUND(Catalogue!G8*SQRT((1+Paramètres!$B$4*(C96-1)+Paramètres!$B$5*(C96-1)^2)),0) -> 0 | H96: =ROUND(Catalogue!H8*SQRT((1+Paramètres!$B$4*(C96-1)+Paramètres!$B$5*(C96-1)^2)),0) -> 0 | I96: 2 | J96: 1 | K96: 0.5 | L96: =IF(M96=0,0,(E96+F96)/2) -> 13.5 | M96: 3 | N96: 4 | O96: 6 | P96: =IF(M96=0,"—",M96&"d"&N96&IF(O96=0,""," + "&O96)) -> 3d4 + 6 | Q96: =ROUND(INDEX(Catalogue!E$4:E$85,MATCH(A96,Catalogue!A$4:A$85,0))*(1+Paramètres!$B$4*(C96-1)+Paramètres!$B$5*(C96-1)^2),0) -> 9 | R96: =ROUND(INDEX(Catalogue!F$4:F$85,MATCH(A96,Catalogue!A$4:A$85,0))*(1+Paramètres!$B$4*(C96-1)+Paramètres!$B$5*(C96-1)^2),0) -> 18 | S96: =L96-AVERAGE(Q96:R96) -> 0 | T96: =IF(M96=0,IF(AND(N96=0,O96=0,E96=0,F96=0),"OK","ERREUR"),IF(AND(M96>=1,M96<=32,OR(N96=4,N96=6,N96=8,N96=10,N96=12,N96=20),O96>=0,E96=M96+O96,F96=M96*N96+O96),"OK","ERREUR")) -> OK | U96: =IF(M96>0,M96*(N96+1)/2+O96,0) -> 13.5 | V96: =IF(ABS(L96-U96)<0.001,"OK","ERREUR") -> OK
A97: ARM005 | B97: Couteau de chasse | C97: 14 | D97: Légères | E97: =IF(M97=0,0,M97+O97) -> 10 | F97: =IF(M97=0,0,M97*N97+O97) -> 20 | G97: =ROUND(Catalogue!G8*SQRT((1+Paramètres!$B$4*(C97-1)+Paramètres!$B$5*(C97-1)^2)),0) -> 0 | H97: =ROUND(Catalogue!H8*SQRT((1+Paramètres!$B$4*(C97-1)+Paramètres!$B$5*(C97-1)^2)),0) -> 0 | I97: 2 | J97: 1 | K97: 0.5 | L97: =IF(M97=0,0,(E97+F97)/2) -> 15 | M97: 2 | N97: 6 | O97: 8 | P97: =IF(M97=0,"—",M97&"d"&N97&IF(O97=0,""," + "&O97)) -> 2d6 + 8 | Q97: =ROUND(INDEX(Catalogue!E$4:E$85,MATCH(A97,Catalogue!A$4:A$85,0))*(1+Paramètres!$B$4*(C97-1)+Paramètres!$B$5*(C97-1)^2),0) -> 10 | R97: =ROUND(INDEX(Catalogue!F$4:F$85,MATCH(A97,Catalogue!A$4:A$85,0))*(1+Paramètres!$B$4*(C97-1)+Paramètres!$B$5*(C97-1)^2),0) -> 21 | S97: =L97-AVERAGE(Q97:R97) -> -0.5 | T97: =IF(M97=0,IF(AND(N97=0,O97=0,E97=0,F97=0),"OK","ERREUR"),IF(AND(M97>=1,M97<=32,OR(N97=4,N97=6,N97=8,N97=10,N97=12,N97=20),O97>=0,E97=M97+O97,F97=M97*N97+O97),"OK","ERREUR")) -> OK | U97: =IF(M97>0,M97*(N97+1)/2+O97,0) -> 15 | V97: =IF(ABS(L97-U97)<0.001,"OK","ERREUR") -> OK
A98: ARM005 | B98: Couteau de chasse | C98: 15 | D98: Légères | E98: =IF(M98=0,0,M98+O98) -> 11 | F98: =IF(M98=0,0,M98*N98+O98) -> 23 | G98: =ROUND(Catalogue!G8*SQRT((1+Paramètres!$B$4*(C98-1)+Paramètres!$B$5*(C98-1)^2)),0) -> 0 | H98: =ROUND(Catalogue!H8*SQRT((1+Paramètres!$B$4*(C98-1)+Paramètres!$B$5*(C98-1)^2)),0) -> 0 | I98: 2 | J98: 1 | K98: 0.5 | L98: =IF(M98=0,0,(E98+F98)/2) -> 17 | M98: 4 | N98: 4 | O98: 7 | P98: =IF(M98=0,"—",M98&"d"&N98&IF(O98=0,""," + "&O98)) -> 4d4 + 7 | Q98: =ROUND(INDEX(Catalogue!E$4:E$85,MATCH(A98,Catalogue!A$4:A$85,0))*(1+Paramètres!$B$4*(C98-1)+Paramètres!$B$5*(C98-1)^2),0) -> 11 | R98: =ROUND(INDEX(Catalogue!F$4:F$85,MATCH(A98,Catalogue!A$4:A$85,0))*(1+Paramètres!$B$4*(C98-1)+Paramètres!$B$5*(C98-1)^2),0) -> 23 | S98: =L98-AVERAGE(Q98:R98) -> 0 | T98: =IF(M98=0,IF(AND(N98=0,O98=0,E98=0,F98=0),"OK","ERREUR"),IF(AND(M98>=1,M98<=32,OR(N98=4,N98=6,N98=8,N98=10,N98=12,N98=20),O98>=0,E98=M98+O98,F98=M98*N98+O98),"OK","ERREUR")) -> OK | U98: =IF(M98>0,M98*(N98+1)/2+O98,0) -> 17 | V98: =IF(ABS(L98-U98)<0.001,"OK","ERREUR") -> OK
A99: ARM005 | B99: Couteau de chasse | C99: 16 | D99: Légères | E99: =IF(M99=0,0,M99+O99) -> 13 | F99: =IF(M99=0,0,M99*N99+O99) -> 25 | G99: =ROUND(Catalogue!G8*SQRT((1+Paramètres!$B$4*(C99-1)+Paramètres!$B$5*(C99-1)^2)),0) -> 0 | H99: =ROUND(Catalogue!H8*SQRT((1+Paramètres!$B$4*(C99-1)+Paramètres!$B$5*(C99-1)^2)),0) -> 0 | I99: 2 | J99: 1 | K99: 0.5 | L99: =IF(M99=0,0,(E99+F99)/2) -> 19 | M99: 4 | N99: 4 | O99: 9 | P99: =IF(M99=0,"—",M99&"d"&N99&IF(O99=0,""," + "&O99)) -> 4d4 + 9 | Q99: =ROUND(INDEX(Catalogue!E$4:E$85,MATCH(A99,Catalogue!A$4:A$85,0))*(1+Paramètres!$B$4*(C99-1)+Paramètres!$B$5*(C99-1)^2),0) -> 13 | R99: =ROUND(INDEX(Catalogue!F$4:F$85,MATCH(A99,Catalogue!A$4:A$85,0))*(1+Paramètres!$B$4*(C99-1)+Paramètres!$B$5*(C99-1)^2),0) -> 25 | S99: =L99-AVERAGE(Q99:R99) -> 0 | T99: =IF(M99=0,IF(AND(N99=0,O99=0,E99=0,F99=0),"OK","ERREUR"),IF(AND(M99>=1,M99<=32,OR(N99=4,N99=6,N99=8,N99=10,N99=12,N99=20),O99>=0,E99=M99+O99,F99=M99*N99+O99),"OK","ERREUR")) -> OK | U99: =IF(M99>0,M99*(N99+1)/2+O99,0) -> 19 | V99: =IF(ABS(L99-U99)<0.001,"OK","ERREUR") -> OK
A100: ARM005 | B100: Couteau de chasse | C100: 17 | D100: Légères | E100: =IF(M100=0,0,M100+O100) -> 13 | F100: =IF(M100=0,0,M100*N100+O100) -> 27 | G100: =ROUND(Catalogue!G8*SQRT((1+Paramètres!$B$4*(C100-1)+Paramètres!$B$5*(C100-1)^2)),0) -> 0 | H100: =ROUND(Catalogue!H8*SQRT((1+Paramètres!$B$4*(C100-1)+Paramètres!$B$5*(C100-1)^2)),0) -> 0 | I100: 2 | J100: 1 | K100: 0.5 | L100: =IF(M100=0,0,(E100+F100)/2) -> 20 | M100: 2 | N100: 8 | O100: 11 | P100: =IF(M100=0,"—",M100&"d"&N100&IF(O100=0,""," + "&O100)) -> 2d8 + 11 | Q100: =ROUND(INDEX(Catalogue!E$4:E$85,MATCH(A100,Catalogue!A$4:A$85,0))*(1+Paramètres!$B$4*(C100-1)+Paramètres!$B$5*(C100-1)^2),0) -> 14 | R100: =ROUND(INDEX(Catalogue!F$4:F$85,MATCH(A100,Catalogue!A$4:A$85,0))*(1+Paramètres!$B$4*(C100-1)+Paramètres!$B$5*(C100-1)^2),0) -> 27 | S100: =L100-AVERAGE(Q100:R100) -> -0.5 | T100: =IF(M100=0,IF(AND(N100=0,O100=0,E100=0,F100=0),"OK","ERREUR"),IF(AND(M100>=1,M100<=32,OR(N100=4,N100=6,N100=8,N100=10,N100=12,N100=20),O100>=0,E100=M100+O100,F100=M100*N100+O100),"OK","ERREUR")) -> OK | U100: =IF(M100>0,M100*(N100+1)/2+O100,0) -> 20 | V100: =IF(ABS(L100-U100)<0.001,"OK","ERREUR") -> OK
...

Sheet Raretés
A1: Raretés et codes couleurs
A2: Niveau d'objet immuable. Les couleurs expriment la rareté; affixes/runes portent la diversité, sans multiplication WD automatique.
A3: Rareté | B3: HEX | C3: WD de rareté (proposé) | D3: Nb affixes | E3: Chasses de rune | F3: Propriété | G3: Origine | H3: Contraintes
A4: Commun | B4: #92999F | C4: 1 | D4: 0 | E4: 0 | F4: Aucun affixe standard | G4: Butin courant | H4: Niveau fixe, dégâts par dés
A5: Rare | B5: #42A75B | C5: 1 | D5: 1 | E5: 1 | F5: 1 affixe | G5: Butin peu fréquent | H5: Rune optionnelle; dégâts sans multiplicateur automatique
A6: Épique | B6: #368DDF | C6: 1 | D6: 2 | E6: 1 | F6: 2 affixes | G6: Butin exceptionnel | H6: Affixes sans effet cumulé excessif
A7: Légendaire | B7: #9B59D0 | C7: 1 | D7: 3 | E7: 2 | F7: 3 affixes | G7: Butin très rare | H7: 2 runes maximum
A8: Unique | B8: #D4A23A | C8: 1 | D8: 0 | E8: 0 | F8: Propriétés fixes / définies par objet | G8: Quête ou boss | H8: Rareté narrative, puissance non garantie
A11: Principes
A12: Rareté≠niveau | B12: Une arme Rare N4 ne gagne jamais de niveau ; le porteur peut s'équiper d'un objet > son niveau avec malus.
A13: Unique≠suprême | B13: Le mécanisme narratif prévaut; certains objets uniques sont de niveau bas.
A14: Affixes | B14: Petits bonus de précision, résistance, stats, mana, critique, statut conditionnel.
A15: Raretés demandées | B15: Aucun palier « Peu commun » dans cette version; peut être ajouté sans rompre les IDs.
A16: Production | B16: Couleurs et slots sont PROPOSÉS, pas une fonctionnalité déjà confirmée du jeu.

Sheet Classes
A1: Affinités des six classes
A2: Les préférences guident les talents, l'équilibrage et les drops — aucune interdiction rigide de classe proposée.
A3: Classe | B3: Branches canoniques | C3: Armement prioritaire | D3: Exemples emblématiques | E3: Alternatives | F3: Attributs dominants | G3: Synergies
A4: Guerrier | B4: Gardien / Brise-ligne / Maître d'armes | C4: Épée+écu, masse+écu, grande hache, hallebarde | D4: Épée longue, marteau à deux mains | E4: Lances, arbalète légère | F4: Force; Constitution | G4: Garde/contre-attaque/puissance WD
A5: Voleur | B5: Assassin / Ombre / Saboteur | C5: Deux dagues, stylet, rapière, couteau de jet | D5: Poignard d'assassin, main-gauche | E5: Arc court, arbalète légère | F5: Dextérité | G5: Critique positionnel, saignement, discrétion
A6: Rôdeur | B6: Tireur / Chasseur / Éclaireur | C6: Arc long/composite, arbalète, lance, javelot | D6: Arc recourbé, épée courte | E6: Rapière, fronde, poignard | F6: Dextérité; Force optionnelle | G6: Portée/LOS/mobilité/ennemi juré
A7: Mage | B7: Évocateur / Arcaniste / Tisseur de surfaces | C7: Baguettes élémentaires, bâtons arcaniques, orbe | D7: Bâton élémentaire, baguette+orbe | E7: Dague légère de secours | F7: Intelligence | G7: Affinité élémentaire/surfaces/mana
A8: Prêtre | B8: Restauration / Protection / Exorcisme | C8: Masse+égide, marteau, sceptre sacré, bouclier runique | D8: Masse d'armes, sceptre sacré | E8: Bâton rituel, arbalète légère | F8: Sagesse; Force optionnelle | G8: Protection/soins/contre morts-vivants
A9: Alchimiste | B9: Grenadier / Apothicaire / Transmutateur | C9: Arbalète légère, dards, couteau, focus secondaire | D9: Sarbacane, arbalète légère, hachette | E9: Dague de jet, bâton rituel | F9: Dextérité; Intelligence | G9: Huiles/poisons/bombes/recettes

Sheet Améliorations
A1: Forge · Alchimie · Runes
A2: Règle ARM-001 : aucune recette ne modifie ItemLevel. Les améliorations changent uniquement les propriétés/bonus d'une instance.
A3: Code | B3: Discipline | C3: Recette | D3: Durée | E3: Effet | F3: Cibles | G3: Ingrédients conceptuels | H3: Palier | I3: Limites / exclusions | J3: Compatibilité runtime
A4: FOR01 | B4: Forge | C4: Affûtage de lame | D4: Permanent | E4: +1 précision (une seule fois) | F4: Lame tranchante/perforante | G4: Pierre d'aiguisage + fer | H4: N1+ | I4: 1 modification d'affûtage par arme | J4: Ne change pas Min/Max
A5: FOR02 | B5: Forge | C5: Trempe simple | D5: Permanent | E5: +1 dégâts plats (sans changement de niveau) | F5: Armes métalliques | G5: Minerai de fer + charbon + essence de forge | H5: N1+ | I5: Non cumulable ; remplacée par Trempe supérieure | J5: Ajoute +1 au FlatDamageBonus effectif
A6: FOR03 | B6: Forge | C6: Trempe supérieure | D6: Permanent | E6: +2 dégâts plats ; remplace Trempe simple | F6: Armes métalliques | G6: Acier raffiné + cœur incandescent | H6: N8+ | I6: Une seule trempe active par objet | J6: Ajoute +2 au FlatDamageBonus, pas de level-up
A7: FOR04 | B7: Forge | C7: Renforcement d'écu | D7: Permanent | E7: +5% armure physique | F7: Boucliers | G7: Rivets + plaque acier | H7: N3+ | I7: Un seul renforcement | J7: Sur protection finale de l'écu
A8: FOR05 | B8: Forge | C8: Bordure runique | D8: Permanent | E8: Ajoute 1 chasse dans limite de rareté | F8: Rare/Épique/Légendaire uniquement | G8: Poudre de rune + métal lunaire | H8: N8+ | I8: Max 1/1/2 chasses selon rareté | J8: Pas de chasses supplémentaires sur Commun
A9: FOR06 | B9: Forge | C9: Rééquilibrage d'arme | D9: Permanent | E9: +1 précision / -5% dégâts théoriques | F9: Armes lourdes | G9: Contrepoids + lingot | H9: N5+ | I9: Exclusif de garde renforcée | J9: Choix, pas bonus gratuit
A10: ALC01 | B10: Alchimie | C10: Huile d'affûtage | D10: Temporaire | E10: +5% dégâts tranchants | F10: Armes tranchantes | G10: Huile claire + pierre pilée | H10: N1+ | I10: 3 combats ou 10 coups réussis | J10: Une huile active par arme
A11: ALC02 | B11: Alchimie | C11: Huile perforante | D11: Temporaire | E11: +5% dégâts perforants | F11: Armes perforantes | G11: Huile claire + épine de fer | H11: N3+ | I11: 3 combats ou 10 coups réussis | J11: Une huile active par arme
A12: ALC03 | B12: Alchimie | C12: Pâte de percussion | D12: Temporaire | E12: +5% dégâts contondants | F12: Armes contondantes | G12: Graisse + poudre de quartz | H12: N3+ | I12: 3 combats ou 10 coups réussis | J12: Une huile active par arme
A13: ALC04 | B13: Alchimie | C13: Poison de lame | D13: Temporaire | E13: Chance limitée d'appliquer Poison | F13: Lames/dards | G13: Venin + distillat végétal | H13: N2+ | I13: 3 combats ou 10 coups réussis | J13: Passe par statuts et ArmorGate existants
A14: ALC05 | B14: Alchimie | C14: Résine incendiaire | D14: Temporaire | E14: Dégâts de Feu additionnels faibles | F14: Arme compatible | G14: Résine + soufre | H14: N5+ | I14: 3 combats ou 10 coups réussis | J14: Ne change pas le DamageType principal
... A24: FOR07 | B24: Forge | C24: Reforge d'artefact unique | D24: Permanent | E24: Effet spécifique prédéfini ; niveau inchangé | F24: Unique scénarisé | G24: Fragment de relique + métal ancien | H24: N12+ | I24: Un effet de reforge par artefact, défini à l'authoring | J24: Ne modifie pas ItemLevel ni l'identité Unique

Sheet Uniques
A1: Douze objets uniques nommés
A2: Concepts narratifs : propriétés fixes, non tirées aléatoirement. Les statuts et dégâts doivent réutiliser le moteur de combat.
A3: ID | B3: Nom propre | C3: Archétype de base | D3: Niveau natif | E3: Classe signature | F3: Identité | G3: Pouvoir spécifique proposé | H3: Acquisition | I3: Chasses proposées
A4: UNI001 | B4: Lame des Veilleurs | C4: Épée droite | D4: 5 | E4: Guerrier | F4: Rarement portée par les sentinelles | G4: Sur parade réussie, bonus de garde pour 1 tour | H4: Bastion oublié | I4: 1
A5: UNI002 | B5: Brise-Sceau | C5: Marteau à deux mains | D5: 11 | E5: Guerrier | F5: Perce les anciennes protections | G5: Bonus contre armure physique (effect séparé) | H5: Boss du gardien | I5: 0
A6: UNI003 | B6: Murmure des Ombres | C6: Poignard d'assassin | D6: 7 | E6: Voleur | F6: Lame silencieuse | G6: Premier coup depuis Caché : chance de saignement | H6: Crypte du voleur | I6: 1
A7: UNI004 | B7: Dernier Mot | C7: Main-gauche | D7: 12 | E7: Voleur | F7: Dague de contre-attaque | G7: Parade/riposte conditionnelle si talent actif | H7: Énigme des miroirs | I7: 0
A8: UNI005 | B8: Corde de l'Horizon | C8: Arc long | D8: 9 | E8: Rôdeur | F8: Arc de forêt ancienne | G8: Bonus de précision au-delà de 3 cases | H8: Autel des pisteurs | I8: 1
A9: UNI006 | B9: Serre de la Chasse | C9: Javelot | D9: 14 | E9: Rôdeur | F9: Javelot des grands chasseurs | G9: Bonus contre ennemi juré | H9: Chasse légendaire | I9: 1
A10: UNI007 | B10: Cendre-Mémoire | C10: Bâton élémentaire | D10: 10 | E10: Mage | F10: Bâton à rune instable | G10: Un seul élément d'affinité choisi de façon persistante | H10: Bibliothèque scellée | I10: 1
A11: UNI008 | B11: Œil d'Azur | C11: Orbe arcanique | D11: 16 | E11: Mage | F11: Orbe de concentration | G11: Bonus de mana et contrôle des surfaces | H11: Sanctuaire arcanique | I11: 0
A12: UNI009 | B12: Aube Silencieuse | C12: Sceptre sacré | D12: 12 | E12: Prêtre | F12: Reliquaire des exorcistes | G12: Contre morts-vivants : effet Holy conditionnel | H12: Temple enfoui | I12: 1
A13: UNI010 | B13: Rempart des Justes | C13: Égide sacrée | D13: 17 | E13: Prêtre | F13: Bouclier votif | G13: Bonus de résistance sacrée au groupe (talent requis) | H13: Boss du temple | I13: 1
A14: UNI011 | B14: Catalyseur d'Argent | C14: Arbalète légère | D14: 8 | E14: Alchimiste | F14: Arbalète alchimique | G14: Effet temporaire amplifié des huiles appliquées | H14: Laboratoire secret | I14: 1
A15: UNI012 | B15: L'Alambic Gris | C15: Grimoire focaliseur | D15: 15 | E15: Alchimiste | F15: Carnet de transmutation | G15: Bonus à certaines recettes, sans attaque propre | H15: Quête du maître alchimiste | I15: 0

Sheet Paramètres
A1: ARMEMENT01 — Cibles d'équilibrage (dés fixes au butin)
A2: La courbe de progression sert à choisir les profils ; la formule de dés M:N:O est la source réelle des dégâts. Modifier k1/k2 ne change pas automatiquement les dés.
A3: Paramètre | B3: Valeur | C3: Rôle
A4: Croissance par niveau d'OBJET k1 | B4: 0.11 | C4: Coefficient par niveau
A5: Accélération par niveau d'OBJET k2 | B5: 0.016 | C5: Accélération modérée des dégâts
A6: Niveau maximum | B6: 20 | C6: Plafond de progression
A7: PA par personnage / tour | B7: 4 | C7: Autorité existante du projet, rappel
A8: Poids d'arme | B8: kg | C8: Poids catalogue conservé, ne dépend pas du niveau
A9: Attributs / rareté / qualité de forge | B9: Hors formule | C9: Affixes, précision et effets conditionnels restent séparés du WD.
A10: Malus de précision / niveau manquant | B10: 2 | C10: −2 précision par niveau d'objet au-dessus du porteur, plafond B13 (proposé)
A11: Perte de puissance / niveau manquant | B11: 0.1 | C11: −10% WD + protection pour chaque niveau manquant (proposé)
A12: Puissance et protection minimum | B12: 0.5 | C12: Plancher 50% (proposé)
A13: Malus de précision maximal | B13: 10 | C13: Malus plafonné à −10 (proposé)
A14: Écart maximum équipable (proposé) | B14: 3 | C14: Au-delà : équipement refusé, sous réserve de validation (anti-abus)
A15: Niveau d'objet fixe | B15: OUI | C15: Aucune forge/rune/huile ne modifie ItemLevel
A16: Dés autorisés | B16: d4, d6, d8, d10, d12, d20 | C16: Sommer NdM lancers indépendants + K; ne pas substituer RandRange(Min,Max).
A17: Rareté et dégâts | B17: Aucun multiplicateur automatique | C17: Les affixes/runes agissent via modificateurs et statuts identifiés.
A18: Source des dés | B18: Niveaux 1-20 : M/N/O | C18: Les colonnes Q/R/S montrent les cibles historiques (non autoritaires).
A19: Mode Dice (contrat ARMEMENT01.2) | B19: Opt-in non implémenté | C19: Activer explicitement uniquement sur une attaque convertie; les profils legacy restent uniformes.
A20: Nb de dés max proposé | B20: 32 | C20: Protection contre abus de données. Le catalogue v0.3 utilise au plus 6 dés.
A21: Bonus K inclus | B21: OUI | C21: Ne jamais dupliquer la constante des dés dans FlatDamageBonus ou SourceDamageBonus.
A22: Validation données | B22: Niveaux 1-20!T:V | C22: Vérifications calculées pour les 1640 profils.

Sheet Implémentation UE5
A1: Intégration Unreal Engine 5.5.4
A2: ARMEMENT01.2 — schéma multi-dés opt-in, sans modification du moteur UE5 dans ce jalon.
A3: Statut | B3: Point d'extension | C3: Contrat | D3: Décision d'architecture
A4: Existant confirmé | B4: FGridAttackDefinition | C4: MinDamage, MaxDamage, AccuracyBonus, DamageType, PhysicalSubtype | D4: Actuel uniforme inclusif ; dX multiples exigent une évolution.
A5: Existant confirmé | B5: FGridCombatRollTrace | C5: Kind=Die|Range, DiceCount, DiceSides, IndividualRolls, FinalValue | D5: À enrichir pour le K de la formule et conserver la présentation des jets legacy.
A6: Existant confirmé | B6: FGridOffensiveEquipmentProfile | C6: AttackDefinition, FlatDamageBonus, DamageScalingAttribute, RangeCells | D6: Permet de convertir les valeurs calculées en profils d'attaques.
A7: Existant confirmé | B7: FGridCombatWeaponAttackProfile | C7: WeaponDamagePercent, bUseEquippedWeapon, RequiredItemTags, bUseWeaponRange | D7: Les talents gardent autorité sur WD; pas de duplication.
A8: Existant confirmé | B8: FGridItemInstance | C8: RuntimeObjectId, ItemDefinitionId, Quantity, WorldTransform, équipement | D8: Ne contient pas encore à lui seul la rareté/forge/runes (constat sur en-tête consulté).
A9: Évolution proposée | B9: FGridItemInstance (SaveGame) | C9: ItemLevel (création seulement), Rarity, AffixIds, RuneIds, ForgeRank et enduit | D9: Séparer niveau IMMUTABLE de la finition ; sauvegarder instance
A10: Évolution proposée | B10: Authoring des versions de butin | C10: ArchetypeId + ItemLevel immuable -> profil NdM+K explicite | D10: La courbe k1/k2 sert à l'équilibrage seulement, jamais au tirage runtime.
A11: Évolution proposée | B11: Weapon stat resolver | C11: Lire niveau fixe + rareté + améliorations, calculer le profil sans mutation du niveau | D11: Même projection C++ pour combat, tooltip et examen
A12: À retirer lors de la migration ARMEMENT | B12: Conversion Min/Max en dé virtuel | C12: Interdite pour les nouvelles armes : d5/d7... non autorisés | D12: Conserver exclusivement comme représentation éventuelle des profils legacy étrangers au nouveau catalogue.
A13: Évolution proposée | B13: FGridWeaponLevelPenalty | C13: d = max(0, ItemLevel - CharacterLevel), malus précision et puissance/protection ; seuil max proposé d=3 | D13: −2 précision / niveau, −10% WD / niveau, blocage d>3 à valider
A14: Évolution proposée | B14: Crafting transaction service | C14: Consommation ingrédients, ForgeRank, runes et enduit ; ZERO changement ItemLevel | D14: Validation atomique et rollback en cas d'échec
A15: Tests nécessaires | B15: Grimrock.RPG.ARMEMENT01.* | C15: immutabilité, dés, sous-niveau, save/load, compatibilité WD et buffs | D15: Statut : à implémenter ; validation TD04.2 par logs
A16: Références dépôt | B16: URL
A17: C++ items | B17: https://github.com/PhilippeMartin1964/GrimrockPrototype/blob/master/Source/GrimrockPrototype/Public/Runtime/GridItemDefinitionAsset.h
A18: Inventaire | B18: https://github.com/PhilippeMartin1964/GrimrockPrototype/blob/master/Source/GrimrockPrototype/Public/Runtime/GridInventoryTypes.h
A19: Profils combats | B19: https://github.com/PhilippeMartin1964/GrimrockPrototype/blob/master/Source/GrimrockPrototype/Public/Runtime/Combat/GridCombatTypes.h
A20: RPG03.9.0 | B20: https://github.com/PhilippeMartin1964/GrimrockPrototype/blob/master/docs/Design/RPG03_9_0_WEAPON_BASED_TALENT_ATTACKS.md
A21: Sources inspirantes | B21: https://divinity.fandom.com/wiki/Original_Sin_2_Weapons
A22: Référence univers | B22: https://www.rpgsoluce.com/soluces/ps4/dos2/guides/uniques.htm
A23: Évolution proposée | B23: FGridCombatRollTrace / Format combat | C23: DiceCount, DiceSides, IndividualRolls, DiceFlatBonus, FinalValue | D23: Seule source de vérité ; formatter les dés réels, aucune relance UMG.
A24: Validation requise | B24: Compatibilité RPG03.9.0 | C24: WD reste basé sur une seule attaque équipée | D24: Pas de double bonus, pas de second resolver.
A25: ARMEMENT01.2 | B25: FGridDamageDiceProfile (proposé) | C25: bEnabled ; DiceCount ; DiceSides ; FlatBonus | D25: Profil opt-in dans FGridAttackDefinition, non destructif des Min/Max legacy.
A26: ARMEMENT01.2 | B26: FGridAttackDefinition::IsValid | C26: Si bEnabled : d4/d6/d8/d10/d12/d20 ; bornes recalculées | D26: Interdire incohérences entre profil canonique et bornes Min/Max exposées.
A27: ARMEMENT01.2 | B27: FGridCombatResolver::ResolveAttack | C27: Legacy inchangé si bEnabled=false ; sinon N vrais tirages indépendants | D27: Utiliser le FRandomStream fourni, sans un second RNG ou resolver.
A28: ARMEMENT01.2 | B28: ResolveAttackFromDiceRolls (proposé) | C28: Injection d'un d20 et TArray<int32> des résultats de dés | D28: Rendre les tests des vrais dés déterministes sans supprimer ResolveAttackFromRolls.
A29: ARMEMENT01.2 | B29: Ordre RNG et ratés | C29: d20 avant dégâts ; préserver les tirages legacy même sur raté | D29: Pour multi-dés, documenter consommation N tirages et masquer résolution en cas de raté.
A30: ARMEMENT01.2 | B30: FGridCombatRollTrace::DiceFlatBonus | C30: K séparé des dés et de SourceDamageBonus | D30: FinalValue = somme(IndividualRolls)+K ; chaque élément 1..DiceSides.
A31: ARMEMENT01.2 | B31: GridCombatEventFeedFormatter | C31: Préserver la branche Range ; Die multi avec K affiché | D31: Exemple : 2d8 (3 + 7) + 4 = 14 ; aucun d5 virtuel pour armes nouvelles.
A32: ARMEMENT01.2 | B32: RPG03.9.0, WeaponAttackProfile | C32: WD applique une seule fois le total jet+K+bonus plats+attributs | D32: L'algorithme critique/armure/résistance reste inchangé.
A33: ARMEMENT01.2 | B33: Monstres / sortilèges legacy | C33: Ne pas convertir implicitement les attaques Min/Max existantes | D33: Aucun changement de probabilités des ennemis avant une migration dédiée.
A34: ARMEMENT01.2 | B34: Invariants SaveGame | C34: ItemLevel, rareté et améliorations séparés (jalons ultérieurs) | D34: Ne jamais randomiser le profil à la restauration; RNG uniquement à l'attaque.
... A39: ARMEMENT01.2 | B39: Compatibilité éclairs/poisons | C39: Effets élémentaires futurs = jets séparés si explicitement spécifiés | D39: Le dé de la base ne devient pas une deuxième attaque.

Sheet Affixes
A1: Banque d'affixes — propositions
A2: Les affixes modifient préférences et tactique sans multiplier inutilement les dégâts. Proc = effet déclenché selon une condition.
A3: Code | B3: Nom | C3: Cible | D3: Effet recommandé | E3: Rare | F3: Épique | G3: Légendaire | H3: Limite d'équilibrage
A4: AFX01 | B4: Précis | C4: Arme | D4: + précision | E4: +1 | F4: +1 à +2 | G4: +2 | H4: ≤ +2 hors Unique
A5: AFX02 | B5: Féroce | C5: Arme | D5: + dégâts critiques | E5: — | F5: +5 % | G5: +10 % | H5: Ne pas augmenter les attaques de base
A6: AFX03 | B6: Affûté | C6: Tranchant | D6: + dégâts WD | E6: — | F6: +3 % | G6: +5 % | H6: Non cumulable avec autre affixe WD
A7: AFX04 | B7: Percuteur | C7: Contondant | D7: + dégâts sur armure physique | E7: — | F7: +4 % | G7: +6 % | H7: Pas de bypass armure
A8: AFX05 | B8: Perce-garde | C8: Perforant | D8: Bonus conditionnel cible protégée | E8: Effet mineur | F8: +5 % | G8: +7 % | H8: Dépend d'une cible valide
A9: AFX06 | B9: Équilibré | C9: Armes lourdes | D9: Réduction malus précision | E9: +1 | F9: +1 | G9: +2 | H9: Pas de réduction du coût PA
A10: AFX07 | B10: Robuste | C10: Bouclier | D10: + armure physique | E10: +3 % | F10: +5 % | G10: +8 % | H10: Bonus sur bouclier seulement
A11: AFX08 | B11: Réfléchissant | C11: Bouclier | D11: + résistance magique typée | E11: +2 % | F11: +4 % | G11: +6 % | H11: Résistance typée pas cumul générique
A12: AFX09 | B12: Vital | C12: Tout équipement | D12: + santé maximale | E12: +3 | F12: +6 | G12: +10 | H12: Ne soigne pas automatiquement
A13: AFX10 | B13: Savant | C13: Focaliseur | D13: + mana maximale | E13: +3 | F13: +6 | G13: +10 | H13: Ne régénère pas gratuitement
A14: AFX11 | B14: Exorciste | C14: Sacré | D14: Bonus contre morts-vivants | E14: Mineur | F14: Modéré | G14: Fort | H14: Tag de monstre exigé
... A21: AFX18 | B21: Econome | C21: Armes à charge / focus | D21: Réduction coût mana conditionnelle | E21: — | F21: Faible | G21: Modérée | H21: Jamais en dessous du plancher fixé

Sheet Pénalités de niveau
A1: ARMEMENT01 — Maniement d'un équipement trop élevé
A2: PROPOSITION À VALIDER — niveau d'objet toujours inchangé ; le malus disparaît quand le personnage gagne des niveaux.
A3: Scénario | B3: Niv. personnage | C3: Niv. objet | D3: Écart (obj-pers.) | E3: Précision | F3: Puissance arme | G3: Protection écu | H3: État
A4: Même niveau | B4: 4 | C4: 4 | D4: =MAX(0,C4-B4) -> 0 | E4: =IF(D4>Paramètres!$B$14,"—",-MIN(Paramètres!$B$13,D4*Paramètres!$B$10)) -> 0 | F4: =IF(D4>Paramètres!$B$14,"—",MAX(Paramètres!$B$12,1-D4*Paramètres!$B$11)) -> 1 | G4: =IF(D4>Paramètres!$B$14,"—",MAX(Paramètres!$B$12,1-D4*Paramètres!$B$11)) -> 1 | H4: =IF(D4>Paramètres!$B$14,"Non équipable (proposé)",IF(D4=0,"Aucun malus","Malus de niveau")) -> Aucun malus
A5: 1 niveau d'écart | B5: 4 | C5: 5 | D5: =MAX(0,C5-B5) -> 1 | E5: =IF(D5>Paramètres!$B$14,"—",-MIN(Paramètres!$B$13,D5*Paramètres!$B$10)) -> -2 | F5: =IF(D5>Paramètres!$B$14,"—",MAX(Paramètres!$B$12,1-D5*Paramètres!$B$11)) -> 0.9 | G5: =IF(D5>Paramètres!$B$14,"—",MAX(Paramètres!$B$12,1-D5*Paramètres!$B$11)) -> 0.9 | H5: =IF(D5>Paramètres!$B$14,"Non équipable (proposé)",IF(D5=0,"Aucun malus","Malus de niveau")) -> Malus de niveau
A6: Exemple demandé — N6 | B6: 4 | C6: 6 | D6: =MAX(0,C6-B6) -> 2 | E6: =IF(D6>Paramètres!$B$14,"—",-MIN(Paramètres!$B$13,D6*Paramètres!$B$10)) -> -4 | F6: =IF(D6>Paramètres!$B$14,"—",MAX(Paramètres!$B$12,1-D6*Paramètres!$B$11)) -> 0.8 | G6: =IF(D6>Paramètres!$B$14,"—",MAX(Paramètres!$B$12,1-D6*Paramètres!$B$11)) -> 0.8 | H6: =IF(D6>Paramètres!$B$14,"Non équipable (proposé)",IF(D6=0,"Aucun malus","Malus de niveau")) -> Malus de niveau
A7: Exemple demandé — N7 | B7: 4 | C7: 7 | D7: =MAX(0,C7-B7) -> 3 | E7: =IF(D7>Paramètres!$B$14,"—",-MIN(Paramètres!$B$13,D7*Paramètres!$B$10)) -> -6 | F7: =IF(D7>Paramètres!$B$14,"—",MAX(Paramètres!$B$12,1-D7*Paramètres!$B$11)) -> 0.7 | G7: =IF(D7>Paramètres!$B$14,"—",MAX(Paramètres!$B$12,1-D7*Paramètres!$B$11)) -> 0.7 | H7: =IF(D7>Paramètres!$B$14,"Non équipable (proposé)",IF(D7=0,"Aucun malus","Malus de niveau")) -> Malus de niveau
A8: Écart important | B8: 4 | C8: 9 | D8: =MAX(0,C8-B8) -> 5 | E8: =IF(D8>Paramètres!$B$14,"—",-MIN(Paramètres!$B$13,D8*Paramètres!$B$10)) -> — | F8: =IF(D8>Paramètres!$B$14,"—",MAX(Paramètres!$B$12,1-D8*Paramètres!$B$11)) -> — | G8: =IF(D8>Paramètres!$B$14,"—",MAX(Paramètres!$B$12,1-D8*Paramètres!$B$11)) -> — | H8: =IF(D8>Paramètres!$B$14,"Non équipable (proposé)",IF(D8=0,"Aucun malus","Malus de niveau")) -> Non équipable (proposé)
A9: Objet N20, personnage N4 | B9: 4 | C9: 20 | D9: =MAX(0,C9-B9) -> 16 | E9: =IF(D9>Paramètres!$B$14,"—",-MIN(Paramètres!$B$13,D9*Paramètres!$B$10)) -> — | F9: =IF(D9>Paramètres!$B$14,"—",MAX(Paramètres!$B$12,1-D9*Paramètres!$B$11)) -> — | G9: =IF(D9>Paramètres!$B$14,"—",MAX(Paramètres!$B$12,1-D9*Paramètres!$B$11)) -> — | H9: =IF(D9>Paramètres!$B$14,"Non équipable (proposé)",IF(D9=0,"Aucun malus","Malus de niveau")) -> Non équipable (proposé)
A10: Personnage devenu N7 | B10: 7 | C10: 7 | D10: =MAX(0,C10-B10) -> 0 | E10: =IF(D10>Paramètres!$B$14,"—",-MIN(Paramètres!$B$13,D10*Paramètres!$B$10)) -> 0 | F10: =IF(D10>Paramètres!$B$14,"—",MAX(Paramètres!$B$12,1-D10*Paramètres!$B$11)) -> 1 | G10: =IF(D10>Paramètres!$B$14,"—",MAX(Paramètres!$B$12,1-D10*Paramètres!$B$11)) -> 1 | H10: =IF(D10>Paramètres!$B$14,"Non équipable (proposé)",IF(D10=0,"Aucun malus","Malus de niveau")) -> Aucun malus
A12: Exemple de dague N7 (4–9 = 1d6 + 3) tenue par personnage N4 : −6 précision ; 70% WD après jet.
A13: Jet 6 → 4 après facteur 70%, avant autres modificateurs ; le dé 1d6 + 3 et le niveau 7 restent INCHANGÉS.
A15: Écart maximal proposé = 3 ; un équipement N9 pour personnage N4 est marqué non équipable (anti-abus à valider).

Sheet Contrat synthèse
A1: ARMEMENT01 — v0.3 + contrat technique ARMEMENT01.2 (sans changement des règles de design)
A2: Statut : contrat proposé, pas encore accepté ni implémenté dans le dépôt Unreal.
A4: ID | B4: Règle | C4: Illustration | D4: Conséquence technique
A5: ARM-001 | B5: ItemLevel fixe et immuable (1–20) | C5: Une épée N7 demeure N7 après une trempe. | D5: ItemLevel sauvegardé, sans évolution par recette.
A6: ARM-002 | B6: Uniquement les d4, d6, d8, d10, d12, d20 pour dégâts | C6: Pas de d5 ni de d15. | D6: Validation des faces autorisées.
A7: ARM-003 | B7: Jet réel : N dés indépendants + K | C7: 2d8 + 4 ; deux tirages, somme puis +4. | D7: Résolveur multi-dés et traces de tirage.
A8: ARM-004 | B8: Min = N + K ; Max = N*M + K | C8: 2d8+4 => 6–20 ; moyenne 13. | D8: Min/Max dérivés, pas une autorité de hasard.
A9: ARM-005 | B9: Une expression multi-dés n'est PAS uniforme | C9: 2d8+4 : 13 plus fréquent que 6. | D9: Ne pas utiliser RandRange(6,20).
A10: ARM-006 | B10: Niveau du porteur insuffisant : pénalités (proposées) | C10: N4 + arme N7 : −6 précision, WD ×0,70. | D10: Tests de maîtrise, pas de mutation de l'objet.
A11: ARM-007 | B11: Écart maximum équipable 3 (à valider) | C11: N4 + arme N9 : refus proposé. | D11: Doit être expressément validé.
A12: ARM-008 | B12: Pas de tirage de dégâts passif pour les boucliers | C12: Protection fixe sans dés. | D12: ShieldBash = action offensive séparée.
A13: ARM-009 | B13: Rareté : gris/vert/bleu/violet/doré | C13: Commun, Rare, Épique, Légendaire, Unique. | D13: UMG = présentation, rareté indépend. du niveau.
A14: ARM-010 | B14: Pas de WD multiplié automatiquement par la rareté | C14: Épique = affixes, pas +8% implicite. | D14: Affixes et runes sont explicites.
A15: ARM-011 | B15: Forge, alchimie et runes sans level-up | C15: Trempe +2 dégâts plats, ItemLevel inchangé. | D15: Bonus séparés de K initial, une application.
... A18: ARM-014 | B18: Source profil fixe par instance, non recalculée | C18: Une arme N7 conserve son NdM+K au chargement. | D18: Profil sauvegardé/restauré sans reroll.
A19: Contrats détaillés : ARMEMENT01_Contrat_Armement_v0_3.md + ARMEMENT01_2_CONTRAT_TECHNIQUE_MULTIDES.md.
A20: ARM2-01 | B20: Compatibilité explicite | C20: Mode Legacy=Min..Max uniforme; mode Dice=NdM+K. | D20: Pas de conversion automatique du mode legacy.
A21: ARM2-02 | B21: Bornes dérivées | C21: Min = N+K, Max=N*M+K. | D21: Valider lors de l'authoring et runtime.
A22: ARM2-03 | B22: Résolution RNG unique | C22: 2d8+4, tirages 3 et 7, résultat 14. | D22: FRandomStream; une seule attaque, aucun tirage UI.
A23: ARM2-04 | B23: Traces complètes | C23: Kind=Die, IndividualRolls=[3,7], K=4, Total=14. | D23: Étendre trace avec DiceFlatBonus.
A24: ARM2-05 | B24: Régression obligatoire | C24: D20 de toucher, WD talents, critiques, monstres legacy. | D24: Ne pas casser le moteur existant.
A25: ARM2-06 | B25: Pénalités de niveau toujours proposées | C25: N4 vs N6/N7, règles à valider séparément. | D25: Ne pas implémenter dans ARMEMENT01.2.
A26: ARM2-07 | B26: Structure du classeur préservée | C26: 12 onglets historiques, aucune suppression. | D26: Colonnes T:V de validation supplémentaires.

Sheet Narratif
A1: ArchetypeId | B1: DescriptionCourteFR | C1: LoreFR | D1: ParticulariteFR | E1: EtatParticularite | F1: NotesConception | G1: EtatValidation
A2: ARM001 | E2: UNDOCUMENTED | G2: DRAFT
A3: ARM002 | E3: UNDOCUMENTED | G3: DRAFT
A4: ARM003 | E4: UNDOCUMENTED | G4: DRAFT
A5: ARM004 | E5: UNDOCUMENTED | G5: DRAFT
A6: ARM005 | E6: UNDOCUMENTED | G6: DRAFT
A7: ARM006 | E7: UNDOCUMENTED | G7: DRAFT
A8: ARM007 | E8: UNDOCUMENTED | G8: DRAFT
A9: ARM008 | E9: UNDOCUMENTED | G9: DRAFT
A10: ARM009 | E10: UNDOCUMENTED | G10: DRAFT
A11: ARM010 | E11: UNDOCUMENTED | G11: DRAFT
A12: ARM011 | E12: UNDOCUMENTED | G12: DRAFT
A13: ARM012 | E13: UNDOCUMENTED | G13: DRAFT
... A83: ARM082 | E83: UNDOCUMENTED | G83: DRAFT
